service_models.cpython-39.pyc (Python 3.9)
[Code]
    File Name: /Users/s/openclaw-memory-auto/integration_hooks/service_models.py
    Object Name: <module>
    Arg Count: 0
    Pos Only Arg Count: 0
    KW Only Arg Count: 0
    Locals: 0
    Stack Size: 4
    Flags: 0x01000040 (CO_NOFREE | CO_FUTURE_ANNOTATIONS)
    [Names]
        '__future__'
        'annotations'
        'dataclasses'
        'asdict'
        'dataclass'
        'field'
        'datetime'
        'timezone'
        'typing'
        'Any'
        'Dict'
        'List'
        'Optional'
        'CapabilityManifest'
        'MemoryCandidate'
        'ConnectResult'
    [Var Names]
    [Free Vars]
    [Cell Vars]
    [Constants]
        0
        (
            'annotations'
        )
        (
            'asdict'
            'dataclass'
            'field'
        )
        (
            'datetime'
            'timezone'
        )
        (
            'Any'
            'Dict'
            'List'
            'Optional'
        )
        [Code]
            File Name: /Users/s/openclaw-memory-auto/integration_hooks/service_models.py
            Object Name: CapabilityManifest
            Arg Count: 0
            Pos Only Arg Count: 0
            KW Only Arg Count: 0
            Locals: 0
            Stack Size: 3
            Flags: 0x01000040 (CO_NOFREE | CO_FUTURE_ANNOTATIONS)
            [Names]
                '__name__'
                '__module__'
                '__qualname__'
                'field'
                'list'
                'capabilities'
                '__annotations__'
                'transport'
                'detected_path'
                'config_file'
                'trusted'
                'to_dict'
            [Var Names]
            [Free Vars]
            [Cell Vars]
            [Constants]
                'CapabilityManifest'
                (
                    'default_factory'
                )
                'List[str]'
                'capabilities'
                'stdio'
                'str'
                'transport'
                ''
                'detected_path'
                'config_file'
                False
                'bool'
                'trusted'
                'Dict[str, Any]'
                (
                    'return'
                )
                [Code]
                    File Name: /Users/s/openclaw-memory-auto/integration_hooks/service_models.py
                    Object Name: to_dict
                    Arg Count: 1
                    Pos Only Arg Count: 0
                    KW Only Arg Count: 0
                    Locals: 1
                    Stack Size: 2
                    Flags: 0x01000043 (CO_OPTIMIZED | CO_NEWLOCALS | CO_NOFREE | CO_FUTURE_ANNOTATIONS)
                    [Names]
                        'asdict'
                    [Var Names]
                        'self'
                    [Free Vars]
                    [Cell Vars]
                    [Constants]
                        None
                    [Disassembly]
                        0       LOAD_GLOBAL                     0: asdict
                        2       LOAD_FAST                       0: self
                        4       CALL_FUNCTION                   1
                        6       RETURN_VALUE                    
                'CapabilityManifest.to_dict'
                None
            [Disassembly]
                0       LOAD_NAME                       0: __name__
                2       STORE_NAME                      1: __module__
                4       LOAD_CONST                      0: 'CapabilityManifest'
                6       STORE_NAME                      2: __qualname__
                8       SETUP_ANNOTATIONS               
                10      LOAD_NAME                       3: field
                12      LOAD_NAME                       4: list
                14      LOAD_CONST                      1: ('default_factory',)
                16      CALL_FUNCTION_KW                1
                18      STORE_NAME                      5: capabilities
                20      LOAD_CONST                      2: 'List[str]'
                22      LOAD_NAME                       6: __annotations__
                24      LOAD_CONST                      3: 'capabilities'
                26      STORE_SUBSCR                    
                28      LOAD_CONST                      4: 'stdio'
                30      STORE_NAME                      7: transport
                32      LOAD_CONST                      5: 'str'
                34      LOAD_NAME                       6: __annotations__
                36      LOAD_CONST                      6: 'transport'
                38      STORE_SUBSCR                    
                40      LOAD_CONST                      7: ''
                42      STORE_NAME                      8: detected_path
                44      LOAD_CONST                      5: 'str'
                46      LOAD_NAME                       6: __annotations__
                48      LOAD_CONST                      8: 'detected_path'
                50      STORE_SUBSCR                    
                52      LOAD_CONST                      7: ''
                54      STORE_NAME                      9: config_file
                56      LOAD_CONST                      5: 'str'
                58      LOAD_NAME                       6: __annotations__
                60      LOAD_CONST                      9: 'config_file'
                62      STORE_SUBSCR                    
                64      LOAD_CONST                      10: False
                66      STORE_NAME                      10: trusted
                68      LOAD_CONST                      11: 'bool'
                70      LOAD_NAME                       6: __annotations__
                72      LOAD_CONST                      12: 'trusted'
                74      STORE_SUBSCR                    
                76      LOAD_CONST                      13: 'Dict[str, Any]'
                78      LOAD_CONST                      14: ('return',)
                80      BUILD_CONST_KEY_MAP             1
                82      LOAD_CONST                      15: <CODE> to_dict
                84      LOAD_CONST                      16: 'CapabilityManifest.to_dict'
                86      MAKE_FUNCTION                   4
                88      STORE_NAME                      11: to_dict
                90      LOAD_CONST                      17: None
                92      RETURN_VALUE                    
        'CapabilityManifest'
        [Code]
            File Name: /Users/s/openclaw-memory-auto/integration_hooks/service_models.py
            Object Name: MemoryCandidate
            Arg Count: 0
            Pos Only Arg Count: 0
            KW Only Arg Count: 0
            Locals: 0
            Stack Size: 3
            Flags: 0x01000040 (CO_NOFREE | CO_FUTURE_ANNOTATIONS)
            [Names]
                '__name__'
                '__module__'
                '__qualname__'
                '__annotations__'
                'field'
                'dict'
                'metadata'
                'kind'
                'confidence'
                'llm_summary'
                'to_dict'
            [Var Names]
            [Free Vars]
            [Cell Vars]
            [Constants]
                'MemoryCandidate'
                'str'
                'source'
                'content'
                (
                    'default_factory'
                )
                'Dict[str, Any]'
                'metadata'
                'interaction_memory'
                'kind'
                None
                'Optional[float]'
                'confidence'
                ''
                'llm_summary'
                (
                    'return'
                )
                [Code]
                    File Name: /Users/s/openclaw-memory-auto/integration_hooks/service_models.py
                    Object Name: to_dict
                    Arg Count: 1
                    Pos Only Arg Count: 0
                    KW Only Arg Count: 0
                    Locals: 1
                    Stack Size: 2
                    Flags: 0x01000043 (CO_OPTIMIZED | CO_NEWLOCALS | CO_NOFREE | CO_FUTURE_ANNOTATIONS)
                    [Names]
                        'asdict'
                    [Var Names]
                        'self'
                    [Free Vars]
                    [Cell Vars]
                    [Constants]
                        None
                    [Disassembly]
                        0       LOAD_GLOBAL                     0: asdict
                        2       LOAD_FAST                       0: self
                        4       CALL_FUNCTION                   1
                        6       RETURN_VALUE                    
                'MemoryCandidate.to_dict'
            [Disassembly]
                0       LOAD_NAME                       0: __name__
                2       STORE_NAME                      1: __module__
                4       LOAD_CONST                      0: 'MemoryCandidate'
                6       STORE_NAME                      2: __qualname__
                8       SETUP_ANNOTATIONS               
                10      LOAD_CONST                      1: 'str'
                12      LOAD_NAME                       3: __annotations__
                14      LOAD_CONST                      2: 'source'
                16      STORE_SUBSCR                    
                18      LOAD_CONST                      1: 'str'
                20      LOAD_NAME                       3: __annotations__
                22      LOAD_CONST                      3: 'content'
                24      STORE_SUBSCR                    
                26      LOAD_NAME                       4: field
                28      LOAD_NAME                       5: dict
                30      LOAD_CONST                      4: ('default_factory',)
                32      CALL_FUNCTION_KW                1
                34      STORE_NAME                      6: metadata
                36      LOAD_CONST                      5: 'Dict[str, Any]'
                38      LOAD_NAME                       3: __annotations__
                40      LOAD_CONST                      6: 'metadata'
                42      STORE_SUBSCR                    
                44      LOAD_CONST                      7: 'interaction_memory'
                46      STORE_NAME                      7: kind
                48      LOAD_CONST                      1: 'str'
                50      LOAD_NAME                       3: __annotations__
                52      LOAD_CONST                      8: 'kind'
                54      STORE_SUBSCR                    
                56      LOAD_CONST                      9: None
                58      STORE_NAME                      8: confidence
                60      LOAD_CONST                      10: 'Optional[float]'
                62      LOAD_NAME                       3: __annotations__
                64      LOAD_CONST                      11: 'confidence'
                66      STORE_SUBSCR                    
                68      LOAD_CONST                      12: ''
                70      STORE_NAME                      9: llm_summary
                72      LOAD_CONST                      1: 'str'
                74      LOAD_NAME                       3: __annotations__
                76      LOAD_CONST                      13: 'llm_summary'
                78      STORE_SUBSCR                    
                80      LOAD_CONST                      5: 'Dict[str, Any]'
                82      LOAD_CONST                      14: ('return',)
                84      BUILD_CONST_KEY_MAP             1
                86      LOAD_CONST                      15: <CODE> to_dict
                88      LOAD_CONST                      16: 'MemoryCandidate.to_dict'
                90      MAKE_FUNCTION                   4
                92      STORE_NAME                      10: to_dict
                94      LOAD_CONST                      9: None
                96      RETURN_VALUE                    
        'MemoryCandidate'
        [Code]
            File Name: /Users/s/openclaw-memory-auto/integration_hooks/service_models.py
            Object Name: ConnectResult
            Arg Count: 0
            Pos Only Arg Count: 0
            KW Only Arg Count: 0
            Locals: 0
            Stack Size: 3
            Flags: 0x01000040 (CO_NOFREE | CO_FUTURE_ANNOTATIONS)
            [Names]
                '__name__'
                '__module__'
                '__qualname__'
                '__annotations__'
                'field'
                'list'
                'detected_targets'
                'verify_ok'
                'smoke_ok'
                'doctor_ok'
                'rolled_back'
                'strict'
                'started_at'
                'finished_at'
                'dict'
                'details'
                'to_dict'
            [Var Names]
            [Free Vars]
            [Cell Vars]
            [Constants]
                'ConnectResult'
                'str'
                'status'
                (
                    'default_factory'
                )
                'List[str]'
                'detected_targets'
                False
                'bool'
                'verify_ok'
                'smoke_ok'
                'doctor_ok'
                'rolled_back'
                'strict'
                [Code]
                    File Name: /Users/s/openclaw-memory-auto/integration_hooks/service_models.py
                    Object Name: <lambda>
                    Arg Count: 0
                    Pos Only Arg Count: 0
                    KW Only Arg Count: 0
                    Locals: 0
                    Stack Size: 3
                    Flags: 0x01000043 (CO_OPTIMIZED | CO_NEWLOCALS | CO_NOFREE | CO_FUTURE_ANNOTATIONS)
                    [Names]
                        'datetime'
                        'now'
                        'timezone'
                        'utc'
                        'isoformat'
                    [Var Names]
                    [Free Vars]
                    [Cell Vars]
                    [Constants]
                        None
                    [Disassembly]
                        0       LOAD_GLOBAL                     0: datetime
                        2       LOAD_METHOD                     1: now
                        4       LOAD_GLOBAL                     2: timezone
                        6       LOAD_ATTR                       3: utc
                        8       CALL_METHOD                     1
                        10      LOAD_METHOD                     4: isoformat
                        12      CALL_METHOD                     0
                        14      RETURN_VALUE                    
                'ConnectResult.<lambda>'
                'started_at'
                ''
                'finished_at'
                'Dict[str, Any]'
                'details'
                (
                    'return'
                )
                [Code]
                    File Name: /Users/s/openclaw-memory-auto/integration_hooks/service_models.py
                    Object Name: to_dict
                    Arg Count: 1
                    Pos Only Arg Count: 0
                    KW Only Arg Count: 0
                    Locals: 2
                    Stack Size: 3
                    Flags: 0x01000043 (CO_OPTIMIZED | CO_NEWLOCALS | CO_NOFREE | CO_FUTURE_ANNOTATIONS)
                    [Names]
                        'asdict'
                        'get'
                        'datetime'
                        'now'
                        'timezone'
                        'utc'
                        'isoformat'
                    [Var Names]
                        'self'
                        'payload'
                    [Free Vars]
                    [Cell Vars]
                    [Constants]
                        None
                        'finished_at'
                    [Disassembly]
                        0       LOAD_GLOBAL                     0: asdict
                        2       LOAD_FAST                       0: self
                        4       CALL_FUNCTION                   1
                        6       STORE_FAST                      1: payload
                        8       LOAD_FAST                       1: payload
                        10      LOAD_METHOD                     1: get
                        12      LOAD_CONST                      1: 'finished_at'
                        14      CALL_METHOD                     1
                        16      POP_JUMP_IF_TRUE                38
                        18      LOAD_GLOBAL                     2: datetime
                        20      LOAD_METHOD                     3: now
                        22      LOAD_GLOBAL                     4: timezone
                        24      LOAD_ATTR                       5: utc
                        26      CALL_METHOD                     1
                        28      LOAD_METHOD                     6: isoformat
                        30      CALL_METHOD                     0
                        32      LOAD_FAST                       1: payload
                        34      LOAD_CONST                      1: 'finished_at'
                        36      STORE_SUBSCR                    
                        38      LOAD_FAST                       1: payload
                        40      RETURN_VALUE                    
                'ConnectResult.to_dict'
                None
            [Disassembly]
                0       LOAD_NAME                       0: __name__
                2       STORE_NAME                      1: __module__
                4       LOAD_CONST                      0: 'ConnectResult'
                6       STORE_NAME                      2: __qualname__
                8       SETUP_ANNOTATIONS               
                10      LOAD_CONST                      1: 'str'
                12      LOAD_NAME                       3: __annotations__
                14      LOAD_CONST                      2: 'status'
                16      STORE_SUBSCR                    
                18      LOAD_NAME                       4: field
                20      LOAD_NAME                       5: list
                22      LOAD_CONST                      3: ('default_factory',)
                24      CALL_FUNCTION_KW                1
                26      STORE_NAME                      6: detected_targets
                28      LOAD_CONST                      4: 'List[str]'
                30      LOAD_NAME                       3: __annotations__
                32      LOAD_CONST                      5: 'detected_targets'
                34      STORE_SUBSCR                    
                36      LOAD_CONST                      6: False
                38      STORE_NAME                      7: verify_ok
                40      LOAD_CONST                      7: 'bool'
                42      LOAD_NAME                       3: __annotations__
                44      LOAD_CONST                      8: 'verify_ok'
                46      STORE_SUBSCR                    
                48      LOAD_CONST                      6: False
                50      STORE_NAME                      8: smoke_ok
                52      LOAD_CONST                      7: 'bool'
                54      LOAD_NAME                       3: __annotations__
                56      LOAD_CONST                      9: 'smoke_ok'
                58      STORE_SUBSCR                    
                60      LOAD_CONST                      6: False
                62      STORE_NAME                      9: doctor_ok
                64      LOAD_CONST                      7: 'bool'
                66      LOAD_NAME                       3: __annotations__
                68      LOAD_CONST                      10: 'doctor_ok'
                70      STORE_SUBSCR                    
                72      LOAD_CONST                      6: False
                74      STORE_NAME                      10: rolled_back
                76      LOAD_CONST                      7: 'bool'
                78      LOAD_NAME                       3: __annotations__
                80      LOAD_CONST                      11: 'rolled_back'
                82      STORE_SUBSCR                    
                84      LOAD_CONST                      6: False
                86      STORE_NAME                      11: strict
                88      LOAD_CONST                      7: 'bool'
                90      LOAD_NAME                       3: __annotations__
                92      LOAD_CONST                      12: 'strict'
                94      STORE_SUBSCR                    
                96      LOAD_NAME                       4: field
                98      LOAD_CONST                      13: <CODE> <lambda>
                100     LOAD_CONST                      14: 'ConnectResult.<lambda>'
                102     MAKE_FUNCTION                   0
                104     LOAD_CONST                      3: ('default_factory',)
                106     CALL_FUNCTION_KW                1
                108     STORE_NAME                      12: started_at
                110     LOAD_CONST                      1: 'str'
                112     LOAD_NAME                       3: __annotations__
                114     LOAD_CONST                      15: 'started_at'
                116     STORE_SUBSCR                    
                118     LOAD_CONST                      16: ''
                120     STORE_NAME                      13: finished_at
                122     LOAD_CONST                      1: 'str'
                124     LOAD_NAME                       3: __annotations__
                126     LOAD_CONST                      17: 'finished_at'
                128     STORE_SUBSCR                    
                130     LOAD_NAME                       4: field
                132     LOAD_NAME                       14: dict
                134     LOAD_CONST                      3: ('default_factory',)
                136     CALL_FUNCTION_KW                1
                138     STORE_NAME                      15: details
                140     LOAD_CONST                      18: 'Dict[str, Any]'
                142     LOAD_NAME                       3: __annotations__
                144     LOAD_CONST                      19: 'details'
                146     STORE_SUBSCR                    
                148     LOAD_CONST                      18: 'Dict[str, Any]'
                150     LOAD_CONST                      20: ('return',)
                152     BUILD_CONST_KEY_MAP             1
                154     LOAD_CONST                      21: <CODE> to_dict
                156     LOAD_CONST                      22: 'ConnectResult.to_dict'
                158     MAKE_FUNCTION                   4
                160     STORE_NAME                      16: to_dict
                162     LOAD_CONST                      23: None
                164     RETURN_VALUE                    
        'ConnectResult'
        None
    [Disassembly]
        0       LOAD_CONST                      0: 0
        2       LOAD_CONST                      1: ('annotations',)
        4       IMPORT_NAME                     0: __future__
        6       IMPORT_FROM                     1: annotations
        8       STORE_NAME                      1: annotations
        10      POP_TOP                         
        12      LOAD_CONST                      0: 0
        14      LOAD_CONST                      2: ('asdict', 'dataclass', 'field')
        16      IMPORT_NAME                     2: dataclasses
        18      IMPORT_FROM                     3: asdict
        20      STORE_NAME                      3: asdict
        22      IMPORT_FROM                     4: dataclass
        24      STORE_NAME                      4: dataclass
        26      IMPORT_FROM                     5: field
        28      STORE_NAME                      5: field
        30      POP_TOP                         
        32      LOAD_CONST                      0: 0
        34      LOAD_CONST                      3: ('datetime', 'timezone')
        36      IMPORT_NAME                     6: datetime
        38      IMPORT_FROM                     6: datetime
        40      STORE_NAME                      6: datetime
        42      IMPORT_FROM                     7: timezone
        44      STORE_NAME                      7: timezone
        46      POP_TOP                         
        48      LOAD_CONST                      0: 0
        50      LOAD_CONST                      4: ('Any', 'Dict', 'List', 'Optional')
        52      IMPORT_NAME                     8: typing
        54      IMPORT_FROM                     9: Any
        56      STORE_NAME                      9: Any
        58      IMPORT_FROM                     10: Dict
        60      STORE_NAME                      10: Dict
        62      IMPORT_FROM                     11: List
        64      STORE_NAME                      11: List
        66      IMPORT_FROM                     12: Optional
        68      STORE_NAME                      12: Optional
        70      POP_TOP                         
        72      LOAD_NAME                       4: dataclass
        74      LOAD_BUILD_CLASS                
        76      LOAD_CONST                      5: <CODE> CapabilityManifest
        78      LOAD_CONST                      6: 'CapabilityManifest'
        80      MAKE_FUNCTION                   0
        82      LOAD_CONST                      6: 'CapabilityManifest'
        84      CALL_FUNCTION                   2
        86      CALL_FUNCTION                   1
        88      STORE_NAME                      13: CapabilityManifest
        90      LOAD_NAME                       4: dataclass
        92      LOAD_BUILD_CLASS                
        94      LOAD_CONST                      7: <CODE> MemoryCandidate
        96      LOAD_CONST                      8: 'MemoryCandidate'
        98      MAKE_FUNCTION                   0
        100     LOAD_CONST                      8: 'MemoryCandidate'
        102     CALL_FUNCTION                   2
        104     CALL_FUNCTION                   1
        106     STORE_NAME                      14: MemoryCandidate
        108     LOAD_NAME                       4: dataclass
        110     LOAD_BUILD_CLASS                
        112     LOAD_CONST                      9: <CODE> ConnectResult
        114     LOAD_CONST                      10: 'ConnectResult'
        116     MAKE_FUNCTION                   0
        118     LOAD_CONST                      10: 'ConnectResult'
        120     CALL_FUNCTION                   2
        122     CALL_FUNCTION                   1
        124     STORE_NAME                      15: ConnectResult
        126     LOAD_CONST                      11: None
        128     RETURN_VALUE                    
