__init__.cpython-39.pyc (Python 3.9)
[Code]
    File Name: /Users/s/openclaw-memory-auto/adapter_registry/__init__.py
    Object Name: <module>
    Arg Count: 0
    Pos Only Arg Count: 0
    KW Only Arg Count: 0
    Locals: 0
    Stack Size: 2
    Flags: 0x00000040 (CO_NOFREE)
    [Names]
        'registry'
        'AdapterRegistry'
    [Var Names]
    [Free Vars]
    [Cell Vars]
    [Constants]
        1
        (
            'AdapterRegistry'
        )
        None
    [Disassembly]
        0       LOAD_CONST                      0: 1
        2       LOAD_CONST                      1: ('AdapterRegistry',)
        4       IMPORT_NAME                     0: registry
        6       IMPORT_FROM                     1: AdapterRegistry
        8       STORE_NAME                      1: AdapterRegistry
        10      POP_TOP                         
        12      LOAD_CONST                      2: None
        14      RETURN_VALUE                    
