registry.cpython-39.pyc (Python 3.9)
[Code]
    File Name: adapter_registry/registry.py
    Object Name: <module>
    Arg Count: 0
    Pos Only Arg Count: 0
    KW Only Arg Count: 0
    Locals: 0
    Stack Size: 3
    Flags: 0x00000040 (CO_NOFREE)
    [Names]
        'json'
        'pathlib'
        'Path'
        'datetime'
        'typing'
        'Any'
        'Dict'
        'List'
        'Optional'
        'Union'
        'integration_hooks.service_models'
        'CapabilityManifest'
        'AdapterRegistry'
    [Var Names]
    [Free Vars]
    [Cell Vars]
    [Constants]
        0
        None
        (
            'Path'
        )
        (
            'datetime'
        )
        (
            'Any'
            'Dict'
            'List'
            'Optional'
            'Union'
        )
        (
            'CapabilityManifest'
        )
        [Code]
            File Name: adapter_registry/registry.py
            Object Name: AdapterRegistry
            Arg Count: 0
            Pos Only Arg Count: 0
            KW Only Arg Count: 0
            Locals: 0
            Stack Size: 8
            Flags: 0x00000040 (CO_NOFREE)
            [Names]
                '__name__'
                '__module__'
                '__qualname__'
                'Path'
                'Optional'
                'List'
                'str'
                '__init__'
                'Union'
                'dict'
                'CapabilityManifest'
                'bool'
                'register'
                'Dict'
                'list_adapters'
                'list'
                'is_write_allowed'
                '_save'
            [Var Names]
            [Free Vars]
            [Cell Vars]
            [Constants]
                'AdapterRegistry'
                None
                (
                    'config_path'
                    'trusted_list'
                )
                [Code]
                    File Name: adapter_registry/registry.py
                    Object Name: __init__
                    Arg Count: 3
                    Pos Only Arg Count: 0
                    KW Only Arg Count: 0
                    Locals: 3
                    Stack Size: 8
                    Flags: 0x00000043 (CO_OPTIMIZED | CO_NEWLOCALS | CO_NOFREE)
                    [Names]
                        'config_path'
                        'trusted_list'
                        'adapters'
                        'exists'
                        'json'
                        'loads'
                        'read_text'
                        'Exception'
                    [Var Names]
                        'self'
                        'config_path'
                        'trusted_list'
                    [Free Vars]
                    [Cell Vars]
                    [Constants]
                        None
                        [Code]
                            File Name: adapter_registry/registry.py
                            Object Name: <listcomp>
                            Arg Count: 1
                            Pos Only Arg Count: 0
                            KW Only Arg Count: 0
                            Locals: 2
                            Stack Size: 4
                            Flags: 0x00000053 (CO_OPTIMIZED | CO_NEWLOCALS | CO_NESTED | CO_NOFREE)
                            [Names]
                                'lower'
                            [Var Names]
                                '.0'
                                'x'
                            [Free Vars]
                            [Cell Vars]
                            [Constants]
                            [Disassembly]
                                0       BUILD_LIST                      0
                                2       LOAD_FAST                       0: .0
                                4       FOR_ITER                        12 (to 18)
                                6       STORE_FAST                      1: x
                                8       LOAD_FAST                       1: x
                                10      LOAD_METHOD                     0: lower
                                12      CALL_METHOD                     0
                                14      LIST_APPEND                     2
                                16      JUMP_ABSOLUTE                   4
                                18      RETURN_VALUE                    
                        'AdapterRegistry.__init__.<locals>.<listcomp>'
                        'utf-8'
                        (
                            'encoding'
                        )
                    [Disassembly]
                        0       LOAD_FAST                       1: config_path
                        2       LOAD_FAST                       0: self
                        4       STORE_ATTR                      0: config_path
                        6       LOAD_CONST                      1: <CODE> <listcomp>
                        8       LOAD_CONST                      2: 'AdapterRegistry.__init__.<locals>.<listcomp>'
                        10      MAKE_FUNCTION                   0
                        12      LOAD_FAST                       2: trusted_list
                        14      JUMP_IF_TRUE_OR_POP             18
                        16      BUILD_LIST                      0
                        18      GET_ITER                        
                        20      CALL_FUNCTION                   1
                        22      LOAD_FAST                       0: self
                        24      STORE_ATTR                      1: trusted_list
                        26      BUILD_MAP                       0
                        28      LOAD_FAST                       0: self
                        30      STORE_ATTR                      2: adapters
                        32      LOAD_FAST                       0: self
                        34      LOAD_ATTR                       0: config_path
                        36      LOAD_METHOD                     3: exists
                        38      CALL_METHOD                     0
                        40      POP_JUMP_IF_FALSE               94
                        42      SETUP_FINALLY                   26 (to 70)
                        44      LOAD_GLOBAL                     4: json
                        46      LOAD_METHOD                     5: loads
                        48      LOAD_FAST                       0: self
                        50      LOAD_ATTR                       0: config_path
                        52      LOAD_ATTR                       6: read_text
                        54      LOAD_CONST                      3: 'utf-8'
                        56      LOAD_CONST                      4: ('encoding',)
                        58      CALL_FUNCTION_KW                1
                        60      CALL_METHOD                     1
                        62      LOAD_FAST                       0: self
                        64      STORE_ATTR                      2: adapters
                        66      POP_BLOCK                       
                        68      JUMP_FORWARD                    24 (to 94)
                        70      DUP_TOP                         
                        72      LOAD_GLOBAL                     7: Exception
                        74      JUMP_IF_NOT_EXC_MATCH           92
                        76      POP_TOP                         
                        78      POP_TOP                         
                        80      POP_TOP                         
                        82      BUILD_MAP                       0
                        84      LOAD_FAST                       0: self
                        86      STORE_ATTR                      2: adapters
                        88      POP_EXCEPT                      
                        90      JUMP_FORWARD                    2 (to 94)
                        92      RERAISE                         
                        94      LOAD_CONST                      0: None
                        96      RETURN_VALUE                    
                'AdapterRegistry.__init__'
                True
                False
                (
                    'name'
                    'capabilities'
                    'non_interactive'
                    'approve_trusted_only'
                    'interactive_confirm'
                    'return'
                )
                [Code]
                    File Name: adapter_registry/registry.py
                    Object Name: register
                    Arg Count: 6
                    Pos Only Arg Count: 0
                    KW Only Arg Count: 0
                    Locals: 10
                    Stack Size: 5
                    Flags: 0x00000043 (CO_OPTIMIZED | CO_NEWLOCALS | CO_NOFREE)
                    [Names]
                        'lower'
                        'trusted_list'
                        'adapters'
                        'isinstance'
                        'CapabilityManifest'
                        'to_dict'
                        'dict'
                        'datetime'
                        'utcnow'
                        'isoformat'
                        '_save'
                    [Var Names]
                        'self'
                        'name'
                        'capabilities'
                        'non_interactive'
                        'approve_trusted_only'
                        'interactive_confirm'
                        'lowered'
                        'trusted'
                        'confirm'
                        'manifest'
                    [Free Vars]
                    [Cell Vars]
                    [Constants]
                        None
                        False
                        'active'
                        (
                            'capabilities'
                            'trusted'
                            'registered_at'
                            'status'
                        )
                        True
                    [Disassembly]
                        0       LOAD_FAST                       1: name
                        2       LOAD_METHOD                     0: lower
                        4       CALL_METHOD                     0
                        6       STORE_FAST                      6: lowered
                        8       LOAD_FAST                       6: lowered
                        10      LOAD_FAST                       0: self
                        12      LOAD_ATTR                       1: trusted_list
                        14      CONTAINS_OP                     0 (in)
                        16      STORE_FAST                      7: trusted
                        18      LOAD_FAST                       4: approve_trusted_only
                        20      POP_JUMP_IF_FALSE               40
                        22      LOAD_FAST                       7: trusted
                        24      POP_JUMP_IF_TRUE                40
                        26      LOAD_FAST                       1: name
                        28      LOAD_FAST                       0: self
                        30      LOAD_ATTR                       2: adapters
                        32      CONTAINS_OP                     1 (not in)
                        34      POP_JUMP_IF_FALSE               40
                        36      LOAD_CONST                      1: False
                        38      RETURN_VALUE                    
                        40      LOAD_FAST                       1: name
                        42      LOAD_FAST                       0: self
                        44      LOAD_ATTR                       2: adapters
                        46      CONTAINS_OP                     0 (in)
                        48      POP_JUMP_IF_FALSE               56
                        50      LOAD_CONST                      1: False
                        52      STORE_FAST                      8: confirm
                        54      JUMP_FORWARD                    20 (to 76)
                        56      LOAD_FAST                       3: non_interactive
                        58      POP_JUMP_IF_FALSE               66
                        60      LOAD_CONST                      1: False
                        62      STORE_FAST                      8: confirm
                        64      JUMP_FORWARD                    10 (to 76)
                        66      LOAD_FAST                       5: interactive_confirm
                        68      JUMP_IF_FALSE_OR_POP            74
                        70      LOAD_FAST                       7: trusted
                        72      UNARY_NOT                       
                        74      STORE_FAST                      8: confirm
                        76      LOAD_FAST                       8: confirm
                        78      POP_JUMP_IF_FALSE               84
                        80      LOAD_CONST                      1: False
                        82      RETURN_VALUE                    
                        84      LOAD_GLOBAL                     3: isinstance
                        86      LOAD_FAST                       2: capabilities
                        88      LOAD_GLOBAL                     4: CapabilityManifest
                        90      CALL_FUNCTION                   2
                        92      POP_JUMP_IF_FALSE               102
                        94      LOAD_FAST                       2: capabilities
                        96      LOAD_METHOD                     5: to_dict
                        98      CALL_METHOD                     0
                        100     JUMP_FORWARD                    10 (to 112)
                        102     LOAD_GLOBAL                     6: dict
                        104     LOAD_FAST                       2: capabilities
                        106     JUMP_IF_TRUE_OR_POP             110
                        108     BUILD_MAP                       0
                        110     CALL_FUNCTION                   1
                        112     STORE_FAST                      9: manifest
                        114     LOAD_FAST                       9: manifest
                        116     LOAD_FAST                       7: trusted
                        118     LOAD_GLOBAL                     7: datetime
                        120     LOAD_METHOD                     8: utcnow
                        122     CALL_METHOD                     0
                        124     LOAD_METHOD                     9: isoformat
                        126     CALL_METHOD                     0
                        128     LOAD_CONST                      2: 'active'
                        130     LOAD_CONST                      3: ('capabilities', 'trusted', 'registered_at', 'status')
                        132     BUILD_CONST_KEY_MAP             4
                        134     LOAD_FAST                       0: self
                        136     LOAD_ATTR                       2: adapters
                        138     LOAD_FAST                       1: name
                        140     STORE_SUBSCR                    
                        142     LOAD_FAST                       0: self
                        144     LOAD_METHOD                     10: _save
                        146     CALL_METHOD                     0
                        148     POP_TOP                         
                        150     LOAD_CONST                      4: True
                        152     RETURN_VALUE                    
                'AdapterRegistry.register'
                (
                    'return'
                )
                [Code]
                    File Name: adapter_registry/registry.py
                    Object Name: list_adapters
                    Arg Count: 1
                    Pos Only Arg Count: 0
                    KW Only Arg Count: 0
                    Locals: 1
                    Stack Size: 2
                    Flags: 0x00000043 (CO_OPTIMIZED | CO_NEWLOCALS | CO_NOFREE)
                    [Names]
                        'dict'
                        'adapters'
                    [Var Names]
                        'self'
                    [Free Vars]
                    [Cell Vars]
                    [Constants]
                        None
                    [Disassembly]
                        0       LOAD_GLOBAL                     0: dict
                        2       LOAD_FAST                       0: self
                        4       LOAD_ATTR                       1: adapters
                        6       CALL_FUNCTION                   1
                        8       RETURN_VALUE                    
                'AdapterRegistry.list_adapters'
                (
                    'client_name'
                    'allowed_list'
                    'return'
                )
                [Code]
                    File Name: adapter_registry/registry.py
                    Object Name: is_write_allowed
                    Arg Count: 3
                    Pos Only Arg Count: 0
                    KW Only Arg Count: 0
                    Locals: 3
                    Stack Size: 3
                    Flags: 0x00000043 (CO_OPTIMIZED | CO_NEWLOCALS | CO_NOFREE)
                    [Names]
                        'lower'
                    [Var Names]
                        'self'
                        'client_name'
                        'allowed_list'
                    [Free Vars]
                    [Cell Vars]
                    [Constants]
                        None
                        '*'
                        True
                        [Code]
                            File Name: adapter_registry/registry.py
                            Object Name: <listcomp>
                            Arg Count: 1
                            Pos Only Arg Count: 0
                            KW Only Arg Count: 0
                            Locals: 2
                            Stack Size: 4
                            Flags: 0x00000053 (CO_OPTIMIZED | CO_NEWLOCALS | CO_NESTED | CO_NOFREE)
                            [Names]
                                'lower'
                            [Var Names]
                                '.0'
                                'x'
                            [Free Vars]
                            [Cell Vars]
                            [Constants]
                            [Disassembly]
                                0       BUILD_LIST                      0
                                2       LOAD_FAST                       0: .0
                                4       FOR_ITER                        12 (to 18)
                                6       STORE_FAST                      1: x
                                8       LOAD_FAST                       1: x
                                10      LOAD_METHOD                     0: lower
                                12      CALL_METHOD                     0
                                14      LIST_APPEND                     2
                                16      JUMP_ABSOLUTE                   4
                                18      RETURN_VALUE                    
                        'AdapterRegistry.is_write_allowed.<locals>.<listcomp>'
                    [Disassembly]
                        0       LOAD_CONST                      1: '*'
                        2       LOAD_FAST                       2: allowed_list
                        4       CONTAINS_OP                     0 (in)
                        6       POP_JUMP_IF_FALSE               12
                        8       LOAD_CONST                      2: True
                        10      RETURN_VALUE                    
                        12      LOAD_FAST                       1: client_name
                        14      LOAD_METHOD                     0: lower
                        16      CALL_METHOD                     0
                        18      LOAD_CONST                      3: <CODE> <listcomp>
                        20      LOAD_CONST                      4: 'AdapterRegistry.is_write_allowed.<locals>.<listcomp>'
                        22      MAKE_FUNCTION                   0
                        24      LOAD_FAST                       2: allowed_list
                        26      GET_ITER                        
                        28      CALL_FUNCTION                   1
                        30      CONTAINS_OP                     0 (in)
                        32      RETURN_VALUE                    
                'AdapterRegistry.is_write_allowed'
                [Code]
                    File Name: adapter_registry/registry.py
                    Object Name: _save
                    Arg Count: 1
                    Pos Only Arg Count: 0
                    KW Only Arg Count: 0
                    Locals: 1
                    Stack Size: 6
                    Flags: 0x00000043 (CO_OPTIMIZED | CO_NEWLOCALS | CO_NOFREE)
                    [Names]
                        'config_path'
                        'parent'
                        'mkdir'
                        'write_text'
                        'json'
                        'dumps'
                        'adapters'
                    [Var Names]
                        'self'
                    [Free Vars]
                    [Cell Vars]
                    [Constants]
                        None
                        True
                        (
                            'parents'
                            'exist_ok'
                        )
                        2
                        False
                        (
                            'indent'
                            'ensure_ascii'
                        )
                        'utf-8'
                        (
                            'encoding'
                        )
                    [Disassembly]
                        0       LOAD_FAST                       0: self
                        2       LOAD_ATTR                       0: config_path
                        4       LOAD_ATTR                       1: parent
                        6       LOAD_ATTR                       2: mkdir
                        8       LOAD_CONST                      1: True
                        10      LOAD_CONST                      1: True
                        12      LOAD_CONST                      2: ('parents', 'exist_ok')
                        14      CALL_FUNCTION_KW                2
                        16      POP_TOP                         
                        18      LOAD_FAST                       0: self
                        20      LOAD_ATTR                       0: config_path
                        22      LOAD_ATTR                       3: write_text
                        24      LOAD_GLOBAL                     4: json
                        26      LOAD_ATTR                       5: dumps
                        28      LOAD_FAST                       0: self
                        30      LOAD_ATTR                       6: adapters
                        32      LOAD_CONST                      3: 2
                        34      LOAD_CONST                      4: False
                        36      LOAD_CONST                      5: ('indent', 'ensure_ascii')
                        38      CALL_FUNCTION_KW                3
                        40      LOAD_CONST                      6: 'utf-8'
                        42      LOAD_CONST                      7: ('encoding',)
                        44      CALL_FUNCTION_KW                2
                        46      POP_TOP                         
                        48      LOAD_CONST                      0: None
                        50      RETURN_VALUE                    
                'AdapterRegistry._save'
                (
                    None
                )
                (
                    True
                    True
                    False
                )
            [Disassembly]
                0       LOAD_NAME                       0: __name__
                2       STORE_NAME                      1: __module__
                4       LOAD_CONST                      0: 'AdapterRegistry'
                6       STORE_NAME                      2: __qualname__
                8       LOAD_CONST                      18: (None,)
                10      LOAD_NAME                       3: Path
                12      LOAD_NAME                       4: Optional
                14      LOAD_NAME                       5: List
                16      LOAD_NAME                       6: str
                18      BINARY_SUBSCR                   
                20      BINARY_SUBSCR                   
                22      LOAD_CONST                      2: ('config_path', 'trusted_list')
                24      BUILD_CONST_KEY_MAP             2
                26      LOAD_CONST                      3: <CODE> __init__
                28      LOAD_CONST                      4: 'AdapterRegistry.__init__'
                30      MAKE_FUNCTION                   5
                32      STORE_NAME                      7: __init__
                34      LOAD_CONST                      19: (True, True, False)
                36      LOAD_NAME                       6: str
                38      LOAD_NAME                       8: Union
                40      LOAD_NAME                       9: dict
                42      LOAD_NAME                       10: CapabilityManifest
                44      BUILD_TUPLE                     2
                46      BINARY_SUBSCR                   
                48      LOAD_NAME                       11: bool
                50      LOAD_NAME                       11: bool
                52      LOAD_NAME                       11: bool
                54      LOAD_NAME                       11: bool
                56      LOAD_CONST                      7: ('name', 'capabilities', 'non_interactive', 'approve_trusted_only', 'interactive_confirm', 'return')
                58      BUILD_CONST_KEY_MAP             6
                60      LOAD_CONST                      8: <CODE> register
                62      LOAD_CONST                      9: 'AdapterRegistry.register'
                64      MAKE_FUNCTION                   5
                66      STORE_NAME                      12: register
                68      LOAD_NAME                       13: Dict
                70      LOAD_NAME                       6: str
                72      LOAD_NAME                       9: dict
                74      BUILD_TUPLE                     2
                76      BINARY_SUBSCR                   
                78      LOAD_CONST                      10: ('return',)
                80      BUILD_CONST_KEY_MAP             1
                82      LOAD_CONST                      11: <CODE> list_adapters
                84      LOAD_CONST                      12: 'AdapterRegistry.list_adapters'
                86      MAKE_FUNCTION                   4
                88      STORE_NAME                      14: list_adapters
                90      LOAD_NAME                       6: str
                92      LOAD_NAME                       15: list
                94      LOAD_NAME                       11: bool
                96      LOAD_CONST                      13: ('client_name', 'allowed_list', 'return')
                98      BUILD_CONST_KEY_MAP             3
                100     LOAD_CONST                      14: <CODE> is_write_allowed
                102     LOAD_CONST                      15: 'AdapterRegistry.is_write_allowed'
                104     MAKE_FUNCTION                   4
                106     STORE_NAME                      16: is_write_allowed
                108     LOAD_CONST                      16: <CODE> _save
                110     LOAD_CONST                      17: 'AdapterRegistry._save'
                112     MAKE_FUNCTION                   0
                114     STORE_NAME                      17: _save
                116     LOAD_CONST                      1: None
                118     RETURN_VALUE                    
        'AdapterRegistry'
    [Disassembly]
        0       LOAD_CONST                      0: 0
        2       LOAD_CONST                      1: None
        4       IMPORT_NAME                     0: json
        6       STORE_NAME                      0: json
        8       LOAD_CONST                      0: 0
        10      LOAD_CONST                      2: ('Path',)
        12      IMPORT_NAME                     1: pathlib
        14      IMPORT_FROM                     2: Path
        16      STORE_NAME                      2: Path
        18      POP_TOP                         
        20      LOAD_CONST                      0: 0
        22      LOAD_CONST                      3: ('datetime',)
        24      IMPORT_NAME                     3: datetime
        26      IMPORT_FROM                     3: datetime
        28      STORE_NAME                      3: datetime
        30      POP_TOP                         
        32      LOAD_CONST                      0: 0
        34      LOAD_CONST                      4: ('Any', 'Dict', 'List', 'Optional', 'Union')
        36      IMPORT_NAME                     4: typing
        38      IMPORT_FROM                     5: Any
        40      STORE_NAME                      5: Any
        42      IMPORT_FROM                     6: Dict
        44      STORE_NAME                      6: Dict
        46      IMPORT_FROM                     7: List
        48      STORE_NAME                      7: List
        50      IMPORT_FROM                     8: Optional
        52      STORE_NAME                      8: Optional
        54      IMPORT_FROM                     9: Union
        56      STORE_NAME                      9: Union
        58      POP_TOP                         
        60      LOAD_CONST                      0: 0
        62      LOAD_CONST                      5: ('CapabilityManifest',)
        64      IMPORT_NAME                     10: integration_hooks.service_models
        66      IMPORT_FROM                     11: CapabilityManifest
        68      STORE_NAME                      11: CapabilityManifest
        70      POP_TOP                         
        72      LOAD_BUILD_CLASS                
        74      LOAD_CONST                      6: <CODE> AdapterRegistry
        76      LOAD_CONST                      7: 'AdapterRegistry'
        78      MAKE_FUNCTION                   0
        80      LOAD_CONST                      7: 'AdapterRegistry'
        82      CALL_FUNCTION                   2
        84      STORE_NAME                      12: AdapterRegistry
        86      LOAD_CONST                      1: None
        88      RETURN_VALUE                    
