common.cpython-39.pyc (Python 3.9)
[Code]
    File Name: scripts/common.py
    Object Name: <module>
    Arg Count: 0
    Pos Only Arg Count: 0
    KW Only Arg Count: 0
    Locals: 0
    Stack Size: 6
    Flags: 0x01000040 (CO_NOFREE | CO_FUTURE_ANNOTATIONS)
    [Names]
        '__future__'
        'annotations'
        'json'
        'os'
        'shutil'
        'subprocess'
        'datetime'
        'pathlib'
        'Path'
        'typing'
        'Any'
        'List'
        'Optional'
        'Tuple'
        'yaml'
        '__file__'
        'resolve'
        'parents'
        'ROOT'
        'CFG_PATH'
        'load_cfg'
        'expand'
        'expand_keep'
        'run'
        'choose_python'
        'write_json'
        'read_json'
        'snapshot_config'
    [Var Names]
    [Free Vars]
    [Cell Vars]
    [Constants]
        0
        (
            'annotations'
        )
        None
        (
            'datetime'
        )
        (
            'Path'
        )
        (
            'Any'
            'List'
            'Optional'
            'Tuple'
        )
        1
        'config'
        'mcp_config.yaml'
        'dict'
        (
            'return'
        )
        [Code]
            File Name: scripts/common.py
            Object Name: load_cfg
            Arg Count: 0
            Pos Only Arg Count: 0
            KW Only Arg Count: 0
            Locals: 0
            Stack Size: 5
            Flags: 0x01000043 (CO_OPTIMIZED | CO_NEWLOCALS | CO_NOFREE | CO_FUTURE_ANNOTATIONS)
            [Names]
                'CFG_PATH'
                'exists'
                'yaml'
                'safe_load'
                'read_text'
            [Var Names]
            [Free Vars]
            [Cell Vars]
            [Constants]
                None
                'utf-8'
                (
                    'encoding'
                )
            [Disassembly]
                0       LOAD_GLOBAL                     0: CFG_PATH
                2       LOAD_METHOD                     1: exists
                4       CALL_METHOD                     0
                6       POP_JUMP_IF_FALSE               30
                8       LOAD_GLOBAL                     2: yaml
                10      LOAD_METHOD                     3: safe_load
                12      LOAD_GLOBAL                     0: CFG_PATH
                14      LOAD_ATTR                       4: read_text
                16      LOAD_CONST                      1: 'utf-8'
                18      LOAD_CONST                      2: ('encoding',)
                20      CALL_FUNCTION_KW                1
                22      CALL_METHOD                     1
                24      JUMP_IF_TRUE_OR_POP             28
                26      BUILD_MAP                       0
                28      RETURN_VALUE                    
                30      BUILD_MAP                       0
                32      RETURN_VALUE                    
        'load_cfg'
        'str'
        'Path'
        (
            'path_like'
            'return'
        )
        [Code]
            File Name: scripts/common.py
            Object Name: expand
            Arg Count: 1
            Pos Only Arg Count: 0
            KW Only Arg Count: 0
            Locals: 1
            Stack Size: 4
            Flags: 0x01000043 (CO_OPTIMIZED | CO_NEWLOCALS | CO_NOFREE | CO_FUTURE_ANNOTATIONS)
            [Names]
                'Path'
                'os'
                'path'
                'expanduser'
                'resolve'
            [Var Names]
                'path_like'
            [Free Vars]
            [Cell Vars]
            [Constants]
                None
            [Disassembly]
                0       LOAD_GLOBAL                     0: Path
                2       LOAD_GLOBAL                     1: os
                4       LOAD_ATTR                       2: path
                6       LOAD_METHOD                     3: expanduser
                8       LOAD_FAST                       0: path_like
                10      CALL_METHOD                     1
                12      CALL_FUNCTION                   1
                14      LOAD_METHOD                     4: resolve
                16      CALL_METHOD                     0
                18      RETURN_VALUE                    
        'expand'
        [Code]
            File Name: scripts/common.py
            Object Name: expand_keep
            Arg Count: 1
            Pos Only Arg Count: 0
            KW Only Arg Count: 0
            Locals: 1
            Stack Size: 4
            Flags: 0x01000043 (CO_OPTIMIZED | CO_NEWLOCALS | CO_NOFREE | CO_FUTURE_ANNOTATIONS)
            [Names]
                'Path'
                'os'
                'path'
                'expanduser'
            [Var Names]
                'path_like'
            [Free Vars]
            [Cell Vars]
            [Constants]
                'Expand ~ but keep symlink path unchanged (important for venv python executables).'
            [Disassembly]
                0       LOAD_GLOBAL                     0: Path
                2       LOAD_GLOBAL                     1: os
                4       LOAD_ATTR                       2: path
                6       LOAD_METHOD                     3: expanduser
                8       LOAD_FAST                       0: path_like
                10      CALL_METHOD                     1
                12      CALL_FUNCTION                   1
                14      RETURN_VALUE                    
        'expand_keep'
        120
        'List[str]'
        'Optional[Path]'
        'int'
        'Tuple[int, str, str]'
        (
            'cmd'
            'cwd'
            'timeout'
            'return'
        )
        [Code]
            File Name: scripts/common.py
            Object Name: run
            Arg Count: 3
            Pos Only Arg Count: 0
            KW Only Arg Count: 0
            Locals: 4
            Stack Size: 7
            Flags: 0x01000043 (CO_OPTIMIZED | CO_NEWLOCALS | CO_NOFREE | CO_FUTURE_ANNOTATIONS)
            [Names]
                'subprocess'
                'run'
                'str'
                'returncode'
                'stdout'
                'stderr'
            [Var Names]
                'cmd'
                'cwd'
                'timeout'
                'p'
            [Free Vars]
            [Cell Vars]
            [Constants]
                None
                True
                (
                    'cwd'
                    'capture_output'
                    'text'
                    'timeout'
                )
            [Disassembly]
                0       LOAD_GLOBAL                     0: subprocess
                2       LOAD_ATTR                       1: run
                4       LOAD_FAST                       0: cmd
                6       LOAD_FAST                       1: cwd
                8       POP_JUMP_IF_FALSE               18
                10      LOAD_GLOBAL                     2: str
                12      LOAD_FAST                       1: cwd
                14      CALL_FUNCTION                   1
                16      JUMP_FORWARD                    2 (to 20)
                18      LOAD_CONST                      0: None
                20      LOAD_CONST                      1: True
                22      LOAD_CONST                      1: True
                24      LOAD_FAST                       2: timeout
                26      LOAD_CONST                      2: ('cwd', 'capture_output', 'text', 'timeout')
                28      CALL_FUNCTION_KW                5
                30      STORE_FAST                      3: p
                32      LOAD_FAST                       3: p
                34      LOAD_ATTR                       3: returncode
                36      LOAD_FAST                       3: p
                38      LOAD_ATTR                       4: stdout
                40      LOAD_FAST                       3: p
                42      LOAD_ATTR                       5: stderr
                44      BUILD_TUPLE                     3
                46      RETURN_VALUE                    
        'run'
        (
            'candidates'
            'return'
        )
        [Code]
            File Name: scripts/common.py
            Object Name: choose_python
            Arg Count: 1
            Pos Only Arg Count: 0
            KW Only Arg Count: 0
            Locals: 3
            Stack Size: 3
            Flags: 0x01000043 (CO_OPTIMIZED | CO_NEWLOCALS | CO_NOFREE | CO_FUTURE_ANNOTATIONS)
            [Names]
                'expand'
                'exists'
                'str'
                'shutil'
                'which'
            [Var Names]
                'candidates'
                'c'
                'p'
            [Free Vars]
            [Cell Vars]
            [Constants]
                None
                'python3'
                '/usr/bin/python3'
            [Disassembly]
                0       LOAD_FAST                       0: candidates
                2       GET_ITER                        
                4       FOR_ITER                        32 (to 38)
                6       STORE_FAST                      1: c
                8       LOAD_GLOBAL                     0: expand
                10      LOAD_FAST                       1: c
                12      CALL_FUNCTION                   1
                14      STORE_FAST                      2: p
                16      LOAD_FAST                       2: p
                18      LOAD_METHOD                     1: exists
                20      CALL_METHOD                     0
                22      POP_JUMP_IF_FALSE               4
                24      LOAD_GLOBAL                     2: str
                26      LOAD_FAST                       2: p
                28      CALL_FUNCTION                   1
                30      ROT_TWO                         
                32      POP_TOP                         
                34      RETURN_VALUE                    
                36      JUMP_ABSOLUTE                   4
                38      LOAD_GLOBAL                     3: shutil
                40      LOAD_METHOD                     4: which
                42      LOAD_CONST                      1: 'python3'
                44      CALL_METHOD                     1
                46      JUMP_IF_TRUE_OR_POP             50
                48      LOAD_CONST                      2: '/usr/bin/python3'
                50      RETURN_VALUE                    
        'choose_python'
        'Any'
        'None'
        (
            'path'
            'obj'
            'return'
        )
        [Code]
            File Name: scripts/common.py
            Object Name: write_json
            Arg Count: 2
            Pos Only Arg Count: 0
            KW Only Arg Count: 0
            Locals: 2
            Stack Size: 6
            Flags: 0x01000043 (CO_OPTIMIZED | CO_NEWLOCALS | CO_NOFREE | CO_FUTURE_ANNOTATIONS)
            [Names]
                'parent'
                'mkdir'
                'write_text'
                'json'
                'dumps'
            [Var Names]
                'path'
                'obj'
            [Free Vars]
            [Cell Vars]
            [Constants]
                None
                True
                (
                    'parents'
                    'exist_ok'
                )
                False
                2
                (
                    'ensure_ascii'
                    'indent'
                )
                'utf-8'
                (
                    'encoding'
                )
            [Disassembly]
                0       LOAD_FAST                       0: path
                2       LOAD_ATTR                       0: parent
                4       LOAD_ATTR                       1: mkdir
                6       LOAD_CONST                      1: True
                8       LOAD_CONST                      1: True
                10      LOAD_CONST                      2: ('parents', 'exist_ok')
                12      CALL_FUNCTION_KW                2
                14      POP_TOP                         
                16      LOAD_FAST                       0: path
                18      LOAD_ATTR                       2: write_text
                20      LOAD_GLOBAL                     3: json
                22      LOAD_ATTR                       4: dumps
                24      LOAD_FAST                       1: obj
                26      LOAD_CONST                      3: False
                28      LOAD_CONST                      4: 2
                30      LOAD_CONST                      5: ('ensure_ascii', 'indent')
                32      CALL_FUNCTION_KW                3
                34      LOAD_CONST                      6: 'utf-8'
                36      LOAD_CONST                      7: ('encoding',)
                38      CALL_FUNCTION_KW                2
                40      POP_TOP                         
                42      LOAD_CONST                      0: None
                44      RETURN_VALUE                    
        'write_json'
        (
            'path'
            'default'
            'return'
        )
        [Code]
            File Name: scripts/common.py
            Object Name: read_json
            Arg Count: 2
            Pos Only Arg Count: 0
            KW Only Arg Count: 0
            Locals: 2
            Stack Size: 8
            Flags: 0x01000043 (CO_OPTIMIZED | CO_NEWLOCALS | CO_NOFREE | CO_FUTURE_ANNOTATIONS)
            [Names]
                'exists'
                'json'
                'loads'
                'read_text'
                'Exception'
            [Var Names]
                'path'
                'default'
            [Free Vars]
            [Cell Vars]
            [Constants]
                None
                'utf-8'
                (
                    'encoding'
                )
            [Disassembly]
                0       LOAD_FAST                       0: path
                2       LOAD_METHOD                     0: exists
                4       CALL_METHOD                     0
                6       POP_JUMP_IF_TRUE                12
                8       LOAD_FAST                       1: default
                10      RETURN_VALUE                    
                12      SETUP_FINALLY                   20 (to 34)
                14      LOAD_GLOBAL                     1: json
                16      LOAD_METHOD                     2: loads
                18      LOAD_FAST                       0: path
                20      LOAD_ATTR                       3: read_text
                22      LOAD_CONST                      1: 'utf-8'
                24      LOAD_CONST                      2: ('encoding',)
                26      CALL_FUNCTION_KW                1
                28      CALL_METHOD                     1
                30      POP_BLOCK                       
                32      RETURN_VALUE                    
                34      DUP_TOP                         
                36      LOAD_GLOBAL                     4: Exception
                38      JUMP_IF_NOT_EXC_MATCH           54
                40      POP_TOP                         
                42      POP_TOP                         
                44      POP_TOP                         
                46      LOAD_FAST                       1: default
                48      ROT_FOUR                        
                50      POP_EXCEPT                      
                52      RETURN_VALUE                    
                54      RERAISE                         
                56      LOAD_CONST                      0: None
                58      RETURN_VALUE                    
        'read_json'
        [Code]
            File Name: scripts/common.py
            Object Name: snapshot_config
            Arg Count: 0
            Pos Only Arg Count: 0
            KW Only Arg Count: 0
            Locals: 4
            Stack Size: 4
            Flags: 0x01000043 (CO_OPTIMIZED | CO_NEWLOCALS | CO_NOFREE | CO_FUTURE_ANNOTATIONS)
            [Names]
                'ROOT'
                'mkdir'
                'datetime'
                'utcnow'
                'strftime'
                'CFG_PATH'
                'exists'
                'write_text'
                'read_text'
            [Var Names]
                'snap_dir'
                'ts'
                'target'
                'reg'
            [Free Vars]
            [Cell Vars]
            [Constants]
                None
                'runtime'
                'snapshots'
                True
                (
                    'parents'
                    'exist_ok'
                )
                '%Y%m%d_%H%M%S'
                'mcp_config.yaml'
                'utf-8'
                (
                    'encoding'
                )
                'adapter_registry'
                'adapters.json'
            [Disassembly]
                0       LOAD_GLOBAL                     0: ROOT
                2       LOAD_CONST                      1: 'runtime'
                4       BINARY_TRUE_DIVIDE              
                6       LOAD_CONST                      2: 'snapshots'
                8       BINARY_TRUE_DIVIDE              
                10      STORE_FAST                      0: snap_dir
                12      LOAD_FAST                       0: snap_dir
                14      LOAD_ATTR                       1: mkdir
                16      LOAD_CONST                      3: True
                18      LOAD_CONST                      3: True
                20      LOAD_CONST                      4: ('parents', 'exist_ok')
                22      CALL_FUNCTION_KW                2
                24      POP_TOP                         
                26      LOAD_GLOBAL                     2: datetime
                28      LOAD_METHOD                     3: utcnow
                30      CALL_METHOD                     0
                32      LOAD_METHOD                     4: strftime
                34      LOAD_CONST                      5: '%Y%m%d_%H%M%S'
                36      CALL_METHOD                     1
                38      STORE_FAST                      1: ts
                40      LOAD_FAST                       0: snap_dir
                42      LOAD_FAST                       1: ts
                44      BINARY_TRUE_DIVIDE              
                46      STORE_FAST                      2: target
                48      LOAD_FAST                       2: target
                50      LOAD_ATTR                       1: mkdir
                52      LOAD_CONST                      3: True
                54      LOAD_CONST                      3: True
                56      LOAD_CONST                      4: ('parents', 'exist_ok')
                58      CALL_FUNCTION_KW                2
                60      POP_TOP                         
                62      LOAD_GLOBAL                     5: CFG_PATH
                64      LOAD_METHOD                     6: exists
                66      CALL_METHOD                     0
                68      POP_JUMP_IF_FALSE               96
                70      LOAD_FAST                       2: target
                72      LOAD_CONST                      6: 'mcp_config.yaml'
                74      BINARY_TRUE_DIVIDE              
                76      LOAD_ATTR                       7: write_text
                78      LOAD_GLOBAL                     5: CFG_PATH
                80      LOAD_ATTR                       8: read_text
                82      LOAD_CONST                      7: 'utf-8'
                84      LOAD_CONST                      8: ('encoding',)
                86      CALL_FUNCTION_KW                1
                88      LOAD_CONST                      7: 'utf-8'
                90      LOAD_CONST                      8: ('encoding',)
                92      CALL_FUNCTION_KW                2
                94      POP_TOP                         
                96      LOAD_GLOBAL                     0: ROOT
                98      LOAD_CONST                      9: 'adapter_registry'
                100     BINARY_TRUE_DIVIDE              
                102     LOAD_CONST                      10: 'adapters.json'
                104     BINARY_TRUE_DIVIDE              
                106     STORE_FAST                      3: reg
                108     LOAD_FAST                       3: reg
                110     LOAD_METHOD                     6: exists
                112     CALL_METHOD                     0
                114     POP_JUMP_IF_FALSE               142
                116     LOAD_FAST                       2: target
                118     LOAD_CONST                      10: 'adapters.json'
                120     BINARY_TRUE_DIVIDE              
                122     LOAD_ATTR                       7: write_text
                124     LOAD_FAST                       3: reg
                126     LOAD_ATTR                       8: read_text
                128     LOAD_CONST                      7: 'utf-8'
                130     LOAD_CONST                      8: ('encoding',)
                132     CALL_FUNCTION_KW                1
                134     LOAD_CONST                      7: 'utf-8'
                136     LOAD_CONST                      8: ('encoding',)
                138     CALL_FUNCTION_KW                2
                140     POP_TOP                         
                142     LOAD_FAST                       1: ts
                144     RETURN_VALUE                    
        'snapshot_config'
        (
            None
            120
        )
    [Disassembly]
        0       LOAD_CONST                      0: 0
        2       LOAD_CONST                      1: ('annotations',)
        4       IMPORT_NAME                     0: __future__
        6       IMPORT_FROM                     1: annotations
        8       STORE_NAME                      1: annotations
        10      POP_TOP                         
        12      LOAD_CONST                      0: 0
        14      LOAD_CONST                      2: None
        16      IMPORT_NAME                     2: json
        18      STORE_NAME                      2: json
        20      LOAD_CONST                      0: 0
        22      LOAD_CONST                      2: None
        24      IMPORT_NAME                     3: os
        26      STORE_NAME                      3: os
        28      LOAD_CONST                      0: 0
        30      LOAD_CONST                      2: None
        32      IMPORT_NAME                     4: shutil
        34      STORE_NAME                      4: shutil
        36      LOAD_CONST                      0: 0
        38      LOAD_CONST                      2: None
        40      IMPORT_NAME                     5: subprocess
        42      STORE_NAME                      5: subprocess
        44      LOAD_CONST                      0: 0
        46      LOAD_CONST                      3: ('datetime',)
        48      IMPORT_NAME                     6: datetime
        50      IMPORT_FROM                     6: datetime
        52      STORE_NAME                      6: datetime
        54      POP_TOP                         
        56      LOAD_CONST                      0: 0
        58      LOAD_CONST                      4: ('Path',)
        60      IMPORT_NAME                     7: pathlib
        62      IMPORT_FROM                     8: Path
        64      STORE_NAME                      8: Path
        66      POP_TOP                         
        68      LOAD_CONST                      0: 0
        70      LOAD_CONST                      5: ('Any', 'List', 'Optional', 'Tuple')
        72      IMPORT_NAME                     9: typing
        74      IMPORT_FROM                     10: Any
        76      STORE_NAME                      10: Any
        78      IMPORT_FROM                     11: List
        80      STORE_NAME                      11: List
        82      IMPORT_FROM                     12: Optional
        84      STORE_NAME                      12: Optional
        86      IMPORT_FROM                     13: Tuple
        88      STORE_NAME                      13: Tuple
        90      POP_TOP                         
        92      LOAD_CONST                      0: 0
        94      LOAD_CONST                      2: None
        96      IMPORT_NAME                     14: yaml
        98      STORE_NAME                      14: yaml
        100     LOAD_NAME                       8: Path
        102     LOAD_NAME                       15: __file__
        104     CALL_FUNCTION                   1
        106     LOAD_METHOD                     16: resolve
        108     CALL_METHOD                     0
        110     LOAD_ATTR                       17: parents
        112     LOAD_CONST                      6: 1
        114     BINARY_SUBSCR                   
        116     STORE_NAME                      18: ROOT
        118     LOAD_NAME                       18: ROOT
        120     LOAD_CONST                      7: 'config'
        122     BINARY_TRUE_DIVIDE              
        124     LOAD_CONST                      8: 'mcp_config.yaml'
        126     BINARY_TRUE_DIVIDE              
        128     STORE_NAME                      19: CFG_PATH
        130     LOAD_CONST                      9: 'dict'
        132     LOAD_CONST                      10: ('return',)
        134     BUILD_CONST_KEY_MAP             1
        136     LOAD_CONST                      11: <CODE> load_cfg
        138     LOAD_CONST                      12: 'load_cfg'
        140     MAKE_FUNCTION                   4
        142     STORE_NAME                      20: load_cfg
        144     LOAD_CONST                      13: 'str'
        146     LOAD_CONST                      14: 'Path'
        148     LOAD_CONST                      15: ('path_like', 'return')
        150     BUILD_CONST_KEY_MAP             2
        152     LOAD_CONST                      16: <CODE> expand
        154     LOAD_CONST                      17: 'expand'
        156     MAKE_FUNCTION                   4
        158     STORE_NAME                      21: expand
        160     LOAD_CONST                      13: 'str'
        162     LOAD_CONST                      14: 'Path'
        164     LOAD_CONST                      15: ('path_like', 'return')
        166     BUILD_CONST_KEY_MAP             2
        168     LOAD_CONST                      18: <CODE> expand_keep
        170     LOAD_CONST                      19: 'expand_keep'
        172     MAKE_FUNCTION                   4
        174     STORE_NAME                      22: expand_keep
        176     LOAD_CONST                      41: (None, 120)
        178     LOAD_CONST                      21: 'List[str]'
        180     LOAD_CONST                      22: 'Optional[Path]'
        182     LOAD_CONST                      23: 'int'
        184     LOAD_CONST                      24: 'Tuple[int, str, str]'
        186     LOAD_CONST                      25: ('cmd', 'cwd', 'timeout', 'return')
        188     BUILD_CONST_KEY_MAP             4
        190     LOAD_CONST                      26: <CODE> run
        192     LOAD_CONST                      27: 'run'
        194     MAKE_FUNCTION                   5
        196     STORE_NAME                      23: run
        198     LOAD_CONST                      21: 'List[str]'
        200     LOAD_CONST                      13: 'str'
        202     LOAD_CONST                      28: ('candidates', 'return')
        204     BUILD_CONST_KEY_MAP             2
        206     LOAD_CONST                      29: <CODE> choose_python
        208     LOAD_CONST                      30: 'choose_python'
        210     MAKE_FUNCTION                   4
        212     STORE_NAME                      24: choose_python
        214     LOAD_CONST                      14: 'Path'
        216     LOAD_CONST                      31: 'Any'
        218     LOAD_CONST                      32: 'None'
        220     LOAD_CONST                      33: ('path', 'obj', 'return')
        222     BUILD_CONST_KEY_MAP             3
        224     LOAD_CONST                      34: <CODE> write_json
        226     LOAD_CONST                      35: 'write_json'
        228     MAKE_FUNCTION                   4
        230     STORE_NAME                      25: write_json
        232     LOAD_CONST                      14: 'Path'
        234     LOAD_CONST                      31: 'Any'
        236     LOAD_CONST                      31: 'Any'
        238     LOAD_CONST                      36: ('path', 'default', 'return')
        240     BUILD_CONST_KEY_MAP             3
        242     LOAD_CONST                      37: <CODE> read_json
        244     LOAD_CONST                      38: 'read_json'
        246     MAKE_FUNCTION                   4
        248     STORE_NAME                      26: read_json
        250     LOAD_CONST                      13: 'str'
        252     LOAD_CONST                      10: ('return',)
        254     BUILD_CONST_KEY_MAP             1
        256     LOAD_CONST                      39: <CODE> snapshot_config
        258     LOAD_CONST                      40: 'snapshot_config'
        260     MAKE_FUNCTION                   4
        262     STORE_NAME                      27: snapshot_config
        264     LOAD_CONST                      2: None
        266     RETURN_VALUE                    
