connect.cpython-39.pyc (Python 3.9)
[Code]
    File Name: /Users/s/openclaw-memory-auto/scripts/connect.py
    Object Name: <module>
    Arg Count: 0
    Pos Only Arg Count: 0
    KW Only Arg Count: 0
    Locals: 0
    Stack Size: 7
    Flags: 0x01000040 (CO_NOFREE | CO_FUTURE_ANNOTATIONS)
    [Names]
        '__future__'
        'annotations'
        'argparse'
        'json'
        'os'
        'subprocess'
        'sys'
        'datetime'
        'timezone'
        'pathlib'
        'Path'
        'typing'
        'Any'
        'Dict'
        'List'
        'Optional'
        'Tuple'
        'common'
        'ROOT'
        'expand'
        'expand_keep'
        'load_cfg'
        'snapshot_config'
        'write_json'
        'integration_hooks.service_models'
        'ConnectResult'
        '_now'
        '_run'
        '_pick_core_python'
        '_detect_targets'
        '_step'
        '_run_py'
        'main'
        '__name__'
        'SystemExit'
    [Var Names]
    [Free Vars]
    [Cell Vars]
    [Constants]
        0
        (
            'annotations'
        )
        None
        (
            'datetime'
            'timezone'
        )
        (
            'Path'
        )
        (
            'Any'
            'Dict'
            'List'
            'Optional'
            'Tuple'
        )
        (
            'ROOT'
            'expand'
            'expand_keep'
            'load_cfg'
            'snapshot_config'
            'write_json'
        )
        (
            'ConnectResult'
        )
        'str'
        (
            'return'
        )
        [Code]
            File Name: /Users/s/openclaw-memory-auto/scripts/connect.py
            Object Name: _now
            Arg Count: 0
            Pos Only Arg Count: 0
            KW Only Arg Count: 0
            Locals: 0
            Stack Size: 3
            Flags: 0x01000043 (CO_OPTIMIZED | CO_NEWLOCALS | CO_NOFREE | CO_FUTURE_ANNOTATIONS)
            [Names]
                'datetime'
                'now'
                'timezone'
                'utc'
                'isoformat'
            [Var Names]
            [Free Vars]
            [Cell Vars]
            [Constants]
                None
            [Disassembly]
                0       LOAD_GLOBAL                     0: datetime
                2       LOAD_METHOD                     1: now
                4       LOAD_GLOBAL                     2: timezone
                6       LOAD_ATTR                       3: utc
                8       CALL_METHOD                     1
                10      LOAD_METHOD                     4: isoformat
                12      CALL_METHOD                     0
                14      RETURN_VALUE                    
        '_now'
        240
        'List[str]'
        'Optional[Dict[str, str]]'
        'int'
        'Tuple[int, str, str]'
        (
            'cmd'
            'env'
            'timeout'
            'return'
        )
        [Code]
            File Name: /Users/s/openclaw-memory-auto/scripts/connect.py
            Object Name: _run
            Arg Count: 3
            Pos Only Arg Count: 0
            KW Only Arg Count: 0
            Locals: 4
            Stack Size: 8
            Flags: 0x01000043 (CO_OPTIMIZED | CO_NEWLOCALS | CO_NOFREE | CO_FUTURE_ANNOTATIONS)
            [Names]
                'subprocess'
                'run'
                'str'
                'ROOT'
                'os'
                'environ'
                'copy'
                'returncode'
                'stdout'
                'stderr'
            [Var Names]
                'cmd'
                'env'
                'timeout'
                'proc'
            [Free Vars]
            [Cell Vars]
            [Constants]
                None
                True
                (
                    'cwd'
                    'env'
                    'capture_output'
                    'text'
                    'timeout'
                )
            [Disassembly]
                0       LOAD_GLOBAL                     0: subprocess
                2       LOAD_ATTR                       1: run
                4       LOAD_FAST                       0: cmd
                6       LOAD_GLOBAL                     2: str
                8       LOAD_GLOBAL                     3: ROOT
                10      CALL_FUNCTION                   1
                12      LOAD_FAST                       1: env
                14      JUMP_IF_TRUE_OR_POP             24
                16      LOAD_GLOBAL                     4: os
                18      LOAD_ATTR                       5: environ
                20      LOAD_METHOD                     6: copy
                22      CALL_METHOD                     0
                24      LOAD_CONST                      1: True
                26      LOAD_CONST                      1: True
                28      LOAD_FAST                       2: timeout
                30      LOAD_CONST                      2: ('cwd', 'env', 'capture_output', 'text', 'timeout')
                32      CALL_FUNCTION_KW                6
                34      STORE_FAST                      3: proc
                36      LOAD_FAST                       3: proc
                38      LOAD_ATTR                       7: returncode
                40      LOAD_FAST                       3: proc
                42      LOAD_ATTR                       8: stdout
                44      LOAD_FAST                       3: proc
                46      LOAD_ATTR                       9: stderr
                48      BUILD_TUPLE                     3
                50      RETURN_VALUE                    
        '_run'
        'Dict[str, Any]'
        (
            'cfg'
            'return'
        )
        [Code]
            File Name: /Users/s/openclaw-memory-auto/scripts/connect.py
            Object Name: _pick_core_python
            Arg Count: 1
            Pos Only Arg Count: 0
            KW Only Arg Count: 0
            Locals: 3
            Stack Size: 5
            Flags: 0x01000043 (CO_OPTIMIZED | CO_NEWLOCALS | CO_NOFREE | CO_FUTURE_ANNOTATIONS)
            [Names]
                'expand_keep'
                'get'
                'exists'
                'str'
                'expand'
                'sys'
                'executable'
            [Var Names]
                'cfg'
                'core'
                'bridge'
            [Free Vars]
            [Cell Vars]
            [Constants]
                None
                'memory_core'
                'core_venv_python'
                '~/.codex/skills/openclaw-memory/.venv/bin/python'
                'bridge_env'
                'venv_dir'
                '~/openclaw-memory-auto/.venv'
                'bin'
                'python'
            [Disassembly]
                0       LOAD_GLOBAL                     0: expand_keep
                2       LOAD_FAST                       0: cfg
                4       LOAD_METHOD                     1: get
                6       LOAD_CONST                      1: 'memory_core'
                8       BUILD_MAP                       0
                10      CALL_METHOD                     2
                12      LOAD_METHOD                     1: get
                14      LOAD_CONST                      2: 'core_venv_python'
                16      LOAD_CONST                      3: '~/.codex/skills/openclaw-memory/.venv/bin/python'
                18      CALL_METHOD                     2
                20      CALL_FUNCTION                   1
                22      STORE_FAST                      1: core
                24      LOAD_FAST                       1: core
                26      LOAD_METHOD                     2: exists
                28      CALL_METHOD                     0
                30      POP_JUMP_IF_FALSE               40
                32      LOAD_GLOBAL                     3: str
                34      LOAD_FAST                       1: core
                36      CALL_FUNCTION                   1
                38      RETURN_VALUE                    
                40      LOAD_GLOBAL                     4: expand
                42      LOAD_FAST                       0: cfg
                44      LOAD_METHOD                     1: get
                46      LOAD_CONST                      4: 'bridge_env'
                48      BUILD_MAP                       0
                50      CALL_METHOD                     2
                52      LOAD_METHOD                     1: get
                54      LOAD_CONST                      5: 'venv_dir'
                56      LOAD_CONST                      6: '~/openclaw-memory-auto/.venv'
                58      CALL_METHOD                     2
                60      CALL_FUNCTION                   1
                62      LOAD_CONST                      7: 'bin'
                64      BINARY_TRUE_DIVIDE              
                66      LOAD_CONST                      8: 'python'
                68      BINARY_TRUE_DIVIDE              
                70      STORE_FAST                      2: bridge
                72      LOAD_FAST                       2: bridge
                74      LOAD_METHOD                     2: exists
                76      CALL_METHOD                     0
                78      POP_JUMP_IF_FALSE               88
                80      LOAD_GLOBAL                     3: str
                82      LOAD_FAST                       2: bridge
                84      CALL_FUNCTION                   1
                86      RETURN_VALUE                    
                88      LOAD_GLOBAL                     5: sys
                90      LOAD_ATTR                       6: executable
                92      RETURN_VALUE                    
        '_pick_core_python'
        [Code]
            File Name: /Users/s/openclaw-memory-auto/scripts/connect.py
            Object Name: _detect_targets
            Arg Count: 1
            Pos Only Arg Count: 0
            KW Only Arg Count: 0
            Locals: 6
            Stack Size: 6
            Flags: 0x01000043 (CO_OPTIMIZED | CO_NEWLOCALS | CO_NOFREE | CO_FUTURE_ANNOTATIONS)
            [Names]
                'adapter_registry.scan_tools'
                'scan_mcp_tools'
                'get'
                'str'
                'lower'
                'append'
            [Var Names]
                'cfg'
                'scan_mcp_tools'
                'found'
                'keys'
                'item'
                'name'
            [Free Vars]
            [Cell Vars]
            [Constants]
                None
                0
                (
                    'scan_mcp_tools'
                )
                'scan'
                'scan_paths'
                'name'
                ''
                'claude'
                'claude_desktop'
                'cursor'
                'windsurf'
            [Disassembly]
                0       LOAD_CONST                      1: 0
                2       LOAD_CONST                      2: ('scan_mcp_tools',)
                4       IMPORT_NAME                     0: adapter_registry.scan_tools
                6       IMPORT_FROM                     1: scan_mcp_tools
                8       STORE_FAST                      1: scan_mcp_tools
                10      POP_TOP                         
                12      LOAD_FAST                       1: scan_mcp_tools
                14      LOAD_FAST                       0: cfg
                16      LOAD_METHOD                     2: get
                18      LOAD_CONST                      3: 'scan'
                20      BUILD_MAP                       0
                22      CALL_METHOD                     2
                24      LOAD_METHOD                     2: get
                26      LOAD_CONST                      4: 'scan_paths'
                28      BUILD_MAP                       0
                30      CALL_METHOD                     2
                32      CALL_FUNCTION                   1
                34      STORE_FAST                      2: found
                36      BUILD_LIST                      0
                38      STORE_FAST                      3: keys
                40      LOAD_FAST                       2: found
                42      GET_ITER                        
                44      FOR_ITER                        106 (to 152)
                46      STORE_FAST                      4: item
                48      LOAD_GLOBAL                     3: str
                50      LOAD_FAST                       4: item
                52      LOAD_METHOD                     2: get
                54      LOAD_CONST                      5: 'name'
                56      LOAD_CONST                      6: ''
                58      CALL_METHOD                     2
                60      CALL_FUNCTION                   1
                62      LOAD_METHOD                     4: lower
                64      CALL_METHOD                     0
                66      STORE_FAST                      5: name
                68      LOAD_CONST                      7: 'claude'
                70      LOAD_FAST                       5: name
                72      CONTAINS_OP                     0 (in)
                74      POP_JUMP_IF_FALSE               96
                76      LOAD_CONST                      8: 'claude_desktop'
                78      LOAD_FAST                       3: keys
                80      CONTAINS_OP                     1 (not in)
                82      POP_JUMP_IF_FALSE               96
                84      LOAD_FAST                       3: keys
                86      LOAD_METHOD                     5: append
                88      LOAD_CONST                      8: 'claude_desktop'
                90      CALL_METHOD                     1
                92      POP_TOP                         
                94      JUMP_ABSOLUTE                   44
                96      LOAD_CONST                      9: 'cursor'
                98      LOAD_FAST                       5: name
                100     CONTAINS_OP                     0 (in)
                102     POP_JUMP_IF_FALSE               124
                104     LOAD_CONST                      9: 'cursor'
                106     LOAD_FAST                       3: keys
                108     CONTAINS_OP                     1 (not in)
                110     POP_JUMP_IF_FALSE               124
                112     LOAD_FAST                       3: keys
                114     LOAD_METHOD                     5: append
                116     LOAD_CONST                      9: 'cursor'
                118     CALL_METHOD                     1
                120     POP_TOP                         
                122     JUMP_ABSOLUTE                   44
                124     LOAD_CONST                      10: 'windsurf'
                126     LOAD_FAST                       5: name
                128     CONTAINS_OP                     0 (in)
                130     POP_JUMP_IF_FALSE               44
                132     LOAD_CONST                      10: 'windsurf'
                134     LOAD_FAST                       3: keys
                136     CONTAINS_OP                     1 (not in)
                138     POP_JUMP_IF_FALSE               44
                140     LOAD_FAST                       3: keys
                142     LOAD_METHOD                     5: append
                144     LOAD_CONST                      10: 'windsurf'
                146     CALL_METHOD                     1
                148     POP_TOP                         
                150     JUMP_ABSOLUTE                   44
                152     LOAD_FAST                       3: keys
                154     RETURN_VALUE                    
        '_detect_targets'
        'List[Dict[str, Any]]'
        'None'
        (
            'report'
            'name'
            'rc'
            'out'
            'err'
            'return'
        )
        [Code]
            File Name: /Users/s/openclaw-memory-auto/scripts/connect.py
            Object Name: _step
            Arg Count: 5
            Pos Only Arg Count: 0
            KW Only Arg Count: 0
            Locals: 5
            Stack Size: 9
            Flags: 0x01000043 (CO_OPTIMIZED | CO_NEWLOCALS | CO_NOFREE | CO_FUTURE_ANNOTATIONS)
            [Names]
                'append'
                'strip'
                '_now'
            [Var Names]
                'report'
                'name'
                'rc'
                'out'
                'err'
            [Free Vars]
            [Cell Vars]
            [Constants]
                None
                0
                ''
                -4000
                (
                    'step'
                    'ok'
                    'rc'
                    'stdout'
                    'stderr'
                    'timestamp'
                )
            [Disassembly]
                0       LOAD_FAST                       0: report
                2       LOAD_METHOD                     0: append
                4       LOAD_FAST                       1: name
                6       LOAD_FAST                       2: rc
                8       LOAD_CONST                      1: 0
                10      COMPARE_OP                      2 (==)
                12      LOAD_FAST                       2: rc
                14      LOAD_FAST                       3: out
                16      JUMP_IF_TRUE_OR_POP             20
                18      LOAD_CONST                      2: ''
                20      LOAD_METHOD                     1: strip
                22      CALL_METHOD                     0
                24      LOAD_CONST                      3: -4000
                26      LOAD_CONST                      0: None
                28      BUILD_SLICE                     2
                30      BINARY_SUBSCR                   
                32      LOAD_FAST                       4: err
                34      JUMP_IF_TRUE_OR_POP             38
                36      LOAD_CONST                      2: ''
                38      LOAD_METHOD                     1: strip
                40      CALL_METHOD                     0
                42      LOAD_CONST                      3: -4000
                44      LOAD_CONST                      0: None
                46      BUILD_SLICE                     2
                48      BINARY_SUBSCR                   
                50      LOAD_GLOBAL                     2: _now
                52      CALL_FUNCTION                   0
                54      LOAD_CONST                      4: ('step', 'ok', 'rc', 'stdout', 'stderr', 'timestamp')
                56      BUILD_CONST_KEY_MAP             6
                58      CALL_METHOD                     1
                60      POP_TOP                         
                62      LOAD_CONST                      0: None
                64      RETURN_VALUE                    
        '_step'
        (
            'script_name'
            'env'
            'return'
        )
        [Code]
            File Name: /Users/s/openclaw-memory-auto/scripts/connect.py
            Object Name: _run_py
            Arg Count: 2
            Pos Only Arg Count: 0
            KW Only Arg Count: 0
            Locals: 2
            Stack Size: 5
            Flags: 0x01000043 (CO_OPTIMIZED | CO_NEWLOCALS | CO_NOFREE | CO_FUTURE_ANNOTATIONS)
            [Names]
                '_run'
                'sys'
                'executable'
                'str'
                'ROOT'
            [Var Names]
                'script_name'
                'env'
            [Free Vars]
            [Cell Vars]
            [Constants]
                None
                'scripts'
                (
                    'env'
                )
            [Disassembly]
                0       LOAD_GLOBAL                     0: _run
                2       LOAD_GLOBAL                     1: sys
                4       LOAD_ATTR                       2: executable
                6       LOAD_GLOBAL                     3: str
                8       LOAD_GLOBAL                     4: ROOT
                10      LOAD_CONST                      1: 'scripts'
                12      BINARY_TRUE_DIVIDE              
                14      LOAD_FAST                       0: script_name
                16      BINARY_TRUE_DIVIDE              
                18      CALL_FUNCTION                   1
                20      BUILD_LIST                      2
                22      LOAD_FAST                       1: env
                24      LOAD_CONST                      2: ('env',)
                26      CALL_FUNCTION_KW                2
                28      RETURN_VALUE                    
        '_run_py'
        [Code]
            File Name: /Users/s/openclaw-memory-auto/scripts/connect.py
            Object Name: main
            Arg Count: 0
            Pos Only Arg Count: 0
            KW Only Arg Count: 0
            Locals: 35
            Stack Size: 13
            Flags: 0x01000043 (CO_OPTIMIZED | CO_NEWLOCALS | CO_NOFREE | CO_FUTURE_ANNOTATIONS)
            [Names]
                'argparse'
                'ArgumentParser'
                'add_argument'
                'parse_args'
                'load_cfg'
                '_pick_core_python'
                '_detect_targets'
                'targets'
                'strip'
                'join'
                'snapshot_config'
                '_now'
                'bool'
                'dry_run'
                'split'
                'ROOT'
                'write_json'
                'print'
                'json'
                'dumps'
                'skip_install'
                '_run_py'
                '_step'
                'os'
                'environ'
                'copy'
                'str'
                'append'
                'expand'
                '_run'
                'strict'
                'ConnectResult'
                'get'
                'rollback_on_fail'
                'rolled_back'
                'status'
                'finished_at'
                'len'
                'details'
                'to_dict'
            [Var Names]
                'parser'
                'args'
                'cfg'
                'core_py'
                'detected'
                'targets'
                'snap'
                'report'
                'out'
                'rc'
                'err'
                'env_scan'
                'env_apply'
                'env_verify'
                'rc_verify'
                'out_verify'
                'err_verify'
                'heal'
                'env_smoke'
                'rc_smoke'
                'out_smoke'
                'err_smoke'
                'rc_doc'
                'out_doc'
                'err_doc'
                'ok_verify'
                'ok_smoke'
                'ok_doctor'
                'overall_ok'
                'conn_result'
                'env_rb'
                'rc_rb'
                'out_rb'
                'err_rb'
                'out_file'
            [Free Vars]
            [Cell Vars]
            [Constants]
                None
                'One-shot no-touch onboarding for OpenClaw memory MCP.'
                (
                    'description'
                )
                '--dry-run'
                'store_true'
                'Show plan only, no file changes.'
                (
                    'action'
                    'help'
                )
                '--rollback-on-fail'
                'Rollback client config on failure.'
                '--strict'
                'Require smoke+verify+doctor all pass.'
                '--skip-install'
                'Skip dependency install step.'
                '--targets'
                ''
                'Comma-separated targets, e.g. claude_desktop,cursor,windsurf'
                (
                    'default'
                    'help'
                )
                ','
                'claude_desktop,cursor,windsurf'
                (
                    'started_at'
                    'snapshot'
                    'dry_run'
                    'detected_targets'
                    'target_keys'
                    'steps'
                    'self_heal'
                )
                'dry_run'
                'status'
                'install_env'
                'scan_register'
                'generate_client_configs'
                'apply_client_configs(targets='
                ')'
                'verify_client_configs(targets='
                'smoke_test'
                'doctor'
                'plan'
                'runtime'
                'connect_report.json'
                False
                2
                (
                    'ensure_ascii'
                    'indent'
                )
                0
                'install_env.py'
                'steps'
                'PYTHONPATH'
                'scan_register.py'
                (
                    'env'
                )
                'generate_client_configs.py'
                'OCMA_TARGET_KEYS'
                'apply_client_configs.py'
                'apply_client_configs'
                'verify_client_configs.py'
                'verify_client_configs'
                'verify_heal'
                (
                    'kind'
                    'actions'
                )
                'actions'
                (
                    'action'
                    'rc'
                )
                'self_heal'
                'verify_client_configs_after_heal'
                ':'
                '~/.codex/skills/openclaw-memory/python'
                'scripts'
                'smoke_test.py'
                '--compact'
                'smoke_heal'
                'smoke_test_retry'
                'smoke_test_after_heal'
                'doctor.py'
                True
                'ready'
                'degraded'
                'started_at'
                (
                    'status'
                    'detected_targets'
                    'verify_ok'
                    'smoke_ok'
                    'doctor_ok'
                    'rolled_back'
                    'strict'
                    'started_at'
                    'finished_at'
                    'details'
                )
                (
                    'verify_ok'
                    'smoke_ok'
                    'doctor_ok'
                    'overall_ok'
                    'strict'
                )
                'result'
                'rollback_client_configs.py'
                'rollback_client_configs'
                'rolled_back'
                'finished_at'
                (
                    'steps_count'
                    'self_heal_count'
                    'snapshot'
                )
                'connect_result'
                1
            [Disassembly]
                0       LOAD_GLOBAL                     0: argparse
                2       LOAD_ATTR                       1: ArgumentParser
                4       LOAD_CONST                      1: 'One-shot no-touch onboarding for OpenClaw memory MCP.'
                6       LOAD_CONST                      2: ('description',)
                8       CALL_FUNCTION_KW                1
                10      STORE_FAST                      0: parser
                12      LOAD_FAST                       0: parser
                14      LOAD_ATTR                       2: add_argument
                16      LOAD_CONST                      3: '--dry-run'
                18      LOAD_CONST                      4: 'store_true'
                20      LOAD_CONST                      5: 'Show plan only, no file changes.'
                22      LOAD_CONST                      6: ('action', 'help')
                24      CALL_FUNCTION_KW                3
                26      POP_TOP                         
                28      LOAD_FAST                       0: parser
                30      LOAD_ATTR                       2: add_argument
                32      LOAD_CONST                      7: '--rollback-on-fail'
                34      LOAD_CONST                      4: 'store_true'
                36      LOAD_CONST                      8: 'Rollback client config on failure.'
                38      LOAD_CONST                      6: ('action', 'help')
                40      CALL_FUNCTION_KW                3
                42      POP_TOP                         
                44      LOAD_FAST                       0: parser
                46      LOAD_ATTR                       2: add_argument
                48      LOAD_CONST                      9: '--strict'
                50      LOAD_CONST                      4: 'store_true'
                52      LOAD_CONST                      10: 'Require smoke+verify+doctor all pass.'
                54      LOAD_CONST                      6: ('action', 'help')
                56      CALL_FUNCTION_KW                3
                58      POP_TOP                         
                60      LOAD_FAST                       0: parser
                62      LOAD_ATTR                       2: add_argument
                64      LOAD_CONST                      11: '--skip-install'
                66      LOAD_CONST                      4: 'store_true'
                68      LOAD_CONST                      12: 'Skip dependency install step.'
                70      LOAD_CONST                      6: ('action', 'help')
                72      CALL_FUNCTION_KW                3
                74      POP_TOP                         
                76      LOAD_FAST                       0: parser
                78      LOAD_ATTR                       2: add_argument
                80      LOAD_CONST                      13: '--targets'
                82      LOAD_CONST                      14: ''
                84      LOAD_CONST                      15: 'Comma-separated targets, e.g. claude_desktop,cursor,windsurf'
                86      LOAD_CONST                      16: ('default', 'help')
                88      CALL_FUNCTION_KW                3
                90      POP_TOP                         
                92      LOAD_FAST                       0: parser
                94      LOAD_METHOD                     3: parse_args
                96      CALL_METHOD                     0
                98      STORE_FAST                      1: args
                100     LOAD_GLOBAL                     4: load_cfg
                102     CALL_FUNCTION                   0
                104     STORE_FAST                      2: cfg
                106     LOAD_GLOBAL                     5: _pick_core_python
                108     LOAD_FAST                       2: cfg
                110     CALL_FUNCTION                   1
                112     STORE_FAST                      3: core_py
                114     LOAD_GLOBAL                     6: _detect_targets
                116     LOAD_FAST                       2: cfg
                118     CALL_FUNCTION                   1
                120     STORE_FAST                      4: detected
                122     LOAD_FAST                       1: args
                124     LOAD_ATTR                       7: targets
                126     LOAD_METHOD                     8: strip
                128     CALL_METHOD                     0
                130     JUMP_IF_TRUE_OR_POP             148
                132     LOAD_FAST                       4: detected
                134     POP_JUMP_IF_FALSE               146
                136     LOAD_CONST                      17: ','
                138     LOAD_METHOD                     9: join
                140     LOAD_FAST                       4: detected
                142     CALL_METHOD                     1
                144     JUMP_FORWARD                    2 (to 148)
                146     LOAD_CONST                      18: 'claude_desktop,cursor,windsurf'
                148     STORE_FAST                      5: targets
                150     LOAD_GLOBAL                     10: snapshot_config
                152     CALL_FUNCTION                   0
                154     STORE_FAST                      6: snap
                156     LOAD_GLOBAL                     11: _now
                158     CALL_FUNCTION                   0
                160     LOAD_FAST                       6: snap
                162     LOAD_GLOBAL                     12: bool
                164     LOAD_FAST                       1: args
                166     LOAD_ATTR                       13: dry_run
                168     CALL_FUNCTION                   1
                170     LOAD_FAST                       4: detected
                172     LOAD_FAST                       5: targets
                174     LOAD_METHOD                     14: split
                176     LOAD_CONST                      17: ','
                178     CALL_METHOD                     1
                180     BUILD_LIST                      0
                182     BUILD_LIST                      0
                184     LOAD_CONST                      19: ('started_at', 'snapshot', 'dry_run', 'detected_targets', 'target_keys', 'steps', 'self_heal')
                186     BUILD_CONST_KEY_MAP             7
                188     STORE_FAST                      7: report
                190     LOAD_FAST                       1: args
                192     LOAD_ATTR                       13: dry_run
                194     POP_JUMP_IF_FALSE               290
                198     LOAD_CONST                      20: 'dry_run'
                200     LOAD_FAST                       7: report
                202     LOAD_CONST                      21: 'status'
                204     STORE_SUBSCR                    
                206     LOAD_CONST                      22: 'install_env'
                208     LOAD_CONST                      23: 'scan_register'
                210     LOAD_CONST                      24: 'generate_client_configs'
                212     LOAD_CONST                      25: 'apply_client_configs(targets='
                214     LOAD_FAST                       5: targets
                216     FORMAT_VALUE                    0 (FVC_NONE)
                218     LOAD_CONST                      26: ')'
                220     BUILD_STRING                    3
                222     LOAD_CONST                      27: 'verify_client_configs(targets='
                224     LOAD_FAST                       5: targets
                226     FORMAT_VALUE                    0 (FVC_NONE)
                228     LOAD_CONST                      26: ')'
                230     BUILD_STRING                    3
                232     LOAD_CONST                      28: 'smoke_test'
                234     LOAD_CONST                      29: 'doctor'
                236     BUILD_LIST                      7
                238     LOAD_FAST                       7: report
                240     LOAD_CONST                      30: 'plan'
                242     STORE_SUBSCR                    
                244     LOAD_GLOBAL                     15: ROOT
                246     LOAD_CONST                      31: 'runtime'
                248     BINARY_TRUE_DIVIDE              
                250     LOAD_CONST                      32: 'connect_report.json'
                252     BINARY_TRUE_DIVIDE              
                254     STORE_FAST                      8: out
                256     LOAD_GLOBAL                     16: write_json
                258     LOAD_FAST                       8: out
                260     LOAD_FAST                       7: report
                262     CALL_FUNCTION                   2
                264     POP_TOP                         
                266     LOAD_GLOBAL                     17: print
                268     LOAD_GLOBAL                     18: json
                270     LOAD_ATTR                       19: dumps
                272     LOAD_FAST                       7: report
                274     LOAD_CONST                      33: False
                276     LOAD_CONST                      34: 2
                278     LOAD_CONST                      35: ('ensure_ascii', 'indent')
                280     CALL_FUNCTION_KW                3
                282     CALL_FUNCTION                   1
                284     POP_TOP                         
                286     LOAD_CONST                      36: 0
                288     RETURN_VALUE                    
                290     LOAD_FAST                       1: args
                292     LOAD_ATTR                       20: skip_install
                294     POP_JUMP_IF_TRUE                332
                298     LOAD_GLOBAL                     21: _run_py
                300     LOAD_CONST                      37: 'install_env.py'
                302     CALL_FUNCTION                   1
                304     UNPACK_SEQUENCE                 3
                306     STORE_FAST                      9: rc
                308     STORE_FAST                      8: out
                310     STORE_FAST                      10: err
                312     LOAD_GLOBAL                     22: _step
                314     LOAD_FAST                       7: report
                316     LOAD_CONST                      38: 'steps'
                318     BINARY_SUBSCR                   
                320     LOAD_CONST                      22: 'install_env'
                322     LOAD_FAST                       9: rc
                324     LOAD_FAST                       8: out
                326     LOAD_FAST                       10: err
                328     CALL_FUNCTION                   5
                330     POP_TOP                         
                332     LOAD_GLOBAL                     23: os
                334     LOAD_ATTR                       24: environ
                336     LOAD_METHOD                     25: copy
                338     CALL_METHOD                     0
                340     STORE_FAST                      11: env_scan
                342     LOAD_GLOBAL                     26: str
                344     LOAD_GLOBAL                     15: ROOT
                346     CALL_FUNCTION                   1
                348     LOAD_FAST                       11: env_scan
                350     LOAD_CONST                      39: 'PYTHONPATH'
                352     STORE_SUBSCR                    
                354     LOAD_GLOBAL                     21: _run_py
                356     LOAD_CONST                      40: 'scan_register.py'
                358     LOAD_FAST                       11: env_scan
                360     LOAD_CONST                      41: ('env',)
                362     CALL_FUNCTION_KW                2
                364     UNPACK_SEQUENCE                 3
                366     STORE_FAST                      9: rc
                368     STORE_FAST                      8: out
                370     STORE_FAST                      10: err
                372     LOAD_GLOBAL                     22: _step
                374     LOAD_FAST                       7: report
                376     LOAD_CONST                      38: 'steps'
                378     BINARY_SUBSCR                   
                380     LOAD_CONST                      23: 'scan_register'
                382     LOAD_FAST                       9: rc
                384     LOAD_FAST                       8: out
                386     LOAD_FAST                       10: err
                388     CALL_FUNCTION                   5
                390     POP_TOP                         
                392     LOAD_GLOBAL                     21: _run_py
                394     LOAD_CONST                      42: 'generate_client_configs.py'
                396     CALL_FUNCTION                   1
                398     UNPACK_SEQUENCE                 3
                400     STORE_FAST                      9: rc
                402     STORE_FAST                      8: out
                404     STORE_FAST                      10: err
                406     LOAD_GLOBAL                     22: _step
                408     LOAD_FAST                       7: report
                410     LOAD_CONST                      38: 'steps'
                412     BINARY_SUBSCR                   
                414     LOAD_CONST                      24: 'generate_client_configs'
                416     LOAD_FAST                       9: rc
                418     LOAD_FAST                       8: out
                420     LOAD_FAST                       10: err
                422     CALL_FUNCTION                   5
                424     POP_TOP                         
                426     LOAD_GLOBAL                     23: os
                428     LOAD_ATTR                       24: environ
                430     LOAD_METHOD                     25: copy
                432     CALL_METHOD                     0
                434     STORE_FAST                      12: env_apply
                436     LOAD_FAST                       5: targets
                438     LOAD_FAST                       12: env_apply
                440     LOAD_CONST                      43: 'OCMA_TARGET_KEYS'
                442     STORE_SUBSCR                    
                444     LOAD_GLOBAL                     21: _run_py
                446     LOAD_CONST                      44: 'apply_client_configs.py'
                448     LOAD_FAST                       12: env_apply
                450     LOAD_CONST                      41: ('env',)
                452     CALL_FUNCTION_KW                2
                454     UNPACK_SEQUENCE                 3
                456     STORE_FAST                      9: rc
                458     STORE_FAST                      8: out
                460     STORE_FAST                      10: err
                462     LOAD_GLOBAL                     22: _step
                464     LOAD_FAST                       7: report
                466     LOAD_CONST                      38: 'steps'
                468     BINARY_SUBSCR                   
                470     LOAD_CONST                      45: 'apply_client_configs'
                472     LOAD_FAST                       9: rc
                474     LOAD_FAST                       8: out
                476     LOAD_FAST                       10: err
                478     CALL_FUNCTION                   5
                480     POP_TOP                         
                482     LOAD_GLOBAL                     23: os
                484     LOAD_ATTR                       24: environ
                486     LOAD_METHOD                     25: copy
                488     CALL_METHOD                     0
                490     STORE_FAST                      13: env_verify
                492     LOAD_FAST                       5: targets
                494     LOAD_FAST                       13: env_verify
                496     LOAD_CONST                      43: 'OCMA_TARGET_KEYS'
                498     STORE_SUBSCR                    
                500     LOAD_GLOBAL                     21: _run_py
                502     LOAD_CONST                      46: 'verify_client_configs.py'
                504     LOAD_FAST                       13: env_verify
                506     LOAD_CONST                      41: ('env',)
                508     CALL_FUNCTION_KW                2
                510     UNPACK_SEQUENCE                 3
                512     STORE_FAST                      14: rc_verify
                514     STORE_FAST                      15: out_verify
                516     STORE_FAST                      16: err_verify
                518     LOAD_GLOBAL                     22: _step
                520     LOAD_FAST                       7: report
                522     LOAD_CONST                      38: 'steps'
                524     BINARY_SUBSCR                   
                526     LOAD_CONST                      47: 'verify_client_configs'
                528     LOAD_FAST                       14: rc_verify
                530     LOAD_FAST                       15: out_verify
                532     LOAD_FAST                       16: err_verify
                534     CALL_FUNCTION                   5
                536     POP_TOP                         
                538     LOAD_FAST                       14: rc_verify
                540     LOAD_CONST                      36: 0
                542     COMPARE_OP                      3 (!=)
                544     POP_JUMP_IF_FALSE               702
                548     LOAD_CONST                      48: 'verify_heal'
                550     BUILD_LIST                      0
                552     LOAD_CONST                      49: ('kind', 'actions')
                554     BUILD_CONST_KEY_MAP             2
                556     STORE_FAST                      17: heal
                558     LOAD_GLOBAL                     21: _run_py
                560     LOAD_CONST                      42: 'generate_client_configs.py'
                562     CALL_FUNCTION                   1
                564     UNPACK_SEQUENCE                 3
                566     STORE_FAST                      9: rc
                568     STORE_FAST                      8: out
                570     STORE_FAST                      10: err
                572     LOAD_FAST                       17: heal
                574     LOAD_CONST                      50: 'actions'
                576     BINARY_SUBSCR                   
                578     LOAD_METHOD                     27: append
                580     LOAD_CONST                      24: 'generate_client_configs'
                582     LOAD_FAST                       9: rc
                584     LOAD_CONST                      51: ('action', 'rc')
                586     BUILD_CONST_KEY_MAP             2
                588     CALL_METHOD                     1
                590     POP_TOP                         
                592     LOAD_GLOBAL                     21: _run_py
                594     LOAD_CONST                      44: 'apply_client_configs.py'
                596     LOAD_FAST                       12: env_apply
                598     LOAD_CONST                      41: ('env',)
                600     CALL_FUNCTION_KW                2
                602     UNPACK_SEQUENCE                 3
                604     STORE_FAST                      9: rc
                606     STORE_FAST                      8: out
                608     STORE_FAST                      10: err
                610     LOAD_FAST                       17: heal
                612     LOAD_CONST                      50: 'actions'
                614     BINARY_SUBSCR                   
                616     LOAD_METHOD                     27: append
                618     LOAD_CONST                      45: 'apply_client_configs'
                620     LOAD_FAST                       9: rc
                622     LOAD_CONST                      51: ('action', 'rc')
                624     BUILD_CONST_KEY_MAP             2
                626     CALL_METHOD                     1
                628     POP_TOP                         
                630     LOAD_GLOBAL                     21: _run_py
                632     LOAD_CONST                      46: 'verify_client_configs.py'
                634     LOAD_FAST                       13: env_verify
                636     LOAD_CONST                      41: ('env',)
                638     CALL_FUNCTION_KW                2
                640     UNPACK_SEQUENCE                 3
                642     STORE_FAST                      14: rc_verify
                644     STORE_FAST                      15: out_verify
                646     STORE_FAST                      16: err_verify
                648     LOAD_FAST                       17: heal
                650     LOAD_CONST                      50: 'actions'
                652     BINARY_SUBSCR                   
                654     LOAD_METHOD                     27: append
                656     LOAD_CONST                      47: 'verify_client_configs'
                658     LOAD_FAST                       14: rc_verify
                660     LOAD_CONST                      51: ('action', 'rc')
                662     BUILD_CONST_KEY_MAP             2
                664     CALL_METHOD                     1
                666     POP_TOP                         
                668     LOAD_FAST                       7: report
                670     LOAD_CONST                      52: 'self_heal'
                672     BINARY_SUBSCR                   
                674     LOAD_METHOD                     27: append
                676     LOAD_FAST                       17: heal
                678     CALL_METHOD                     1
                680     POP_TOP                         
                682     LOAD_GLOBAL                     22: _step
                684     LOAD_FAST                       7: report
                686     LOAD_CONST                      38: 'steps'
                688     BINARY_SUBSCR                   
                690     LOAD_CONST                      53: 'verify_client_configs_after_heal'
                692     LOAD_FAST                       14: rc_verify
                694     LOAD_FAST                       15: out_verify
                696     LOAD_FAST                       16: err_verify
                698     CALL_FUNCTION                   5
                700     POP_TOP                         
                702     LOAD_GLOBAL                     23: os
                704     LOAD_ATTR                       24: environ
                706     LOAD_METHOD                     25: copy
                708     CALL_METHOD                     0
                710     STORE_FAST                      18: env_smoke
                712     LOAD_GLOBAL                     15: ROOT
                714     FORMAT_VALUE                    0 (FVC_NONE)
                716     LOAD_CONST                      54: ':'
                718     LOAD_GLOBAL                     28: expand
                720     LOAD_CONST                      55: '~/.codex/skills/openclaw-memory/python'
                722     CALL_FUNCTION                   1
                724     FORMAT_VALUE                    0 (FVC_NONE)
                726     BUILD_STRING                    3
                728     LOAD_FAST                       18: env_smoke
                730     LOAD_CONST                      39: 'PYTHONPATH'
                732     STORE_SUBSCR                    
                734     LOAD_GLOBAL                     29: _run
                736     LOAD_FAST                       3: core_py
                738     LOAD_GLOBAL                     26: str
                740     LOAD_GLOBAL                     15: ROOT
                742     LOAD_CONST                      56: 'scripts'
                744     BINARY_TRUE_DIVIDE              
                746     LOAD_CONST                      57: 'smoke_test.py'
                748     BINARY_TRUE_DIVIDE              
                750     CALL_FUNCTION                   1
                752     LOAD_CONST                      58: '--compact'
                754     BUILD_LIST                      3
                756     LOAD_FAST                       18: env_smoke
                758     LOAD_CONST                      41: ('env',)
                760     CALL_FUNCTION_KW                2
                762     UNPACK_SEQUENCE                 3
                764     STORE_FAST                      19: rc_smoke
                766     STORE_FAST                      20: out_smoke
                768     STORE_FAST                      21: err_smoke
                770     LOAD_GLOBAL                     22: _step
                772     LOAD_FAST                       7: report
                774     LOAD_CONST                      38: 'steps'
                776     BINARY_SUBSCR                   
                778     LOAD_CONST                      28: 'smoke_test'
                780     LOAD_FAST                       19: rc_smoke
                782     LOAD_FAST                       20: out_smoke
                784     LOAD_FAST                       21: err_smoke
                786     CALL_FUNCTION                   5
                788     POP_TOP                         
                790     LOAD_FAST                       19: rc_smoke
                792     LOAD_CONST                      36: 0
                794     COMPARE_OP                      3 (!=)
                796     POP_JUMP_IF_FALSE               934
                800     LOAD_CONST                      59: 'smoke_heal'
                802     BUILD_LIST                      0
                804     LOAD_CONST                      49: ('kind', 'actions')
                806     BUILD_CONST_KEY_MAP             2
                808     STORE_FAST                      17: heal
                810     LOAD_GLOBAL                     21: _run_py
                812     LOAD_CONST                      37: 'install_env.py'
                814     CALL_FUNCTION                   1
                816     UNPACK_SEQUENCE                 3
                818     STORE_FAST                      9: rc
                820     STORE_FAST                      8: out
                822     STORE_FAST                      10: err
                824     LOAD_FAST                       17: heal
                826     LOAD_CONST                      50: 'actions'
                828     BINARY_SUBSCR                   
                830     LOAD_METHOD                     27: append
                832     LOAD_CONST                      22: 'install_env'
                834     LOAD_FAST                       9: rc
                836     LOAD_CONST                      51: ('action', 'rc')
                838     BUILD_CONST_KEY_MAP             2
                840     CALL_METHOD                     1
                842     POP_TOP                         
                844     LOAD_GLOBAL                     29: _run
                846     LOAD_FAST                       3: core_py
                848     LOAD_GLOBAL                     26: str
                850     LOAD_GLOBAL                     15: ROOT
                852     LOAD_CONST                      56: 'scripts'
                854     BINARY_TRUE_DIVIDE              
                856     LOAD_CONST                      57: 'smoke_test.py'
                858     BINARY_TRUE_DIVIDE              
                860     CALL_FUNCTION                   1
                862     LOAD_CONST                      58: '--compact'
                864     BUILD_LIST                      3
                866     LOAD_FAST                       18: env_smoke
                868     LOAD_CONST                      41: ('env',)
                870     CALL_FUNCTION_KW                2
                872     UNPACK_SEQUENCE                 3
                874     STORE_FAST                      19: rc_smoke
                876     STORE_FAST                      20: out_smoke
                878     STORE_FAST                      21: err_smoke
                880     LOAD_FAST                       17: heal
                882     LOAD_CONST                      50: 'actions'
                884     BINARY_SUBSCR                   
                886     LOAD_METHOD                     27: append
                888     LOAD_CONST                      60: 'smoke_test_retry'
                890     LOAD_FAST                       19: rc_smoke
                892     LOAD_CONST                      51: ('action', 'rc')
                894     BUILD_CONST_KEY_MAP             2
                896     CALL_METHOD                     1
                898     POP_TOP                         
                900     LOAD_FAST                       7: report
                902     LOAD_CONST                      52: 'self_heal'
                904     BINARY_SUBSCR                   
                906     LOAD_METHOD                     27: append
                908     LOAD_FAST                       17: heal
                910     CALL_METHOD                     1
                912     POP_TOP                         
                914     LOAD_GLOBAL                     22: _step
                916     LOAD_FAST                       7: report
                918     LOAD_CONST                      38: 'steps'
                920     BINARY_SUBSCR                   
                922     LOAD_CONST                      61: 'smoke_test_after_heal'
                924     LOAD_FAST                       19: rc_smoke
                926     LOAD_FAST                       20: out_smoke
                928     LOAD_FAST                       21: err_smoke
                930     CALL_FUNCTION                   5
                932     POP_TOP                         
                934     LOAD_GLOBAL                     21: _run_py
                936     LOAD_CONST                      62: 'doctor.py'
                938     CALL_FUNCTION                   1
                940     UNPACK_SEQUENCE                 3
                942     STORE_FAST                      22: rc_doc
                944     STORE_FAST                      23: out_doc
                946     STORE_FAST                      24: err_doc
                948     LOAD_GLOBAL                     22: _step
                950     LOAD_FAST                       7: report
                952     LOAD_CONST                      38: 'steps'
                954     BINARY_SUBSCR                   
                956     LOAD_CONST                      29: 'doctor'
                958     LOAD_FAST                       22: rc_doc
                960     LOAD_FAST                       23: out_doc
                962     LOAD_FAST                       24: err_doc
                964     CALL_FUNCTION                   5
                966     POP_TOP                         
                968     LOAD_FAST                       14: rc_verify
                970     LOAD_CONST                      36: 0
                972     COMPARE_OP                      2 (==)
                974     STORE_FAST                      25: ok_verify
                976     LOAD_FAST                       19: rc_smoke
                978     LOAD_CONST                      36: 0
                980     COMPARE_OP                      2 (==)
                982     STORE_FAST                      26: ok_smoke
                984     LOAD_FAST                       22: rc_doc
                986     LOAD_CONST                      36: 0
                988     COMPARE_OP                      2 (==)
                990     STORE_FAST                      27: ok_doctor
                992     LOAD_FAST                       25: ok_verify
                994     JUMP_IF_FALSE_OR_POP            1018
                998     LOAD_FAST                       26: ok_smoke
                1000    JUMP_IF_FALSE_OR_POP            1018
                1004    LOAD_FAST                       1: args
                1006    LOAD_ATTR                       30: strict
                1008    POP_JUMP_IF_FALSE               1016
                1012    LOAD_FAST                       27: ok_doctor
                1014    JUMP_FORWARD                    2 (to 1018)
                1016    LOAD_CONST                      63: True
                1018    STORE_FAST                      28: overall_ok
                1020    LOAD_GLOBAL                     31: ConnectResult
                1022    LOAD_FAST                       28: overall_ok
                1024    POP_JUMP_IF_FALSE               1032
                1028    LOAD_CONST                      64: 'ready'
                1030    JUMP_FORWARD                    2 (to 1034)
                1032    LOAD_CONST                      65: 'degraded'
                1034    LOAD_FAST                       4: detected
                1036    LOAD_FAST                       25: ok_verify
                1038    LOAD_FAST                       26: ok_smoke
                1040    LOAD_FAST                       27: ok_doctor
                1042    LOAD_CONST                      33: False
                1044    LOAD_GLOBAL                     12: bool
                1046    LOAD_FAST                       1: args
                1048    LOAD_ATTR                       30: strict
                1050    CALL_FUNCTION                   1
                1052    LOAD_GLOBAL                     26: str
                1054    LOAD_FAST                       7: report
                1056    LOAD_METHOD                     32: get
                1058    LOAD_CONST                      66: 'started_at'
                1060    LOAD_CONST                      14: ''
                1062    CALL_METHOD                     2
                1064    CALL_FUNCTION                   1
                1066    LOAD_CONST                      14: ''
                1068    BUILD_MAP                       0
                1070    LOAD_CONST                      67: ('status', 'detected_targets', 'verify_ok', 'smoke_ok', 'doctor_ok', 'rolled_back', 'strict', 'started_at', 'finished_at', 'details')
                1072    CALL_FUNCTION_KW                10
                1074    STORE_FAST                      29: conn_result
                1076    LOAD_FAST                       25: ok_verify
                1078    LOAD_FAST                       26: ok_smoke
                1080    LOAD_FAST                       27: ok_doctor
                1082    LOAD_FAST                       28: overall_ok
                1084    LOAD_GLOBAL                     12: bool
                1086    LOAD_FAST                       1: args
                1088    LOAD_ATTR                       30: strict
                1090    CALL_FUNCTION                   1
                1092    LOAD_CONST                      68: ('verify_ok', 'smoke_ok', 'doctor_ok', 'overall_ok', 'strict')
                1094    BUILD_CONST_KEY_MAP             5
                1096    LOAD_FAST                       7: report
                1098    LOAD_CONST                      69: 'result'
                1100    STORE_SUBSCR                    
                1102    LOAD_FAST                       28: overall_ok
                1104    POP_JUMP_IF_TRUE                1200
                1108    LOAD_FAST                       1: args
                1110    LOAD_ATTR                       33: rollback_on_fail
                1112    POP_JUMP_IF_FALSE               1200
                1116    LOAD_GLOBAL                     23: os
                1118    LOAD_ATTR                       24: environ
                1120    LOAD_METHOD                     25: copy
                1122    CALL_METHOD                     0
                1124    STORE_FAST                      30: env_rb
                1126    LOAD_FAST                       5: targets
                1128    LOAD_FAST                       30: env_rb
                1130    LOAD_CONST                      43: 'OCMA_TARGET_KEYS'
                1132    STORE_SUBSCR                    
                1134    LOAD_GLOBAL                     21: _run_py
                1136    LOAD_CONST                      70: 'rollback_client_configs.py'
                1138    LOAD_FAST                       30: env_rb
                1140    LOAD_CONST                      41: ('env',)
                1142    CALL_FUNCTION_KW                2
                1144    UNPACK_SEQUENCE                 3
                1146    STORE_FAST                      31: rc_rb
                1148    STORE_FAST                      32: out_rb
                1150    STORE_FAST                      33: err_rb
                1152    LOAD_GLOBAL                     22: _step
                1154    LOAD_FAST                       7: report
                1156    LOAD_CONST                      38: 'steps'
                1158    BINARY_SUBSCR                   
                1160    LOAD_CONST                      71: 'rollback_client_configs'
                1162    LOAD_FAST                       31: rc_rb
                1164    LOAD_FAST                       32: out_rb
                1166    LOAD_FAST                       33: err_rb
                1168    CALL_FUNCTION                   5
                1170    POP_TOP                         
                1172    LOAD_FAST                       31: rc_rb
                1174    LOAD_CONST                      36: 0
                1176    COMPARE_OP                      2 (==)
                1178    LOAD_FAST                       7: report
                1180    LOAD_CONST                      72: 'rolled_back'
                1182    STORE_SUBSCR                    
                1184    LOAD_GLOBAL                     12: bool
                1186    LOAD_FAST                       7: report
                1188    LOAD_CONST                      72: 'rolled_back'
                1190    BINARY_SUBSCR                   
                1192    CALL_FUNCTION                   1
                1194    LOAD_FAST                       29: conn_result
                1196    STORE_ATTR                      34: rolled_back
                1198    JUMP_FORWARD                    8 (to 1208)
                1200    LOAD_CONST                      33: False
                1202    LOAD_FAST                       7: report
                1204    LOAD_CONST                      72: 'rolled_back'
                1206    STORE_SUBSCR                    
                1208    LOAD_FAST                       29: conn_result
                1210    LOAD_ATTR                       35: status
                1212    LOAD_FAST                       7: report
                1214    LOAD_CONST                      21: 'status'
                1216    STORE_SUBSCR                    
                1218    LOAD_GLOBAL                     11: _now
                1220    CALL_FUNCTION                   0
                1222    LOAD_FAST                       7: report
                1224    LOAD_CONST                      73: 'finished_at'
                1226    STORE_SUBSCR                    
                1228    LOAD_FAST                       7: report
                1230    LOAD_CONST                      73: 'finished_at'
                1232    BINARY_SUBSCR                   
                1234    LOAD_FAST                       29: conn_result
                1236    STORE_ATTR                      36: finished_at
                1238    LOAD_GLOBAL                     37: len
                1240    LOAD_FAST                       7: report
                1242    LOAD_CONST                      38: 'steps'
                1244    BINARY_SUBSCR                   
                1246    CALL_FUNCTION                   1
                1248    LOAD_GLOBAL                     37: len
                1250    LOAD_FAST                       7: report
                1252    LOAD_CONST                      52: 'self_heal'
                1254    BINARY_SUBSCR                   
                1256    CALL_FUNCTION                   1
                1258    LOAD_FAST                       6: snap
                1260    LOAD_CONST                      74: ('steps_count', 'self_heal_count', 'snapshot')
                1262    BUILD_CONST_KEY_MAP             3
                1264    LOAD_FAST                       29: conn_result
                1266    STORE_ATTR                      38: details
                1268    LOAD_FAST                       29: conn_result
                1270    LOAD_METHOD                     39: to_dict
                1272    CALL_METHOD                     0
                1274    LOAD_FAST                       7: report
                1276    LOAD_CONST                      75: 'connect_result'
                1278    STORE_SUBSCR                    
                1280    LOAD_GLOBAL                     15: ROOT
                1282    LOAD_CONST                      31: 'runtime'
                1284    BINARY_TRUE_DIVIDE              
                1286    LOAD_CONST                      32: 'connect_report.json'
                1288    BINARY_TRUE_DIVIDE              
                1290    STORE_FAST                      34: out_file
                1292    LOAD_GLOBAL                     16: write_json
                1294    LOAD_FAST                       34: out_file
                1296    LOAD_FAST                       7: report
                1298    CALL_FUNCTION                   2
                1300    POP_TOP                         
                1302    LOAD_GLOBAL                     17: print
                1304    LOAD_GLOBAL                     18: json
                1306    LOAD_ATTR                       19: dumps
                1308    LOAD_FAST                       7: report
                1310    LOAD_CONST                      33: False
                1312    LOAD_CONST                      34: 2
                1314    LOAD_CONST                      35: ('ensure_ascii', 'indent')
                1316    CALL_FUNCTION_KW                3
                1318    CALL_FUNCTION                   1
                1320    POP_TOP                         
                1322    LOAD_FAST                       28: overall_ok
                1324    POP_JUMP_IF_FALSE               1332
                1328    LOAD_CONST                      36: 0
                1330    RETURN_VALUE                    
                1332    LOAD_CONST                      76: 1
                1334    RETURN_VALUE                    
        'main'
        '__main__'
        (
            None
            240
        )
        (
            None
        )
    [Disassembly]
        0       LOAD_CONST                      0: 0
        2       LOAD_CONST                      1: ('annotations',)
        4       IMPORT_NAME                     0: __future__
        6       IMPORT_FROM                     1: annotations
        8       STORE_NAME                      1: annotations
        10      POP_TOP                         
        12      LOAD_CONST                      0: 0
        14      LOAD_CONST                      2: None
        16      IMPORT_NAME                     2: argparse
        18      STORE_NAME                      2: argparse
        20      LOAD_CONST                      0: 0
        22      LOAD_CONST                      2: None
        24      IMPORT_NAME                     3: json
        26      STORE_NAME                      3: json
        28      LOAD_CONST                      0: 0
        30      LOAD_CONST                      2: None
        32      IMPORT_NAME                     4: os
        34      STORE_NAME                      4: os
        36      LOAD_CONST                      0: 0
        38      LOAD_CONST                      2: None
        40      IMPORT_NAME                     5: subprocess
        42      STORE_NAME                      5: subprocess
        44      LOAD_CONST                      0: 0
        46      LOAD_CONST                      2: None
        48      IMPORT_NAME                     6: sys
        50      STORE_NAME                      6: sys
        52      LOAD_CONST                      0: 0
        54      LOAD_CONST                      3: ('datetime', 'timezone')
        56      IMPORT_NAME                     7: datetime
        58      IMPORT_FROM                     7: datetime
        60      STORE_NAME                      7: datetime
        62      IMPORT_FROM                     8: timezone
        64      STORE_NAME                      8: timezone
        66      POP_TOP                         
        68      LOAD_CONST                      0: 0
        70      LOAD_CONST                      4: ('Path',)
        72      IMPORT_NAME                     9: pathlib
        74      IMPORT_FROM                     10: Path
        76      STORE_NAME                      10: Path
        78      POP_TOP                         
        80      LOAD_CONST                      0: 0
        82      LOAD_CONST                      5: ('Any', 'Dict', 'List', 'Optional', 'Tuple')
        84      IMPORT_NAME                     11: typing
        86      IMPORT_FROM                     12: Any
        88      STORE_NAME                      12: Any
        90      IMPORT_FROM                     13: Dict
        92      STORE_NAME                      13: Dict
        94      IMPORT_FROM                     14: List
        96      STORE_NAME                      14: List
        98      IMPORT_FROM                     15: Optional
        100     STORE_NAME                      15: Optional
        102     IMPORT_FROM                     16: Tuple
        104     STORE_NAME                      16: Tuple
        106     POP_TOP                         
        108     LOAD_CONST                      0: 0
        110     LOAD_CONST                      6: ('ROOT', 'expand', 'expand_keep', 'load_cfg', 'snapshot_config', 'write_json')
        112     IMPORT_NAME                     17: common
        114     IMPORT_FROM                     18: ROOT
        116     STORE_NAME                      18: ROOT
        118     IMPORT_FROM                     19: expand
        120     STORE_NAME                      19: expand
        122     IMPORT_FROM                     20: expand_keep
        124     STORE_NAME                      20: expand_keep
        126     IMPORT_FROM                     21: load_cfg
        128     STORE_NAME                      21: load_cfg
        130     IMPORT_FROM                     22: snapshot_config
        132     STORE_NAME                      22: snapshot_config
        134     IMPORT_FROM                     23: write_json
        136     STORE_NAME                      23: write_json
        138     POP_TOP                         
        140     LOAD_CONST                      0: 0
        142     LOAD_CONST                      7: ('ConnectResult',)
        144     IMPORT_NAME                     24: integration_hooks.service_models
        146     IMPORT_FROM                     25: ConnectResult
        148     STORE_NAME                      25: ConnectResult
        150     POP_TOP                         
        152     LOAD_CONST                      8: 'str'
        154     LOAD_CONST                      9: ('return',)
        156     BUILD_CONST_KEY_MAP             1
        158     LOAD_CONST                      10: <CODE> _now
        160     LOAD_CONST                      11: '_now'
        162     MAKE_FUNCTION                   4
        164     STORE_NAME                      26: _now
        166     LOAD_CONST                      37: (None, 240)
        168     LOAD_CONST                      13: 'List[str]'
        170     LOAD_CONST                      14: 'Optional[Dict[str, str]]'
        172     LOAD_CONST                      15: 'int'
        174     LOAD_CONST                      16: 'Tuple[int, str, str]'
        176     LOAD_CONST                      17: ('cmd', 'env', 'timeout', 'return')
        178     BUILD_CONST_KEY_MAP             4
        180     LOAD_CONST                      18: <CODE> _run
        182     LOAD_CONST                      19: '_run'
        184     MAKE_FUNCTION                   5
        186     STORE_NAME                      27: _run
        188     LOAD_CONST                      20: 'Dict[str, Any]'
        190     LOAD_CONST                      8: 'str'
        192     LOAD_CONST                      21: ('cfg', 'return')
        194     BUILD_CONST_KEY_MAP             2
        196     LOAD_CONST                      22: <CODE> _pick_core_python
        198     LOAD_CONST                      23: '_pick_core_python'
        200     MAKE_FUNCTION                   4
        202     STORE_NAME                      28: _pick_core_python
        204     LOAD_CONST                      20: 'Dict[str, Any]'
        206     LOAD_CONST                      13: 'List[str]'
        208     LOAD_CONST                      21: ('cfg', 'return')
        210     BUILD_CONST_KEY_MAP             2
        212     LOAD_CONST                      24: <CODE> _detect_targets
        214     LOAD_CONST                      25: '_detect_targets'
        216     MAKE_FUNCTION                   4
        218     STORE_NAME                      29: _detect_targets
        220     LOAD_CONST                      26: 'List[Dict[str, Any]]'
        222     LOAD_CONST                      8: 'str'
        224     LOAD_CONST                      15: 'int'
        226     LOAD_CONST                      8: 'str'
        228     LOAD_CONST                      8: 'str'
        230     LOAD_CONST                      27: 'None'
        232     LOAD_CONST                      28: ('report', 'name', 'rc', 'out', 'err', 'return')
        234     BUILD_CONST_KEY_MAP             6
        236     LOAD_CONST                      29: <CODE> _step
        238     LOAD_CONST                      30: '_step'
        240     MAKE_FUNCTION                   4
        242     STORE_NAME                      30: _step
        244     LOAD_CONST                      38: (None,)
        246     LOAD_CONST                      8: 'str'
        248     LOAD_CONST                      14: 'Optional[Dict[str, str]]'
        250     LOAD_CONST                      16: 'Tuple[int, str, str]'
        252     LOAD_CONST                      31: ('script_name', 'env', 'return')
        254     BUILD_CONST_KEY_MAP             3
        256     LOAD_CONST                      32: <CODE> _run_py
        258     LOAD_CONST                      33: '_run_py'
        260     MAKE_FUNCTION                   5
        262     STORE_NAME                      31: _run_py
        264     LOAD_CONST                      15: 'int'
        266     LOAD_CONST                      9: ('return',)
        268     BUILD_CONST_KEY_MAP             1
        270     LOAD_CONST                      34: <CODE> main
        272     LOAD_CONST                      35: 'main'
        274     MAKE_FUNCTION                   4
        276     STORE_NAME                      32: main
        278     LOAD_NAME                       33: __name__
        280     LOAD_CONST                      36: '__main__'
        282     COMPARE_OP                      2 (==)
        284     POP_JUMP_IF_FALSE               298
        288     LOAD_NAME                       34: SystemExit
        290     LOAD_NAME                       32: main
        292     CALL_FUNCTION                   0
        294     CALL_FUNCTION                   1
        296     RAISE_VARARGS                   1
        298     LOAD_CONST                      2: None
        300     RETURN_VALUE                    
