generate_client_configs.cpython-39.pyc (Python 3.9)
[Code]
    File Name: scripts/generate_client_configs.py
    Object Name: <module>
    Arg Count: 0
    Pos Only Arg Count: 0
    KW Only Arg Count: 0
    Locals: 0
    Stack Size: 3
    Flags: 0x01000040 (CO_NOFREE | CO_FUTURE_ANNOTATIONS)
    [Names]
        '__future__'
        'annotations'
        'json'
        'pathlib'
        'Path'
        'common'
        'ROOT'
        'expand'
        'expand_keep'
        'load_cfg'
        'main'
        '__name__'
        'SystemExit'
    [Var Names]
    [Free Vars]
    [Cell Vars]
    [Constants]
        0
        (
            'annotations'
        )
        None
        (
            'Path'
        )
        (
            'ROOT'
            'expand'
            'expand_keep'
            'load_cfg'
        )
        'int'
        (
            'return'
        )
        [Code]
            File Name: scripts/generate_client_configs.py
            Object Name: main
            Arg Count: 0
            Pos Only Arg Count: 0
            KW Only Arg Count: 0
            Locals: 9
            Stack Size: 7
            Flags: 0x01000043 (CO_OPTIMIZED | CO_NEWLOCALS | CO_NOFREE | CO_FUTURE_ANNOTATIONS)
            [Names]
                'load_cfg'
                'expand'
                'get'
                'expand_keep'
                'exists'
                'ROOT'
                'mkdir'
                'str'
                'write_text'
                'json'
                'dumps'
                'print'
            [Var Names]
                'cfg'
                'bridge_venv'
                'bridge_py'
                'core_py'
                'py'
                'server_file'
                'out_dir'
                'snippet'
                'name'
            [Free Vars]
            [Cell Vars]
            [Constants]
                None
                'bridge_env'
                'venv_dir'
                '~/openclaw-memory-auto/.venv'
                'bin'
                'python'
                'memory_core'
                'core_venv_python'
                '~/.codex/skills/openclaw-memory/.venv/bin/python'
                'mcp_server'
                'mcp_server.py'
                'runtime'
                'client_snippets'
                True
                (
                    'parents'
                    'exist_ok'
                )
                'mcpServers'
                'openclaw-memory'
                'OPENCLAW_MCP_CLIENT'
                'CLIENT_NAME'
                (
                    'command'
                    'args'
                    'env'
                )
                (
                    'claude_desktop_config.json'
                    'cursor_mcp.json'
                    'windsurf_mcp.json'
                )
                False
                2
                (
                    'ensure_ascii'
                    'indent'
                )
                'utf-8'
                (
                    'encoding'
                )
                'snippets_dir='
                'generate_client_configs=ok'
                0
            [Disassembly]
                0       LOAD_GLOBAL                     0: load_cfg
                2       CALL_FUNCTION                   0
                4       STORE_FAST                      0: cfg
                6       LOAD_GLOBAL                     1: expand
                8       LOAD_FAST                       0: cfg
                10      LOAD_METHOD                     2: get
                12      LOAD_CONST                      1: 'bridge_env'
                14      BUILD_MAP                       0
                16      CALL_METHOD                     2
                18      LOAD_METHOD                     2: get
                20      LOAD_CONST                      2: 'venv_dir'
                22      LOAD_CONST                      3: '~/openclaw-memory-auto/.venv'
                24      CALL_METHOD                     2
                26      CALL_FUNCTION                   1
                28      STORE_FAST                      1: bridge_venv
                30      LOAD_FAST                       1: bridge_venv
                32      LOAD_CONST                      4: 'bin'
                34      BINARY_TRUE_DIVIDE              
                36      LOAD_CONST                      5: 'python'
                38      BINARY_TRUE_DIVIDE              
                40      STORE_FAST                      2: bridge_py
                42      LOAD_GLOBAL                     3: expand_keep
                44      LOAD_FAST                       0: cfg
                46      LOAD_METHOD                     2: get
                48      LOAD_CONST                      6: 'memory_core'
                50      BUILD_MAP                       0
                52      CALL_METHOD                     2
                54      LOAD_METHOD                     2: get
                56      LOAD_CONST                      7: 'core_venv_python'
                58      LOAD_CONST                      8: '~/.codex/skills/openclaw-memory/.venv/bin/python'
                60      CALL_METHOD                     2
                62      CALL_FUNCTION                   1
                64      STORE_FAST                      3: core_py
                66      LOAD_FAST                       3: core_py
                68      LOAD_METHOD                     4: exists
                70      CALL_METHOD                     0
                72      POP_JUMP_IF_FALSE               78
                74      LOAD_FAST                       3: core_py
                76      JUMP_FORWARD                    2 (to 80)
                78      LOAD_FAST                       2: bridge_py
                80      STORE_FAST                      4: py
                82      LOAD_GLOBAL                     5: ROOT
                84      LOAD_CONST                      9: 'mcp_server'
                86      BINARY_TRUE_DIVIDE              
                88      LOAD_CONST                      10: 'mcp_server.py'
                90      BINARY_TRUE_DIVIDE              
                92      STORE_FAST                      5: server_file
                94      LOAD_GLOBAL                     5: ROOT
                96      LOAD_CONST                      11: 'runtime'
                98      BINARY_TRUE_DIVIDE              
                100     LOAD_CONST                      12: 'client_snippets'
                102     BINARY_TRUE_DIVIDE              
                104     STORE_FAST                      6: out_dir
                106     LOAD_FAST                       6: out_dir
                108     LOAD_ATTR                       6: mkdir
                110     LOAD_CONST                      13: True
                112     LOAD_CONST                      13: True
                114     LOAD_CONST                      14: ('parents', 'exist_ok')
                116     CALL_FUNCTION_KW                2
                118     POP_TOP                         
                120     LOAD_CONST                      15: 'mcpServers'
                122     LOAD_CONST                      16: 'openclaw-memory'
                124     LOAD_GLOBAL                     7: str
                126     LOAD_FAST                       4: py
                128     CALL_FUNCTION                   1
                130     LOAD_GLOBAL                     7: str
                132     LOAD_FAST                       5: server_file
                134     CALL_FUNCTION                   1
                136     BUILD_LIST                      1
                138     LOAD_CONST                      17: 'OPENCLAW_MCP_CLIENT'
                140     LOAD_CONST                      18: 'CLIENT_NAME'
                142     BUILD_MAP                       1
                144     LOAD_CONST                      19: ('command', 'args', 'env')
                146     BUILD_CONST_KEY_MAP             3
                148     BUILD_MAP                       1
                150     BUILD_MAP                       1
                152     STORE_FAST                      7: snippet
                154     LOAD_CONST                      20: ('claude_desktop_config.json', 'cursor_mcp.json', 'windsurf_mcp.json')
                156     GET_ITER                        
                158     FOR_ITER                        34 (to 194)
                160     STORE_FAST                      8: name
                162     LOAD_FAST                       6: out_dir
                164     LOAD_FAST                       8: name
                166     BINARY_TRUE_DIVIDE              
                168     LOAD_ATTR                       8: write_text
                170     LOAD_GLOBAL                     9: json
                172     LOAD_ATTR                       10: dumps
                174     LOAD_FAST                       7: snippet
                176     LOAD_CONST                      21: False
                178     LOAD_CONST                      22: 2
                180     LOAD_CONST                      23: ('ensure_ascii', 'indent')
                182     CALL_FUNCTION_KW                3
                184     LOAD_CONST                      24: 'utf-8'
                186     LOAD_CONST                      25: ('encoding',)
                188     CALL_FUNCTION_KW                2
                190     POP_TOP                         
                192     JUMP_ABSOLUTE                   158
                194     LOAD_GLOBAL                     11: print
                196     LOAD_CONST                      26: 'snippets_dir='
                198     LOAD_FAST                       6: out_dir
                200     FORMAT_VALUE                    0 (FVC_NONE)
                202     BUILD_STRING                    2
                204     CALL_FUNCTION                   1
                206     POP_TOP                         
                208     LOAD_GLOBAL                     11: print
                210     LOAD_CONST                      27: 'generate_client_configs=ok'
                212     CALL_FUNCTION                   1
                214     POP_TOP                         
                216     LOAD_CONST                      28: 0
                218     RETURN_VALUE                    
        'main'
        '__main__'
    [Disassembly]
        0       LOAD_CONST                      0: 0
        2       LOAD_CONST                      1: ('annotations',)
        4       IMPORT_NAME                     0: __future__
        6       IMPORT_FROM                     1: annotations
        8       STORE_NAME                      1: annotations
        10      POP_TOP                         
        12      LOAD_CONST                      0: 0
        14      LOAD_CONST                      2: None
        16      IMPORT_NAME                     2: json
        18      STORE_NAME                      2: json
        20      LOAD_CONST                      0: 0
        22      LOAD_CONST                      3: ('Path',)
        24      IMPORT_NAME                     3: pathlib
        26      IMPORT_FROM                     4: Path
        28      STORE_NAME                      4: Path
        30      POP_TOP                         
        32      LOAD_CONST                      0: 0
        34      LOAD_CONST                      4: ('ROOT', 'expand', 'expand_keep', 'load_cfg')
        36      IMPORT_NAME                     5: common
        38      IMPORT_FROM                     6: ROOT
        40      STORE_NAME                      6: ROOT
        42      IMPORT_FROM                     7: expand
        44      STORE_NAME                      7: expand
        46      IMPORT_FROM                     8: expand_keep
        48      STORE_NAME                      8: expand_keep
        50      IMPORT_FROM                     9: load_cfg
        52      STORE_NAME                      9: load_cfg
        54      POP_TOP                         
        56      LOAD_CONST                      5: 'int'
        58      LOAD_CONST                      6: ('return',)
        60      BUILD_CONST_KEY_MAP             1
        62      LOAD_CONST                      7: <CODE> main
        64      LOAD_CONST                      8: 'main'
        66      MAKE_FUNCTION                   4
        68      STORE_NAME                      10: main
        70      LOAD_NAME                       11: __name__
        72      LOAD_CONST                      9: '__main__'
        74      COMPARE_OP                      2 (==)
        76      POP_JUMP_IF_FALSE               88
        78      LOAD_NAME                       12: SystemExit
        80      LOAD_NAME                       10: main
        82      CALL_FUNCTION                   0
        84      CALL_FUNCTION                   1
        86      RAISE_VARARGS                   1
        88      LOAD_CONST                      2: None
        90      RETURN_VALUE                    
