rollback_client_configs.cpython-39.pyc (Python 3.9)
[Code]
    File Name: scripts/rollback_client_configs.py
    Object Name: <module>
    Arg Count: 0
    Pos Only Arg Count: 0
    KW Only Arg Count: 0
    Locals: 0
    Stack Size: 4
    Flags: 0x01000040 (CO_NOFREE | CO_FUTURE_ANNOTATIONS)
    [Names]
        '__future__'
        'annotations'
        'argparse'
        'json'
        'os'
        'pathlib'
        'Path'
        'common'
        'ROOT'
        'expand'
        '_read_json'
        '_write_json'
        '_resolve_target_keys'
        'main'
        '__name__'
        'SystemExit'
    [Var Names]
    [Free Vars]
    [Cell Vars]
    [Constants]
        0
        (
            'annotations'
        )
        None
        (
            'Path'
        )
        (
            'ROOT'
            'expand'
        )
        'Path'
        'dict'
        (
            'path'
            'return'
        )
        [Code]
            File Name: scripts/rollback_client_configs.py
            Object Name: _read_json
            Arg Count: 1
            Pos Only Arg Count: 0
            KW Only Arg Count: 0
            Locals: 1
            Stack Size: 8
            Flags: 0x01000043 (CO_OPTIMIZED | CO_NEWLOCALS | CO_NOFREE | CO_FUTURE_ANNOTATIONS)
            [Names]
                'exists'
                'json'
                'loads'
                'read_text'
                'Exception'
            [Var Names]
                'path'
            [Free Vars]
            [Cell Vars]
            [Constants]
                None
                'utf-8'
                (
                    'encoding'
                )
            [Disassembly]
                0       LOAD_FAST                       0: path
                2       LOAD_METHOD                     0: exists
                4       CALL_METHOD                     0
                6       POP_JUMP_IF_TRUE                12
                8       BUILD_MAP                       0
                10      RETURN_VALUE                    
                12      SETUP_FINALLY                   20 (to 34)
                14      LOAD_GLOBAL                     1: json
                16      LOAD_METHOD                     2: loads
                18      LOAD_FAST                       0: path
                20      LOAD_ATTR                       3: read_text
                22      LOAD_CONST                      1: 'utf-8'
                24      LOAD_CONST                      2: ('encoding',)
                26      CALL_FUNCTION_KW                1
                28      CALL_METHOD                     1
                30      POP_BLOCK                       
                32      RETURN_VALUE                    
                34      DUP_TOP                         
                36      LOAD_GLOBAL                     4: Exception
                38      JUMP_IF_NOT_EXC_MATCH           54
                40      POP_TOP                         
                42      POP_TOP                         
                44      POP_TOP                         
                46      BUILD_MAP                       0
                48      ROT_FOUR                        
                50      POP_EXCEPT                      
                52      RETURN_VALUE                    
                54      RERAISE                         
                56      LOAD_CONST                      0: None
                58      RETURN_VALUE                    
        '_read_json'
        'None'
        (
            'path'
            'payload'
            'return'
        )
        [Code]
            File Name: scripts/rollback_client_configs.py
            Object Name: _write_json
            Arg Count: 2
            Pos Only Arg Count: 0
            KW Only Arg Count: 0
            Locals: 2
            Stack Size: 6
            Flags: 0x01000043 (CO_OPTIMIZED | CO_NEWLOCALS | CO_NOFREE | CO_FUTURE_ANNOTATIONS)
            [Names]
                'parent'
                'mkdir'
                'write_text'
                'json'
                'dumps'
            [Var Names]
                'path'
                'payload'
            [Free Vars]
            [Cell Vars]
            [Constants]
                None
                True
                (
                    'parents'
                    'exist_ok'
                )
                False
                2
                (
                    'ensure_ascii'
                    'indent'
                )
                'utf-8'
                (
                    'encoding'
                )
            [Disassembly]
                0       LOAD_FAST                       0: path
                2       LOAD_ATTR                       0: parent
                4       LOAD_ATTR                       1: mkdir
                6       LOAD_CONST                      1: True
                8       LOAD_CONST                      1: True
                10      LOAD_CONST                      2: ('parents', 'exist_ok')
                12      CALL_FUNCTION_KW                2
                14      POP_TOP                         
                16      LOAD_FAST                       0: path
                18      LOAD_ATTR                       2: write_text
                20      LOAD_GLOBAL                     3: json
                22      LOAD_ATTR                       4: dumps
                24      LOAD_FAST                       1: payload
                26      LOAD_CONST                      3: False
                28      LOAD_CONST                      4: 2
                30      LOAD_CONST                      5: ('ensure_ascii', 'indent')
                32      CALL_FUNCTION_KW                3
                34      LOAD_CONST                      6: 'utf-8'
                36      LOAD_CONST                      7: ('encoding',)
                38      CALL_FUNCTION_KW                2
                40      POP_TOP                         
                42      LOAD_CONST                      0: None
                44      RETURN_VALUE                    
        '_write_json'
        ''
        'str'
        'list[str]'
        (
            'cli_targets'
            'return'
        )
        [Code]
            File Name: scripts/rollback_client_configs.py
            Object Name: _resolve_target_keys
            Arg Count: 1
            Pos Only Arg Count: 0
            KW Only Arg Count: 0
            Locals: 2
            Stack Size: 4
            Flags: 0x01000043 (CO_OPTIMIZED | CO_NEWLOCALS | CO_NOFREE | CO_FUTURE_ANNOTATIONS)
            [Names]
                'strip'
                'split'
                'os'
                'environ'
                'get'
            [Var Names]
                'cli_targets'
                'raw'
            [Free Vars]
            [Cell Vars]
            [Constants]
                None
                [Code]
                    File Name: scripts/rollback_client_configs.py
                    Object Name: <listcomp>
                    Arg Count: 1
                    Pos Only Arg Count: 0
                    KW Only Arg Count: 0
                    Locals: 2
                    Stack Size: 4
                    Flags: 0x01000053 (CO_OPTIMIZED | CO_NEWLOCALS | CO_NESTED | CO_NOFREE | CO_FUTURE_ANNOTATIONS)
                    [Names]
                        'strip'
                    [Var Names]
                        '.0'
                        'x'
                    [Free Vars]
                    [Cell Vars]
                    [Constants]
                    [Disassembly]
                        0       BUILD_LIST                      0
                        2       LOAD_FAST                       0: .0
                        4       FOR_ITER                        20 (to 26)
                        6       STORE_FAST                      1: x
                        8       LOAD_FAST                       1: x
                        10      LOAD_METHOD                     0: strip
                        12      CALL_METHOD                     0
                        14      POP_JUMP_IF_FALSE               4
                        16      LOAD_FAST                       1: x
                        18      LOAD_METHOD                     0: strip
                        20      CALL_METHOD                     0
                        22      LIST_APPEND                     2
                        24      JUMP_ABSOLUTE                   4
                        26      RETURN_VALUE                    
                '_resolve_target_keys.<locals>.<listcomp>'
                ','
                'OCMA_TARGET_KEYS'
                ''
                [Code]
                    File Name: scripts/rollback_client_configs.py
                    Object Name: <listcomp>
                    Arg Count: 1
                    Pos Only Arg Count: 0
                    KW Only Arg Count: 0
                    Locals: 2
                    Stack Size: 4
                    Flags: 0x01000053 (CO_OPTIMIZED | CO_NEWLOCALS | CO_NESTED | CO_NOFREE | CO_FUTURE_ANNOTATIONS)
                    [Names]
                        'strip'
                    [Var Names]
                        '.0'
                        'x'
                    [Free Vars]
                    [Cell Vars]
                    [Constants]
                    [Disassembly]
                        0       BUILD_LIST                      0
                        2       LOAD_FAST                       0: .0
                        4       FOR_ITER                        20 (to 26)
                        6       STORE_FAST                      1: x
                        8       LOAD_FAST                       1: x
                        10      LOAD_METHOD                     0: strip
                        12      CALL_METHOD                     0
                        14      POP_JUMP_IF_FALSE               4
                        16      LOAD_FAST                       1: x
                        18      LOAD_METHOD                     0: strip
                        20      CALL_METHOD                     0
                        22      LIST_APPEND                     2
                        24      JUMP_ABSOLUTE                   4
                        26      RETURN_VALUE                    
            [Disassembly]
                0       LOAD_FAST                       0: cli_targets
                2       LOAD_METHOD                     0: strip
                4       CALL_METHOD                     0
                6       POP_JUMP_IF_FALSE               28
                8       LOAD_CONST                      1: <CODE> <listcomp>
                10      LOAD_CONST                      2: '_resolve_target_keys.<locals>.<listcomp>'
                12      MAKE_FUNCTION                   0
                14      LOAD_FAST                       0: cli_targets
                16      LOAD_METHOD                     1: split
                18      LOAD_CONST                      3: ','
                20      CALL_METHOD                     1
                22      GET_ITER                        
                24      CALL_FUNCTION                   1
                26      RETURN_VALUE                    
                28      LOAD_GLOBAL                     2: os
                30      LOAD_ATTR                       3: environ
                32      LOAD_METHOD                     4: get
                34      LOAD_CONST                      4: 'OCMA_TARGET_KEYS'
                36      LOAD_CONST                      5: ''
                38      CALL_METHOD                     2
                40      LOAD_METHOD                     0: strip
                42      CALL_METHOD                     0
                44      STORE_FAST                      1: raw
                46      LOAD_FAST                       1: raw
                48      POP_JUMP_IF_FALSE               70
                50      LOAD_CONST                      6: <CODE> <listcomp>
                52      LOAD_CONST                      2: '_resolve_target_keys.<locals>.<listcomp>'
                54      MAKE_FUNCTION                   0
                56      LOAD_FAST                       1: raw
                58      LOAD_METHOD                     1: split
                60      LOAD_CONST                      3: ','
                62      CALL_METHOD                     1
                64      GET_ITER                        
                66      CALL_FUNCTION                   1
                68      RETURN_VALUE                    
                70      BUILD_LIST                      0
                72      RETURN_VALUE                    
        '_resolve_target_keys'
        'int'
        (
            'return'
        )
        [Code]
            File Name: scripts/rollback_client_configs.py
            Object Name: main
            Arg Count: 0
            Pos Only Arg Count: 0
            KW Only Arg Count: 0
            Locals: 13
            Stack Size: 6
            Flags: 0x01000003 (CO_OPTIMIZED | CO_NEWLOCALS | CO_FUTURE_ANNOTATIONS)
            [Names]
                'argparse'
                'ArgumentParser'
                'add_argument'
                'parse_args'
                'ROOT'
                'sorted'
                'glob'
                'print'
                'expand'
                '_resolve_target_keys'
                'targets'
                'items'
                'exists'
                'parent'
                'mkdir'
                'write_text'
                'read_text'
                '_read_json'
                'isinstance'
                'dict'
                'get'
                'pop'
                '_write_json'
                'name'
                'json'
                'dumps'
            [Var Names]
                'parser'
                'args'
                'snap_root'
                'snaps'
                'latest'
                'targets'
                'restored'
                'key'
                'target'
                'backup'
                'obj'
                'mcp_servers'
                'out'
            [Free Vars]
            [Cell Vars]
                'keys'
            [Constants]
                None
                'Rollback MCP client configs.'
                (
                    'description'
                )
                '--targets'
                ''
                'Comma-separated targets: claude_desktop,cursor,windsurf'
                (
                    'default'
                    'help'
                )
                'runtime'
                'snapshots'
                'client_configs'
                [Code]
                    File Name: scripts/rollback_client_configs.py
                    Object Name: <listcomp>
                    Arg Count: 1
                    Pos Only Arg Count: 0
                    KW Only Arg Count: 0
                    Locals: 2
                    Stack Size: 4
                    Flags: 0x01000053 (CO_OPTIMIZED | CO_NEWLOCALS | CO_NESTED | CO_NOFREE | CO_FUTURE_ANNOTATIONS)
                    [Names]
                        'is_dir'
                    [Var Names]
                        '.0'
                        'p'
                    [Free Vars]
                    [Cell Vars]
                    [Constants]
                    [Disassembly]
                        0       BUILD_LIST                      0
                        2       LOAD_FAST                       0: .0
                        4       FOR_ITER                        16 (to 22)
                        6       STORE_FAST                      1: p
                        8       LOAD_FAST                       1: p
                        10      LOAD_METHOD                     0: is_dir
                        12      CALL_METHOD                     0
                        14      POP_JUMP_IF_FALSE               4
                        16      LOAD_FAST                       1: p
                        18      LIST_APPEND                     2
                        20      JUMP_ABSOLUTE                   4
                        22      RETURN_VALUE                    
                'main.<locals>.<listcomp>'
                '*'
                'rollback_client_configs=no_snapshot'
                1
                -1
                '~/Library/Application Support/Claude/claude_desktop_config.json'
                '~/.cursor/mcp.json'
                '~/.windsurf/mcp.json'
                (
                    'claude_desktop'
                    'cursor'
                    'windsurf'
                )
                [Code]
                    File Name: scripts/rollback_client_configs.py
                    Object Name: <dictcomp>
                    Arg Count: 1
                    Pos Only Arg Count: 0
                    KW Only Arg Count: 0
                    Locals: 3
                    Stack Size: 4
                    Flags: 0x01000013 (CO_OPTIMIZED | CO_NEWLOCALS | CO_NESTED | CO_FUTURE_ANNOTATIONS)
                    [Names]
                    [Var Names]
                        '.0'
                        'k'
                        'v'
                    [Free Vars]
                        'keys'
                    [Cell Vars]
                    [Constants]
                    [Disassembly]
                        0       BUILD_MAP                       0
                        2       LOAD_FAST                       0: .0
                        4       FOR_ITER                        22 (to 28)
                        6       UNPACK_SEQUENCE                 2
                        8       STORE_FAST                      1: k
                        10      STORE_FAST                      2: v
                        12      LOAD_FAST                       1: k
                        14      LOAD_DEREF                      0: keys
                        16      CONTAINS_OP                     0 (in)
                        18      POP_JUMP_IF_FALSE               4
                        20      LOAD_FAST                       1: k
                        22      LOAD_FAST                       2: v
                        24      MAP_ADD                         2
                        26      JUMP_ABSOLUTE                   4
                        28      RETURN_VALUE                    
                'main.<locals>.<dictcomp>'
                'rollback_client_configs=no_targets'
                '.backup.json'
                True
                (
                    'parents'
                    'exist_ok'
                )
                'utf-8'
                (
                    'encoding'
                )
                'full_restore'
                'mcpServers'
                'openclaw-memory'
                'entry_removed'
                'no_change'
                (
                    'rollback_snapshot'
                    'restored'
                )
                False
                2
                (
                    'ensure_ascii'
                    'indent'
                )
                0
            [Disassembly]
                0       LOAD_GLOBAL                     0: argparse
                2       LOAD_ATTR                       1: ArgumentParser
                4       LOAD_CONST                      1: 'Rollback MCP client configs.'
                6       LOAD_CONST                      2: ('description',)
                8       CALL_FUNCTION_KW                1
                10      STORE_FAST                      0: parser
                12      LOAD_FAST                       0: parser
                14      LOAD_ATTR                       2: add_argument
                16      LOAD_CONST                      3: '--targets'
                18      LOAD_CONST                      4: ''
                20      LOAD_CONST                      5: 'Comma-separated targets: claude_desktop,cursor,windsurf'
                22      LOAD_CONST                      6: ('default', 'help')
                24      CALL_FUNCTION_KW                3
                26      POP_TOP                         
                28      LOAD_FAST                       0: parser
                30      LOAD_METHOD                     3: parse_args
                32      CALL_METHOD                     0
                34      STORE_FAST                      1: args
                36      LOAD_GLOBAL                     4: ROOT
                38      LOAD_CONST                      7: 'runtime'
                40      BINARY_TRUE_DIVIDE              
                42      LOAD_CONST                      8: 'snapshots'
                44      BINARY_TRUE_DIVIDE              
                46      LOAD_CONST                      9: 'client_configs'
                48      BINARY_TRUE_DIVIDE              
                50      STORE_FAST                      2: snap_root
                52      LOAD_GLOBAL                     5: sorted
                54      LOAD_CONST                      10: <CODE> <listcomp>
                56      LOAD_CONST                      11: 'main.<locals>.<listcomp>'
                58      MAKE_FUNCTION                   0
                60      LOAD_FAST                       2: snap_root
                62      LOAD_METHOD                     6: glob
                64      LOAD_CONST                      12: '*'
                66      CALL_METHOD                     1
                68      GET_ITER                        
                70      CALL_FUNCTION                   1
                72      CALL_FUNCTION                   1
                74      STORE_FAST                      3: snaps
                76      LOAD_FAST                       3: snaps
                78      POP_JUMP_IF_TRUE                92
                80      LOAD_GLOBAL                     7: print
                82      LOAD_CONST                      13: 'rollback_client_configs=no_snapshot'
                84      CALL_FUNCTION                   1
                86      POP_TOP                         
                88      LOAD_CONST                      14: 1
                90      RETURN_VALUE                    
                92      LOAD_FAST                       3: snaps
                94      LOAD_CONST                      15: -1
                96      BINARY_SUBSCR                   
                98      STORE_FAST                      4: latest
                100     LOAD_GLOBAL                     8: expand
                102     LOAD_CONST                      16: '~/Library/Application Support/Claude/claude_desktop_config.json'
                104     CALL_FUNCTION                   1
                106     LOAD_GLOBAL                     8: expand
                108     LOAD_CONST                      17: '~/.cursor/mcp.json'
                110     CALL_FUNCTION                   1
                112     LOAD_GLOBAL                     8: expand
                114     LOAD_CONST                      18: '~/.windsurf/mcp.json'
                116     CALL_FUNCTION                   1
                118     LOAD_CONST                      19: ('claude_desktop', 'cursor', 'windsurf')
                120     BUILD_CONST_KEY_MAP             3
                122     STORE_FAST                      5: targets
                124     LOAD_GLOBAL                     9: _resolve_target_keys
                126     LOAD_FAST                       1: args
                128     LOAD_ATTR                       10: targets
                130     CALL_FUNCTION                   1
                132     STORE_DEREF                     0: keys
                134     LOAD_DEREF                      0: keys
                136     POP_JUMP_IF_FALSE               160
                138     LOAD_CLOSURE                    0: keys
                140     BUILD_TUPLE                     1
                142     LOAD_CONST                      20: <CODE> <dictcomp>
                144     LOAD_CONST                      21: 'main.<locals>.<dictcomp>'
                146     MAKE_FUNCTION                   8
                148     LOAD_FAST                       5: targets
                150     LOAD_METHOD                     11: items
                152     CALL_METHOD                     0
                154     GET_ITER                        
                156     CALL_FUNCTION                   1
                158     STORE_FAST                      5: targets
                160     LOAD_FAST                       5: targets
                162     POP_JUMP_IF_TRUE                176
                164     LOAD_GLOBAL                     7: print
                166     LOAD_CONST                      22: 'rollback_client_configs=no_targets'
                168     CALL_FUNCTION                   1
                170     POP_TOP                         
                172     LOAD_CONST                      14: 1
                174     RETURN_VALUE                    
                176     BUILD_MAP                       0
                178     STORE_FAST                      6: restored
                180     LOAD_FAST                       5: targets
                182     LOAD_METHOD                     11: items
                184     CALL_METHOD                     0
                186     GET_ITER                        
                188     FOR_ITER                        184 (to 374)
                190     UNPACK_SEQUENCE                 2
                192     STORE_FAST                      7: key
                194     STORE_FAST                      8: target
                196     LOAD_FAST                       4: latest
                198     LOAD_FAST                       7: key
                200     FORMAT_VALUE                    0 (FVC_NONE)
                202     LOAD_CONST                      23: '.backup.json'
                204     BUILD_STRING                    2
                206     BINARY_TRUE_DIVIDE              
                208     STORE_FAST                      9: backup
                210     LOAD_FAST                       9: backup
                212     LOAD_METHOD                     12: exists
                214     CALL_METHOD                     0
                216     POP_JUMP_IF_FALSE               268
                220     LOAD_FAST                       8: target
                222     LOAD_ATTR                       13: parent
                224     LOAD_ATTR                       14: mkdir
                226     LOAD_CONST                      24: True
                228     LOAD_CONST                      24: True
                230     LOAD_CONST                      25: ('parents', 'exist_ok')
                232     CALL_FUNCTION_KW                2
                234     POP_TOP                         
                236     LOAD_FAST                       8: target
                238     LOAD_ATTR                       15: write_text
                240     LOAD_FAST                       9: backup
                242     LOAD_ATTR                       16: read_text
                244     LOAD_CONST                      26: 'utf-8'
                246     LOAD_CONST                      27: ('encoding',)
                248     CALL_FUNCTION_KW                1
                250     LOAD_CONST                      26: 'utf-8'
                252     LOAD_CONST                      27: ('encoding',)
                254     CALL_FUNCTION_KW                2
                256     POP_TOP                         
                258     LOAD_CONST                      28: 'full_restore'
                260     LOAD_FAST                       6: restored
                262     LOAD_FAST                       7: key
                264     STORE_SUBSCR                    
                266     JUMP_ABSOLUTE                   188
                268     LOAD_GLOBAL                     17: _read_json
                270     LOAD_FAST                       8: target
                272     CALL_FUNCTION                   1
                274     STORE_FAST                      10: obj
                276     LOAD_GLOBAL                     18: isinstance
                278     LOAD_FAST                       10: obj
                280     LOAD_GLOBAL                     19: dict
                282     CALL_FUNCTION                   2
                284     POP_JUMP_IF_FALSE               298
                288     LOAD_FAST                       10: obj
                290     LOAD_METHOD                     20: get
                292     LOAD_CONST                      29: 'mcpServers'
                294     CALL_METHOD                     1
                296     JUMP_FORWARD                    2 (to 300)
                298     LOAD_CONST                      0: None
                300     STORE_FAST                      11: mcp_servers
                302     LOAD_GLOBAL                     18: isinstance
                304     LOAD_FAST                       11: mcp_servers
                306     LOAD_GLOBAL                     19: dict
                308     CALL_FUNCTION                   2
                310     POP_JUMP_IF_FALSE               364
                314     LOAD_CONST                      30: 'openclaw-memory'
                316     LOAD_FAST                       11: mcp_servers
                318     CONTAINS_OP                     0 (in)
                320     POP_JUMP_IF_FALSE               364
                324     LOAD_FAST                       11: mcp_servers
                326     LOAD_METHOD                     21: pop
                328     LOAD_CONST                      30: 'openclaw-memory'
                330     LOAD_CONST                      0: None
                332     CALL_METHOD                     2
                334     POP_TOP                         
                336     LOAD_FAST                       11: mcp_servers
                338     LOAD_FAST                       10: obj
                340     LOAD_CONST                      29: 'mcpServers'
                342     STORE_SUBSCR                    
                344     LOAD_GLOBAL                     22: _write_json
                346     LOAD_FAST                       8: target
                348     LOAD_FAST                       10: obj
                350     CALL_FUNCTION                   2
                352     POP_TOP                         
                354     LOAD_CONST                      31: 'entry_removed'
                356     LOAD_FAST                       6: restored
                358     LOAD_FAST                       7: key
                360     STORE_SUBSCR                    
                362     JUMP_ABSOLUTE                   188
                364     LOAD_CONST                      32: 'no_change'
                366     LOAD_FAST                       6: restored
                368     LOAD_FAST                       7: key
                370     STORE_SUBSCR                    
                372     JUMP_ABSOLUTE                   188
                374     LOAD_FAST                       4: latest
                376     LOAD_ATTR                       23: name
                378     LOAD_FAST                       6: restored
                380     LOAD_CONST                      33: ('rollback_snapshot', 'restored')
                382     BUILD_CONST_KEY_MAP             2
                384     STORE_FAST                      12: out
                386     LOAD_GLOBAL                     7: print
                388     LOAD_GLOBAL                     24: json
                390     LOAD_ATTR                       25: dumps
                392     LOAD_FAST                       12: out
                394     LOAD_CONST                      34: False
                396     LOAD_CONST                      35: 2
                398     LOAD_CONST                      36: ('ensure_ascii', 'indent')
                400     CALL_FUNCTION_KW                3
                402     CALL_FUNCTION                   1
                404     POP_TOP                         
                406     LOAD_CONST                      37: 0
                408     RETURN_VALUE                    
        'main'
        '__main__'
        (
            ''
        )
    [Disassembly]
        0       LOAD_CONST                      0: 0
        2       LOAD_CONST                      1: ('annotations',)
        4       IMPORT_NAME                     0: __future__
        6       IMPORT_FROM                     1: annotations
        8       STORE_NAME                      1: annotations
        10      POP_TOP                         
        12      LOAD_CONST                      0: 0
        14      LOAD_CONST                      2: None
        16      IMPORT_NAME                     2: argparse
        18      STORE_NAME                      2: argparse
        20      LOAD_CONST                      0: 0
        22      LOAD_CONST                      2: None
        24      IMPORT_NAME                     3: json
        26      STORE_NAME                      3: json
        28      LOAD_CONST                      0: 0
        30      LOAD_CONST                      2: None
        32      IMPORT_NAME                     4: os
        34      STORE_NAME                      4: os
        36      LOAD_CONST                      0: 0
        38      LOAD_CONST                      3: ('Path',)
        40      IMPORT_NAME                     5: pathlib
        42      IMPORT_FROM                     6: Path
        44      STORE_NAME                      6: Path
        46      POP_TOP                         
        48      LOAD_CONST                      0: 0
        50      LOAD_CONST                      4: ('ROOT', 'expand')
        52      IMPORT_NAME                     7: common
        54      IMPORT_FROM                     8: ROOT
        56      STORE_NAME                      8: ROOT
        58      IMPORT_FROM                     9: expand
        60      STORE_NAME                      9: expand
        62      POP_TOP                         
        64      LOAD_CONST                      5: 'Path'
        66      LOAD_CONST                      6: 'dict'
        68      LOAD_CONST                      7: ('path', 'return')
        70      BUILD_CONST_KEY_MAP             2
        72      LOAD_CONST                      8: <CODE> _read_json
        74      LOAD_CONST                      9: '_read_json'
        76      MAKE_FUNCTION                   4
        78      STORE_NAME                      10: _read_json
        80      LOAD_CONST                      5: 'Path'
        82      LOAD_CONST                      6: 'dict'
        84      LOAD_CONST                      10: 'None'
        86      LOAD_CONST                      11: ('path', 'payload', 'return')
        88      BUILD_CONST_KEY_MAP             3
        90      LOAD_CONST                      12: <CODE> _write_json
        92      LOAD_CONST                      13: '_write_json'
        94      MAKE_FUNCTION                   4
        96      STORE_NAME                      11: _write_json
        98      LOAD_CONST                      25: ('',)
        100     LOAD_CONST                      15: 'str'
        102     LOAD_CONST                      16: 'list[str]'
        104     LOAD_CONST                      17: ('cli_targets', 'return')
        106     BUILD_CONST_KEY_MAP             2
        108     LOAD_CONST                      18: <CODE> _resolve_target_keys
        110     LOAD_CONST                      19: '_resolve_target_keys'
        112     MAKE_FUNCTION                   5
        114     STORE_NAME                      12: _resolve_target_keys
        116     LOAD_CONST                      20: 'int'
        118     LOAD_CONST                      21: ('return',)
        120     BUILD_CONST_KEY_MAP             1
        122     LOAD_CONST                      22: <CODE> main
        124     LOAD_CONST                      23: 'main'
        126     MAKE_FUNCTION                   4
        128     STORE_NAME                      13: main
        130     LOAD_NAME                       14: __name__
        132     LOAD_CONST                      24: '__main__'
        134     COMPARE_OP                      2 (==)
        136     POP_JUMP_IF_FALSE               148
        138     LOAD_NAME                       15: SystemExit
        140     LOAD_NAME                       13: main
        142     CALL_FUNCTION                   0
        144     CALL_FUNCTION                   1
        146     RAISE_VARARGS                   1
        148     LOAD_CONST                      2: None
        150     RETURN_VALUE                    
