adapter_llm.cpython-39.pyc (Python 3.9)
[Code]
    File Name: /Users/s/openclaw-memory-auto/local_llm_adapter/adapter_llm.py
    Object Name: <module>
    Arg Count: 0
    Pos Only Arg Count: 0
    KW Only Arg Count: 0
    Locals: 0
    Stack Size: 5
    Flags: 0x01000040 (CO_NOFREE | CO_FUTURE_ANNOTATIONS)
    [Names]
        '__future__'
        'annotations'
        'os'
        'sys'
        'pathlib'
        'Path'
        'typing'
        'Dict'
        'yaml'
        '__file__'
        'resolve'
        'parents'
        'ROOT'
        'CFG'
        '_load_cfg'
        'CONFIG'
        'str'
        'path'
        'insert'
        'integration_hooks.service_models'
        'MemoryCandidate'
        'mcp_server.memory_service_interface'
        'MemoryServiceInterface'
        'from_config'
        'SERVICE'
        'submit_memory_candidate'
        'parse_event_rule_layer'
        'llm_enhance'
        'process_event'
        '__name__'
        'sample_event'
        'print'
    [Var Names]
    [Free Vars]
    [Cell Vars]
    [Constants]
        0
        (
            'annotations'
        )
        None
        (
            'Path'
        )
        (
            'Dict'
        )
        1
        'config'
        'mcp_config.yaml'
        'dict'
        (
            'return'
        )
        [Code]
            File Name: /Users/s/openclaw-memory-auto/local_llm_adapter/adapter_llm.py
            Object Name: _load_cfg
            Arg Count: 0
            Pos Only Arg Count: 0
            KW Only Arg Count: 0
            Locals: 0
            Stack Size: 5
            Flags: 0x01000043 (CO_OPTIMIZED | CO_NEWLOCALS | CO_NOFREE | CO_FUTURE_ANNOTATIONS)
            [Names]
                'CFG'
                'exists'
                'yaml'
                'safe_load'
                'read_text'
            [Var Names]
            [Free Vars]
            [Cell Vars]
            [Constants]
                None
                'utf-8'
                (
                    'encoding'
                )
            [Disassembly]
                0       LOAD_GLOBAL                     0: CFG
                2       LOAD_METHOD                     1: exists
                4       CALL_METHOD                     0
                6       POP_JUMP_IF_FALSE               30
                8       LOAD_GLOBAL                     2: yaml
                10      LOAD_METHOD                     3: safe_load
                12      LOAD_GLOBAL                     0: CFG
                14      LOAD_ATTR                       4: read_text
                16      LOAD_CONST                      1: 'utf-8'
                18      LOAD_CONST                      2: ('encoding',)
                20      CALL_FUNCTION_KW                1
                22      CALL_METHOD                     1
                24      JUMP_IF_TRUE_OR_POP             28
                26      BUILD_MAP                       0
                28      RETURN_VALUE                    
                30      BUILD_MAP                       0
                32      RETURN_VALUE                    
        '_load_cfg'
        (
            'MemoryCandidate'
        )
        (
            'MemoryServiceInterface'
        )
        'Dict'
        (
            'candidate'
        )
        [Code]
            File Name: /Users/s/openclaw-memory-auto/local_llm_adapter/adapter_llm.py
            Object Name: submit_memory_candidate
            Arg Count: 1
            Pos Only Arg Count: 0
            KW Only Arg Count: 0
            Locals: 4
            Stack Size: 11
            Flags: 0x01000043 (CO_OPTIMIZED | CO_NEWLOCALS | CO_NOFREE | CO_FUTURE_ANNOTATIONS)
            [Names]
                'SERVICE'
                'available'
                'core_error'
                'str'
                'get'
                'strip'
                'MemoryCandidate'
                'dict'
                'submit'
            [Var Names]
                'candidate'
                'text'
                'source'
                'mem'
            [Free Vars]
            [Cell Vars]
            [Constants]
                None
                False
                'core_unavailable'
                'E_CORE_UNAVAILABLE'
                (
                    'ok'
                    'reason'
                    'error'
                    'error_code'
                )
                'content'
                ''
                'source'
                'adapter:unknown'
                'empty_content'
                'E_EMPTY_CONTENT'
                (
                    'ok'
                    'reason'
                    'error_code'
                )
                'metadata'
                'kind'
                'interaction_memory'
                'confidence'
                'llm_summary'
                (
                    'source'
                    'content'
                    'metadata'
                    'kind'
                    'confidence'
                    'llm_summary'
                )
            [Disassembly]
                0       LOAD_GLOBAL                     0: SERVICE
                2       LOAD_METHOD                     1: available
                4       CALL_METHOD                     0
                6       POP_JUMP_IF_TRUE                24
                8       LOAD_CONST                      1: False
                10      LOAD_CONST                      2: 'core_unavailable'
                12      LOAD_GLOBAL                     0: SERVICE
                14      LOAD_ATTR                       2: core_error
                16      LOAD_CONST                      3: 'E_CORE_UNAVAILABLE'
                18      LOAD_CONST                      4: ('ok', 'reason', 'error', 'error_code')
                20      BUILD_CONST_KEY_MAP             4
                22      RETURN_VALUE                    
                24      LOAD_GLOBAL                     3: str
                26      LOAD_FAST                       0: candidate
                28      LOAD_METHOD                     4: get
                30      LOAD_CONST                      5: 'content'
                32      LOAD_CONST                      6: ''
                34      CALL_METHOD                     2
                36      CALL_FUNCTION                   1
                38      LOAD_METHOD                     5: strip
                40      CALL_METHOD                     0
                42      STORE_FAST                      1: text
                44      LOAD_GLOBAL                     3: str
                46      LOAD_FAST                       0: candidate
                48      LOAD_METHOD                     4: get
                50      LOAD_CONST                      7: 'source'
                52      LOAD_CONST                      8: 'adapter:unknown'
                54      CALL_METHOD                     2
                56      CALL_FUNCTION                   1
                58      LOAD_METHOD                     5: strip
                60      CALL_METHOD                     0
                62      JUMP_IF_TRUE_OR_POP             66
                64      LOAD_CONST                      8: 'adapter:unknown'
                66      STORE_FAST                      2: source
                68      LOAD_FAST                       1: text
                70      POP_JUMP_IF_TRUE                84
                72      LOAD_CONST                      1: False
                74      LOAD_CONST                      9: 'empty_content'
                76      LOAD_CONST                      10: 'E_EMPTY_CONTENT'
                78      LOAD_CONST                      11: ('ok', 'reason', 'error_code')
                80      BUILD_CONST_KEY_MAP             3
                82      RETURN_VALUE                    
                84      LOAD_GLOBAL                     6: MemoryCandidate
                86      LOAD_FAST                       2: source
                88      LOAD_FAST                       1: text
                90      LOAD_GLOBAL                     7: dict
                92      LOAD_FAST                       0: candidate
                94      LOAD_METHOD                     4: get
                96      LOAD_CONST                      12: 'metadata'
                98      CALL_METHOD                     1
                100     JUMP_IF_TRUE_OR_POP             104
                102     BUILD_MAP                       0
                104     CALL_FUNCTION                   1
                106     LOAD_GLOBAL                     3: str
                108     LOAD_FAST                       0: candidate
                110     LOAD_METHOD                     4: get
                112     LOAD_CONST                      13: 'kind'
                114     LOAD_CONST                      14: 'interaction_memory'
                116     CALL_METHOD                     2
                118     CALL_FUNCTION                   1
                120     LOAD_FAST                       0: candidate
                122     LOAD_METHOD                     4: get
                124     LOAD_CONST                      15: 'confidence'
                126     LOAD_CONST                      0: None
                128     CALL_METHOD                     2
                130     LOAD_GLOBAL                     3: str
                132     LOAD_FAST                       0: candidate
                134     LOAD_METHOD                     4: get
                136     LOAD_CONST                      16: 'llm_summary'
                138     LOAD_CONST                      6: ''
                140     CALL_METHOD                     2
                142     CALL_FUNCTION                   1
                144     LOAD_CONST                      17: ('source', 'content', 'metadata', 'kind', 'confidence', 'llm_summary')
                146     CALL_FUNCTION_KW                6
                148     STORE_FAST                      3: mem
                150     LOAD_GLOBAL                     0: SERVICE
                152     LOAD_METHOD                     8: submit
                154     LOAD_FAST                       3: mem
                156     CALL_METHOD                     1
                158     RETURN_VALUE                    
        'submit_memory_candidate'
        [Code]
            File Name: /Users/s/openclaw-memory-auto/local_llm_adapter/adapter_llm.py
            Object Name: parse_event_rule_layer
            Arg Count: 1
            Pos Only Arg Count: 0
            KW Only Arg Count: 0
            Locals: 2
            Stack Size: 6
            Flags: 0x01000043 (CO_OPTIMIZED | CO_NEWLOCALS | CO_NOFREE | CO_FUTURE_ANNOTATIONS)
            [Names]
                'get'
            [Var Names]
                'event'
                'candidate'
            [Free Vars]
            [Cell Vars]
            [Constants]
                None
                'source'
                'adapter:event'
                'text'
                ''
                'timestamp'
                'interaction_memory'
                (
                    'source'
                    'content'
                    'metadata'
                    'kind'
                )
            [Disassembly]
                0       LOAD_FAST                       0: event
                2       LOAD_METHOD                     0: get
                4       LOAD_CONST                      1: 'source'
                6       LOAD_CONST                      2: 'adapter:event'
                8       CALL_METHOD                     2
                10      LOAD_FAST                       0: event
                12      LOAD_METHOD                     0: get
                14      LOAD_CONST                      3: 'text'
                16      LOAD_CONST                      4: ''
                18      CALL_METHOD                     2
                20      LOAD_CONST                      5: 'timestamp'
                22      LOAD_FAST                       0: event
                24      LOAD_METHOD                     0: get
                26      LOAD_CONST                      5: 'timestamp'
                28      CALL_METHOD                     1
                30      BUILD_MAP                       1
                32      LOAD_CONST                      6: 'interaction_memory'
                34      LOAD_CONST                      7: ('source', 'content', 'metadata', 'kind')
                36      BUILD_CONST_KEY_MAP             4
                38      STORE_FAST                      1: candidate
                40      LOAD_FAST                       1: candidate
                42      RETURN_VALUE                    
        'parse_event_rule_layer'
        [Code]
            File Name: /Users/s/openclaw-memory-auto/local_llm_adapter/adapter_llm.py
            Object Name: llm_enhance
            Arg Count: 1
            Pos Only Arg Count: 0
            KW Only Arg Count: 0
            Locals: 2
            Stack Size: 5
            Flags: 0x01000043 (CO_OPTIMIZED | CO_NEWLOCALS | CO_NOFREE | CO_FUTURE_ANNOTATIONS)
            [Names]
                'str'
                'get'
                'len'
            [Var Names]
                'candidate'
                'text'
            [Free Vars]
            [Cell Vars]
            [Constants]
                None
                'content'
                ''
                80
                '...'
                'llm_summary'
                0.95
                'confidence'
            [Disassembly]
                0       LOAD_GLOBAL                     0: str
                2       LOAD_FAST                       0: candidate
                4       LOAD_METHOD                     1: get
                6       LOAD_CONST                      1: 'content'
                8       LOAD_CONST                      2: ''
                10      CALL_METHOD                     2
                12      CALL_FUNCTION                   1
                14      STORE_FAST                      1: text
                16      LOAD_GLOBAL                     2: len
                18      LOAD_FAST                       1: text
                20      CALL_FUNCTION                   1
                22      LOAD_CONST                      3: 80
                24      COMPARE_OP                      4 (>)
                26      POP_JUMP_IF_FALSE               44
                28      LOAD_FAST                       1: text
                30      LOAD_CONST                      0: None
                32      LOAD_CONST                      3: 80
                34      BUILD_SLICE                     2
                36      BINARY_SUBSCR                   
                38      LOAD_CONST                      4: '...'
                40      BINARY_ADD                      
                42      JUMP_FORWARD                    2 (to 46)
                44      LOAD_FAST                       1: text
                46      LOAD_FAST                       0: candidate
                48      LOAD_CONST                      5: 'llm_summary'
                50      STORE_SUBSCR                    
                52      LOAD_CONST                      6: 0.95
                54      LOAD_FAST                       0: candidate
                56      LOAD_CONST                      7: 'confidence'
                58      STORE_SUBSCR                    
                60      LOAD_FAST                       0: candidate
                62      RETURN_VALUE                    
        'llm_enhance'
        [Code]
            File Name: /Users/s/openclaw-memory-auto/local_llm_adapter/adapter_llm.py
            Object Name: process_event
            Arg Count: 1
            Pos Only Arg Count: 0
            KW Only Arg Count: 0
            Locals: 2
            Stack Size: 2
            Flags: 0x01000043 (CO_OPTIMIZED | CO_NEWLOCALS | CO_NOFREE | CO_FUTURE_ANNOTATIONS)
            [Names]
                'parse_event_rule_layer'
                'llm_enhance'
                'submit_memory_candidate'
            [Var Names]
                'event'
                'candidate'
            [Free Vars]
            [Cell Vars]
            [Constants]
                None
            [Disassembly]
                0       LOAD_GLOBAL                     0: parse_event_rule_layer
                2       LOAD_FAST                       0: event
                4       CALL_FUNCTION                   1
                6       STORE_FAST                      1: candidate
                8       LOAD_GLOBAL                     1: llm_enhance
                10      LOAD_FAST                       1: candidate
                12      CALL_FUNCTION                   1
                14      STORE_FAST                      1: candidate
                16      LOAD_GLOBAL                     2: submit_memory_candidate
                18      LOAD_FAST                       1: candidate
                20      CALL_FUNCTION                   1
                22      RETURN_VALUE                    
        'process_event'
        '__main__'
        'adapter:CustomToolX'
        '用户操作日志示例，自动进入记忆 pipeline'
        '2026-04-15T10:00:00'
        (
            'source'
            'text'
            'timestamp'
        )
    [Disassembly]
        0       LOAD_CONST                      0: 0
        2       LOAD_CONST                      1: ('annotations',)
        4       IMPORT_NAME                     0: __future__
        6       IMPORT_FROM                     1: annotations
        8       STORE_NAME                      1: annotations
        10      POP_TOP                         
        12      LOAD_CONST                      0: 0
        14      LOAD_CONST                      2: None
        16      IMPORT_NAME                     2: os
        18      STORE_NAME                      2: os
        20      LOAD_CONST                      0: 0
        22      LOAD_CONST                      2: None
        24      IMPORT_NAME                     3: sys
        26      STORE_NAME                      3: sys
        28      LOAD_CONST                      0: 0
        30      LOAD_CONST                      3: ('Path',)
        32      IMPORT_NAME                     4: pathlib
        34      IMPORT_FROM                     5: Path
        36      STORE_NAME                      5: Path
        38      POP_TOP                         
        40      LOAD_CONST                      0: 0
        42      LOAD_CONST                      4: ('Dict',)
        44      IMPORT_NAME                     6: typing
        46      IMPORT_FROM                     7: Dict
        48      STORE_NAME                      7: Dict
        50      POP_TOP                         
        52      LOAD_CONST                      0: 0
        54      LOAD_CONST                      2: None
        56      IMPORT_NAME                     8: yaml
        58      STORE_NAME                      8: yaml
        60      LOAD_NAME                       5: Path
        62      LOAD_NAME                       9: __file__
        64      CALL_FUNCTION                   1
        66      LOAD_METHOD                     10: resolve
        68      CALL_METHOD                     0
        70      LOAD_ATTR                       11: parents
        72      LOAD_CONST                      5: 1
        74      BINARY_SUBSCR                   
        76      STORE_NAME                      12: ROOT
        78      LOAD_NAME                       12: ROOT
        80      LOAD_CONST                      6: 'config'
        82      BINARY_TRUE_DIVIDE              
        84      LOAD_CONST                      7: 'mcp_config.yaml'
        86      BINARY_TRUE_DIVIDE              
        88      STORE_NAME                      13: CFG
        90      LOAD_CONST                      8: 'dict'
        92      LOAD_CONST                      9: ('return',)
        94      BUILD_CONST_KEY_MAP             1
        96      LOAD_CONST                      10: <CODE> _load_cfg
        98      LOAD_CONST                      11: '_load_cfg'
        100     MAKE_FUNCTION                   4
        102     STORE_NAME                      14: _load_cfg
        104     LOAD_NAME                       14: _load_cfg
        106     CALL_FUNCTION                   0
        108     STORE_NAME                      15: CONFIG
        110     LOAD_NAME                       16: str
        112     LOAD_NAME                       12: ROOT
        114     CALL_FUNCTION                   1
        116     LOAD_NAME                       3: sys
        118     LOAD_ATTR                       17: path
        120     CONTAINS_OP                     1 (not in)
        122     POP_JUMP_IF_FALSE               142
        124     LOAD_NAME                       3: sys
        126     LOAD_ATTR                       17: path
        128     LOAD_METHOD                     18: insert
        130     LOAD_CONST                      0: 0
        132     LOAD_NAME                       16: str
        134     LOAD_NAME                       12: ROOT
        136     CALL_FUNCTION                   1
        138     CALL_METHOD                     2
        140     POP_TOP                         
        142     LOAD_CONST                      0: 0
        144     LOAD_CONST                      12: ('MemoryCandidate',)
        146     IMPORT_NAME                     19: integration_hooks.service_models
        148     IMPORT_FROM                     20: MemoryCandidate
        150     STORE_NAME                      20: MemoryCandidate
        152     POP_TOP                         
        154     LOAD_CONST                      0: 0
        156     LOAD_CONST                      13: ('MemoryServiceInterface',)
        158     IMPORT_NAME                     21: mcp_server.memory_service_interface
        160     IMPORT_FROM                     22: MemoryServiceInterface
        162     STORE_NAME                      22: MemoryServiceInterface
        164     POP_TOP                         
        166     LOAD_NAME                       22: MemoryServiceInterface
        168     LOAD_METHOD                     23: from_config
        170     LOAD_NAME                       15: CONFIG
        172     CALL_METHOD                     1
        174     STORE_NAME                      24: SERVICE
        176     LOAD_CONST                      14: 'Dict'
        178     LOAD_CONST                      15: ('candidate',)
        180     BUILD_CONST_KEY_MAP             1
        182     LOAD_CONST                      16: <CODE> submit_memory_candidate
        184     LOAD_CONST                      17: 'submit_memory_candidate'
        186     MAKE_FUNCTION                   4
        188     STORE_NAME                      25: submit_memory_candidate
        190     LOAD_CONST                      18: <CODE> parse_event_rule_layer
        192     LOAD_CONST                      19: 'parse_event_rule_layer'
        194     MAKE_FUNCTION                   0
        196     STORE_NAME                      26: parse_event_rule_layer
        198     LOAD_CONST                      20: <CODE> llm_enhance
        200     LOAD_CONST                      21: 'llm_enhance'
        202     MAKE_FUNCTION                   0
        204     STORE_NAME                      27: llm_enhance
        206     LOAD_CONST                      22: <CODE> process_event
        208     LOAD_CONST                      23: 'process_event'
        210     MAKE_FUNCTION                   0
        212     STORE_NAME                      28: process_event
        214     LOAD_NAME                       29: __name__
        216     LOAD_CONST                      24: '__main__'
        218     COMPARE_OP                      2 (==)
        220     POP_JUMP_IF_FALSE               246
        222     LOAD_CONST                      25: 'adapter:CustomToolX'
        224     LOAD_CONST                      26: '用户操作日志示例，自动进入记忆 pipeline'
        226     LOAD_CONST                      27: '2026-04-15T10:00:00'
        228     LOAD_CONST                      28: ('source', 'text', 'timestamp')
        230     BUILD_CONST_KEY_MAP             3
        232     STORE_NAME                      30: sample_event
        234     LOAD_NAME                       31: print
        236     LOAD_NAME                       28: process_event
        238     LOAD_NAME                       30: sample_event
        240     CALL_FUNCTION                   1
        242     CALL_FUNCTION                   1
        244     POP_TOP                         
        246     LOAD_CONST                      2: None
        248     RETURN_VALUE                    
