memory_service_interface.cpython-39.pyc (Python 3.9)
[Code]
    File Name: /Users/s/openclaw-memory-auto/mcp_server/memory_service_interface.py
    Object Name: <module>
    Arg Count: 0
    Pos Only Arg Count: 0
    KW Only Arg Count: 0
    Locals: 0
    Stack Size: 3
    Flags: 0x01000040 (CO_NOFREE | CO_FUTURE_ANNOTATIONS)
    [Names]
        '__future__'
        'annotations'
        'json'
        'os'
        'sys'
        'datetime'
        'date'
        'timedelta'
        'pathlib'
        'Path'
        'typing'
        'Any'
        'Dict'
        'List'
        'Optional'
        'integration_hooks.service_models'
        'MemoryCandidate'
        'ERR_CORE_UNAVAILABLE'
        'ERR_PROFILE_NOT_FOUND'
        'ERR_PROFILE_PARSE'
        'ERR_PROFILE_UNKNOWN'
        'MemoryServiceInterface'
    [Var Names]
    [Free Vars]
    [Cell Vars]
    [Constants]
        0
        (
            'annotations'
        )
        None
        (
            'date'
            'datetime'
            'timedelta'
        )
        (
            'Path'
        )
        (
            'Any'
            'Dict'
            'List'
            'Optional'
        )
        (
            'MemoryCandidate'
        )
        'E_CORE_UNAVAILABLE'
        'E_PROFILE_NOT_FOUND'
        'E_PROFILE_PARSE'
        'E_PROFILE_UNKNOWN'
        [Code]
            File Name: /Users/s/openclaw-memory-auto/mcp_server/memory_service_interface.py
            Object Name: MemoryServiceInterface
            Arg Count: 0
            Pos Only Arg Count: 0
            KW Only Arg Count: 0
            Locals: 0
            Stack Size: 6
            Flags: 0x01000040 (CO_NOFREE | CO_FUTURE_ANNOTATIONS)
            [Names]
                '__name__'
                '__module__'
                '__qualname__'
                '__doc__'
                '__init__'
                'classmethod'
                'from_config'
                'available'
                'submit'
                'query'
                'context'
                'status'
                'profile'
                '_core_unavailable'
                '_resource_int'
                '_profile_ok'
                '_profile_error'
                '_normalize_submit_result'
                '_normalize_result_row'
                'staticmethod'
                '_json_safe'
                '_expand'
            [Var Names]
            [Free Vars]
            [Cell Vars]
            [Constants]
                'MemoryServiceInterface'
                'Thin service boundary between server/adapter and memory engine.'
                None
                'Any'
                'Dict[str, Any]'
                'Optional[str]'
                'None'
                (
                    'core'
                    'config'
                    'core_error'
                    'return'
                )
                [Code]
                    File Name: /Users/s/openclaw-memory-auto/mcp_server/memory_service_interface.py
                    Object Name: __init__
                    Arg Count: 4
                    Pos Only Arg Count: 0
                    KW Only Arg Count: 0
                    Locals: 4
                    Stack Size: 6
                    Flags: 0x01000043 (CO_OPTIMIZED | CO_NEWLOCALS | CO_NOFREE | CO_FUTURE_ANNOTATIONS)
                    [Names]
                        'core'
                        'config'
                        'core_error'
                        '_expand'
                        'get'
                        'workspace'
                        'isinstance'
                        'dict'
                        'profile_cfg'
                    [Var Names]
                        'self'
                        'core'
                        'config'
                        'core_error'
                    [Free Vars]
                    [Cell Vars]
                    [Constants]
                        None
                        ''
                        'memory_core'
                        'workspace'
                        '~/.codex/memories/openclaw-memory-workspace'
                        'resources'
                    [Disassembly]
                        0       LOAD_FAST                       1: core
                        2       LOAD_FAST                       0: self
                        4       STORE_ATTR                      0: core
                        6       LOAD_FAST                       2: config
                        8       JUMP_IF_TRUE_OR_POP             12
                        10      BUILD_MAP                       0
                        12      LOAD_FAST                       0: self
                        14      STORE_ATTR                      1: config
                        16      LOAD_FAST                       3: core_error
                        18      JUMP_IF_TRUE_OR_POP             22
                        20      LOAD_CONST                      1: ''
                        22      LOAD_FAST                       0: self
                        24      STORE_ATTR                      2: core_error
                        26      LOAD_FAST                       0: self
                        28      LOAD_METHOD                     3: _expand
                        30      LOAD_FAST                       0: self
                        32      LOAD_ATTR                       1: config
                        34      LOAD_METHOD                     4: get
                        36      LOAD_CONST                      2: 'memory_core'
                        38      BUILD_MAP                       0
                        40      CALL_METHOD                     2
                        42      LOAD_METHOD                     4: get
                        44      LOAD_CONST                      3: 'workspace'
                        46      LOAD_CONST                      4: '~/.codex/memories/openclaw-memory-workspace'
                        48      CALL_METHOD                     2
                        50      CALL_METHOD                     1
                        52      LOAD_FAST                       0: self
                        54      STORE_ATTR                      5: workspace
                        56      LOAD_GLOBAL                     6: isinstance
                        58      LOAD_FAST                       0: self
                        60      LOAD_ATTR                       1: config
                        62      LOAD_METHOD                     4: get
                        64      LOAD_CONST                      5: 'resources'
                        66      BUILD_MAP                       0
                        68      CALL_METHOD                     2
                        70      LOAD_GLOBAL                     7: dict
                        72      CALL_FUNCTION                   2
                        74      POP_JUMP_IF_FALSE               90
                        76      LOAD_FAST                       0: self
                        78      LOAD_ATTR                       1: config
                        80      LOAD_METHOD                     4: get
                        82      LOAD_CONST                      5: 'resources'
                        84      BUILD_MAP                       0
                        86      CALL_METHOD                     2
                        88      JUMP_FORWARD                    2 (to 92)
                        90      BUILD_MAP                       0
                        92      LOAD_FAST                       0: self
                        94      STORE_ATTR                      8: profile_cfg
                        96      LOAD_CONST                      0: None
                        98      RETURN_VALUE                    
                'MemoryServiceInterface.__init__'
                "'MemoryServiceInterface'"
                (
                    'config'
                    'return'
                )
                [Code]
                    File Name: /Users/s/openclaw-memory-auto/mcp_server/memory_service_interface.py
                    Object Name: from_config
                    Arg Count: 2
                    Pos Only Arg Count: 0
                    KW Only Arg Count: 0
                    Locals: 8
                    Stack Size: 10
                    Flags: 0x01000043 (CO_OPTIMIZED | CO_NEWLOCALS | CO_NOFREE | CO_FUTURE_ANNOTATIONS)
                    [Names]
                        'os'
                        'path'
                        'expanduser'
                        'get'
                        'sys'
                        'insert'
                        'memory.core'
                        'MemoryCore'
                        'Exception'
                        'str'
                    [Var Names]
                        'cls'
                        'config'
                        'cfg'
                        'python_path'
                        'core'
                        'core_error'
                        'MemoryCore'
                        'exc'
                    [Free Vars]
                    [Cell Vars]
                    [Constants]
                        None
                        'memory_core'
                        'python_path'
                        '~/.codex/skills/openclaw-memory/python'
                        0
                        ''
                        (
                            'MemoryCore'
                        )
                        (
                            'core'
                            'config'
                            'core_error'
                        )
                    [Disassembly]
                        0       LOAD_FAST                       1: config
                        2       JUMP_IF_TRUE_OR_POP             6
                        4       BUILD_MAP                       0
                        6       STORE_FAST                      2: cfg
                        8       LOAD_GLOBAL                     0: os
                        10      LOAD_ATTR                       1: path
                        12      LOAD_METHOD                     2: expanduser
                        14      LOAD_FAST                       2: cfg
                        16      LOAD_METHOD                     3: get
                        18      LOAD_CONST                      1: 'memory_core'
                        20      BUILD_MAP                       0
                        22      CALL_METHOD                     2
                        24      LOAD_METHOD                     3: get
                        26      LOAD_CONST                      2: 'python_path'
                        28      LOAD_CONST                      3: '~/.codex/skills/openclaw-memory/python'
                        30      CALL_METHOD                     2
                        32      CALL_METHOD                     1
                        34      STORE_FAST                      3: python_path
                        36      LOAD_FAST                       3: python_path
                        38      LOAD_GLOBAL                     4: sys
                        40      LOAD_ATTR                       1: path
                        42      CONTAINS_OP                     1 (not in)
                        44      POP_JUMP_IF_FALSE               60
                        46      LOAD_GLOBAL                     4: sys
                        48      LOAD_ATTR                       1: path
                        50      LOAD_METHOD                     5: insert
                        52      LOAD_CONST                      4: 0
                        54      LOAD_FAST                       3: python_path
                        56      CALL_METHOD                     2
                        58      POP_TOP                         
                        60      LOAD_CONST                      0: None
                        62      STORE_FAST                      4: core
                        64      LOAD_CONST                      5: ''
                        66      STORE_FAST                      5: core_error
                        68      SETUP_FINALLY                   22 (to 92)
                        70      LOAD_CONST                      4: 0
                        72      LOAD_CONST                      6: ('MemoryCore',)
                        74      IMPORT_NAME                     6: memory.core
                        76      IMPORT_FROM                     7: MemoryCore
                        78      STORE_FAST                      6: MemoryCore
                        80      POP_TOP                         
                        82      LOAD_FAST                       6: MemoryCore
                        84      CALL_FUNCTION                   0
                        86      STORE_FAST                      4: core
                        88      POP_BLOCK                       
                        90      JUMP_FORWARD                    44 (to 136)
                        92      DUP_TOP                         
                        94      LOAD_GLOBAL                     8: Exception
                        96      JUMP_IF_NOT_EXC_MATCH           134
                        98      POP_TOP                         
                        100     STORE_FAST                      7: exc
                        102     POP_TOP                         
                        104     SETUP_FINALLY                   20 (to 126)
                        106     LOAD_GLOBAL                     9: str
                        108     LOAD_FAST                       7: exc
                        110     CALL_FUNCTION                   1
                        112     STORE_FAST                      5: core_error
                        114     POP_BLOCK                       
                        116     POP_EXCEPT                      
                        118     LOAD_CONST                      0: None
                        120     STORE_FAST                      7: exc
                        122     DELETE_FAST                     7: exc
                        124     JUMP_FORWARD                    10 (to 136)
                        126     LOAD_CONST                      0: None
                        128     STORE_FAST                      7: exc
                        130     DELETE_FAST                     7: exc
                        132     RERAISE                         
                        134     RERAISE                         
                        136     LOAD_FAST                       0: cls
                        138     LOAD_FAST                       4: core
                        140     LOAD_FAST                       2: cfg
                        142     LOAD_FAST                       5: core_error
                        144     LOAD_CONST                      7: ('core', 'config', 'core_error')
                        146     CALL_FUNCTION_KW                3
                        148     RETURN_VALUE                    
                'MemoryServiceInterface.from_config'
                'bool'
                (
                    'return'
                )
                [Code]
                    File Name: /Users/s/openclaw-memory-auto/mcp_server/memory_service_interface.py
                    Object Name: available
                    Arg Count: 1
                    Pos Only Arg Count: 0
                    KW Only Arg Count: 0
                    Locals: 1
                    Stack Size: 2
                    Flags: 0x01000043 (CO_OPTIMIZED | CO_NEWLOCALS | CO_NOFREE | CO_FUTURE_ANNOTATIONS)
                    [Names]
                        'core'
                    [Var Names]
                        'self'
                    [Free Vars]
                    [Cell Vars]
                    [Constants]
                        None
                    [Disassembly]
                        0       LOAD_FAST                       0: self
                        2       LOAD_ATTR                       0: core
                        4       LOAD_CONST                      0: None
                        6       IS_OP                           1 (is not)
                        8       RETURN_VALUE                    
                'MemoryServiceInterface.available'
                'MemoryCandidate'
                (
                    'candidate'
                    'return'
                )
                [Code]
                    File Name: /Users/s/openclaw-memory-auto/mcp_server/memory_service_interface.py
                    Object Name: submit
                    Arg Count: 2
                    Pos Only Arg Count: 0
                    KW Only Arg Count: 0
                    Locals: 8
                    Stack Size: 10
                    Flags: 0x01000043 (CO_OPTIMIZED | CO_NEWLOCALS | CO_NOFREE | CO_FUTURE_ANNOTATIONS)
                    [Names]
                        'available'
                        '_core_unavailable'
                        'str'
                        'source'
                        'content'
                        'getattr'
                        'core'
                        'hasattr'
                        'process_interaction'
                        '_normalize_submit_result'
                        'append_interaction'
                        'Exception'
                    [Var Names]
                        'self'
                        'candidate'
                        'source'
                        'text'
                        'auto'
                        'raw'
                        'normalized'
                        'exc'
                    [Free Vars]
                    [Cell Vars]
                    [Constants]
                        None
                        ''
                        'auto_memory'
                        'process_interaction'
                        (
                            'source'
                        )
                        True
                        'auto_memory_pipeline'
                        'items'
                        'accepted_count'
                        'review_count'
                        'rejected_count'
                        'saved_any'
                        (
                            'ok'
                            'mode'
                            'source'
                            'result'
                            'accepted_count'
                            'review_count'
                            'rejected_count'
                            'saved_any'
                        )
                        'append_interaction'
                        1
                        0
                        False
                        'E_SUBMIT_FAILED'
                        (
                            'ok'
                            'error'
                            'error_code'
                        )
                    [Disassembly]
                        0       LOAD_FAST                       0: self
                        2       LOAD_METHOD                     0: available
                        4       CALL_METHOD                     0
                        6       POP_JUMP_IF_TRUE                16
                        8       LOAD_FAST                       0: self
                        10      LOAD_METHOD                     1: _core_unavailable
                        12      CALL_METHOD                     0
                        14      RETURN_VALUE                    
                        16      LOAD_GLOBAL                     2: str
                        18      LOAD_FAST                       1: candidate
                        20      LOAD_ATTR                       3: source
                        22      JUMP_IF_TRUE_OR_POP             26
                        24      LOAD_CONST                      1: ''
                        26      CALL_FUNCTION                   1
                        28      STORE_FAST                      2: source
                        30      LOAD_GLOBAL                     2: str
                        32      LOAD_FAST                       1: candidate
                        34      LOAD_ATTR                       4: content
                        36      JUMP_IF_TRUE_OR_POP             40
                        38      LOAD_CONST                      1: ''
                        40      CALL_FUNCTION                   1
                        42      STORE_FAST                      3: text
                        44      SETUP_FINALLY                   132 (to 178)
                        46      LOAD_GLOBAL                     5: getattr
                        48      LOAD_FAST                       0: self
                        50      LOAD_ATTR                       6: core
                        52      LOAD_CONST                      2: 'auto_memory'
                        54      LOAD_CONST                      0: None
                        56      CALL_FUNCTION                   3
                        58      STORE_FAST                      4: auto
                        60      LOAD_FAST                       4: auto
                        62      POP_JUMP_IF_FALSE               142
                        64      LOAD_GLOBAL                     7: hasattr
                        66      LOAD_FAST                       4: auto
                        68      LOAD_CONST                      3: 'process_interaction'
                        70      CALL_FUNCTION                   2
                        72      POP_JUMP_IF_FALSE               142
                        74      LOAD_FAST                       4: auto
                        76      LOAD_ATTR                       8: process_interaction
                        78      LOAD_FAST                       3: text
                        80      LOAD_FAST                       2: source
                        82      LOAD_CONST                      4: ('source',)
                        84      CALL_FUNCTION_KW                2
                        86      STORE_FAST                      5: raw
                        88      LOAD_FAST                       0: self
                        90      LOAD_METHOD                     9: _normalize_submit_result
                        92      LOAD_FAST                       5: raw
                        94      CALL_METHOD                     1
                        96      STORE_FAST                      6: normalized
                        98      LOAD_CONST                      5: True
                        100     LOAD_CONST                      6: 'auto_memory_pipeline'
                        102     LOAD_FAST                       2: source
                        104     LOAD_FAST                       6: normalized
                        106     LOAD_CONST                      7: 'items'
                        108     BINARY_SUBSCR                   
                        110     LOAD_FAST                       6: normalized
                        112     LOAD_CONST                      8: 'accepted_count'
                        114     BINARY_SUBSCR                   
                        116     LOAD_FAST                       6: normalized
                        118     LOAD_CONST                      9: 'review_count'
                        120     BINARY_SUBSCR                   
                        122     LOAD_FAST                       6: normalized
                        124     LOAD_CONST                      10: 'rejected_count'
                        126     BINARY_SUBSCR                   
                        128     LOAD_FAST                       6: normalized
                        130     LOAD_CONST                      11: 'saved_any'
                        132     BINARY_SUBSCR                   
                        134     LOAD_CONST                      12: ('ok', 'mode', 'source', 'result', 'accepted_count', 'review_count', 'rejected_count', 'saved_any')
                        136     BUILD_CONST_KEY_MAP             8
                        138     POP_BLOCK                       
                        140     RETURN_VALUE                    
                        142     LOAD_FAST                       0: self
                        144     LOAD_ATTR                       6: core
                        146     LOAD_METHOD                     10: append_interaction
                        148     LOAD_FAST                       3: text
                        150     CALL_METHOD                     1
                        152     POP_TOP                         
                        154     LOAD_CONST                      5: True
                        156     LOAD_CONST                      13: 'append_interaction'
                        158     LOAD_FAST                       2: source
                        160     BUILD_LIST                      0
                        162     LOAD_CONST                      14: 1
                        164     LOAD_CONST                      15: 0
                        166     LOAD_CONST                      15: 0
                        168     LOAD_CONST                      5: True
                        170     LOAD_CONST                      12: ('ok', 'mode', 'source', 'result', 'accepted_count', 'review_count', 'rejected_count', 'saved_any')
                        172     BUILD_CONST_KEY_MAP             8
                        174     POP_BLOCK                       
                        176     RETURN_VALUE                    
                        178     DUP_TOP                         
                        180     LOAD_GLOBAL                     11: Exception
                        182     JUMP_IF_NOT_EXC_MATCH           228
                        184     POP_TOP                         
                        186     STORE_FAST                      7: exc
                        188     POP_TOP                         
                        190     SETUP_FINALLY                   28 (to 220)
                        192     LOAD_CONST                      16: False
                        194     LOAD_GLOBAL                     2: str
                        196     LOAD_FAST                       7: exc
                        198     CALL_FUNCTION                   1
                        200     LOAD_CONST                      17: 'E_SUBMIT_FAILED'
                        202     LOAD_CONST                      18: ('ok', 'error', 'error_code')
                        204     BUILD_CONST_KEY_MAP             3
                        206     POP_BLOCK                       
                        208     ROT_FOUR                        
                        210     POP_EXCEPT                      
                        212     LOAD_CONST                      0: None
                        214     STORE_FAST                      7: exc
                        216     DELETE_FAST                     7: exc
                        218     RETURN_VALUE                    
                        220     LOAD_CONST                      0: None
                        222     STORE_FAST                      7: exc
                        224     DELETE_FAST                     7: exc
                        226     RERAISE                         
                        228     RERAISE                         
                        230     LOAD_CONST                      0: None
                        232     RETURN_VALUE                    
                'MemoryServiceInterface.submit'
                5
                'str'
                'int'
                (
                    'query'
                    'top_k'
                    'return'
                )
                [Code]
                    File Name: /Users/s/openclaw-memory-auto/mcp_server/memory_service_interface.py
                    Object Name: query
                    Arg Count: 3
                    Pos Only Arg Count: 0
                    KW Only Arg Count: 0
                    Locals: 6
                    Stack Size: 10
                    Flags: 0x01000003 (CO_OPTIMIZED | CO_NEWLOCALS | CO_FUTURE_ANNOTATIONS)
                    [Names]
                        'available'
                        '_core_unavailable'
                        'core'
                        'retrieve_memories'
                        'len'
                        'Exception'
                        'str'
                    [Var Names]
                        'self'
                        'query'
                        'top_k'
                        'rows'
                        'normalized'
                        'exc'
                    [Free Vars]
                    [Cell Vars]
                        'self'
                    [Constants]
                        None
                        (
                            'top_k'
                        )
                        [Code]
                            File Name: /Users/s/openclaw-memory-auto/mcp_server/memory_service_interface.py
                            Object Name: <listcomp>
                            Arg Count: 1
                            Pos Only Arg Count: 0
                            KW Only Arg Count: 0
                            Locals: 2
                            Stack Size: 5
                            Flags: 0x01000013 (CO_OPTIMIZED | CO_NEWLOCALS | CO_NESTED | CO_FUTURE_ANNOTATIONS)
                            [Names]
                                '_normalize_result_row'
                            [Var Names]
                                '.0'
                                'row'
                            [Free Vars]
                                'self'
                            [Cell Vars]
                            [Constants]
                            [Disassembly]
                                0       BUILD_LIST                      0
                                2       LOAD_FAST                       0: .0
                                4       FOR_ITER                        14 (to 20)
                                6       STORE_FAST                      1: row
                                8       LOAD_DEREF                      0: self
                                10      LOAD_METHOD                     0: _normalize_result_row
                                12      LOAD_FAST                       1: row
                                14      CALL_METHOD                     1
                                16      LIST_APPEND                     2
                                18      JUMP_ABSOLUTE                   4
                                20      RETURN_VALUE                    
                        'MemoryServiceInterface.query.<locals>.<listcomp>'
                        True
                        (
                            'ok'
                            'query'
                            'count'
                            'results'
                        )
                        False
                        'E_QUERY_FAILED'
                        (
                            'ok'
                            'error'
                            'error_code'
                        )
                    [Disassembly]
                        0       LOAD_DEREF                      0: self
                        2       LOAD_METHOD                     0: available
                        4       CALL_METHOD                     0
                        6       POP_JUMP_IF_TRUE                16
                        8       LOAD_DEREF                      0: self
                        10      LOAD_METHOD                     1: _core_unavailable
                        12      CALL_METHOD                     0
                        14      RETURN_VALUE                    
                        16      SETUP_FINALLY                   58 (to 76)
                        18      LOAD_DEREF                      0: self
                        20      LOAD_ATTR                       2: core
                        22      LOAD_ATTR                       3: retrieve_memories
                        24      LOAD_FAST                       1: query
                        26      LOAD_FAST                       2: top_k
                        28      LOAD_CONST                      1: ('top_k',)
                        30      CALL_FUNCTION_KW                2
                        32      STORE_FAST                      3: rows
                        34      LOAD_CLOSURE                    0: self
                        36      BUILD_TUPLE                     1
                        38      LOAD_CONST                      2: <CODE> <listcomp>
                        40      LOAD_CONST                      3: 'MemoryServiceInterface.query.<locals>.<listcomp>'
                        42      MAKE_FUNCTION                   8
                        44      LOAD_FAST                       3: rows
                        46      JUMP_IF_TRUE_OR_POP             50
                        48      BUILD_LIST                      0
                        50      GET_ITER                        
                        52      CALL_FUNCTION                   1
                        54      STORE_FAST                      4: normalized
                        56      LOAD_CONST                      4: True
                        58      LOAD_FAST                       1: query
                        60      LOAD_GLOBAL                     4: len
                        62      LOAD_FAST                       4: normalized
                        64      CALL_FUNCTION                   1
                        66      LOAD_FAST                       4: normalized
                        68      LOAD_CONST                      5: ('ok', 'query', 'count', 'results')
                        70      BUILD_CONST_KEY_MAP             4
                        72      POP_BLOCK                       
                        74      RETURN_VALUE                    
                        76      DUP_TOP                         
                        78      LOAD_GLOBAL                     5: Exception
                        80      JUMP_IF_NOT_EXC_MATCH           126
                        82      POP_TOP                         
                        84      STORE_FAST                      5: exc
                        86      POP_TOP                         
                        88      SETUP_FINALLY                   28 (to 118)
                        90      LOAD_CONST                      6: False
                        92      LOAD_GLOBAL                     6: str
                        94      LOAD_FAST                       5: exc
                        96      CALL_FUNCTION                   1
                        98      LOAD_CONST                      7: 'E_QUERY_FAILED'
                        100     LOAD_CONST                      8: ('ok', 'error', 'error_code')
                        102     BUILD_CONST_KEY_MAP             3
                        104     POP_BLOCK                       
                        106     ROT_FOUR                        
                        108     POP_EXCEPT                      
                        110     LOAD_CONST                      0: None
                        112     STORE_FAST                      5: exc
                        114     DELETE_FAST                     5: exc
                        116     RETURN_VALUE                    
                        118     LOAD_CONST                      0: None
                        120     STORE_FAST                      5: exc
                        122     DELETE_FAST                     5: exc
                        124     RERAISE                         
                        126     RERAISE                         
                        128     LOAD_CONST                      0: None
                        130     RETURN_VALUE                    
                'MemoryServiceInterface.query'
                (
                    'message'
                    'return'
                )
                [Code]
                    File Name: /Users/s/openclaw-memory-auto/mcp_server/memory_service_interface.py
                    Object Name: context
                    Arg Count: 2
                    Pos Only Arg Count: 0
                    KW Only Arg Count: 0
                    Locals: 4
                    Stack Size: 10
                    Flags: 0x01000043 (CO_OPTIMIZED | CO_NEWLOCALS | CO_NOFREE | CO_FUTURE_ANNOTATIONS)
                    [Names]
                        'available'
                        '_core_unavailable'
                        'core'
                        'get_response_memory_context'
                        '_json_safe'
                        'Exception'
                        'str'
                    [Var Names]
                        'self'
                        'message'
                        'payload'
                        'exc'
                    [Free Vars]
                    [Cell Vars]
                    [Constants]
                        None
                        True
                        (
                            'ok'
                            'context'
                        )
                        False
                        'E_CONTEXT_FAILED'
                        (
                            'ok'
                            'error'
                            'error_code'
                        )
                    [Disassembly]
                        0       LOAD_FAST                       0: self
                        2       LOAD_METHOD                     0: available
                        4       CALL_METHOD                     0
                        6       POP_JUMP_IF_TRUE                16
                        8       LOAD_FAST                       0: self
                        10      LOAD_METHOD                     1: _core_unavailable
                        12      CALL_METHOD                     0
                        14      RETURN_VALUE                    
                        16      SETUP_FINALLY                   30 (to 48)
                        18      LOAD_FAST                       0: self
                        20      LOAD_ATTR                       2: core
                        22      LOAD_METHOD                     3: get_response_memory_context
                        24      LOAD_FAST                       1: message
                        26      CALL_METHOD                     1
                        28      STORE_FAST                      2: payload
                        30      LOAD_CONST                      1: True
                        32      LOAD_FAST                       0: self
                        34      LOAD_METHOD                     4: _json_safe
                        36      LOAD_FAST                       2: payload
                        38      CALL_METHOD                     1
                        40      LOAD_CONST                      2: ('ok', 'context')
                        42      BUILD_CONST_KEY_MAP             2
                        44      POP_BLOCK                       
                        46      RETURN_VALUE                    
                        48      DUP_TOP                         
                        50      LOAD_GLOBAL                     5: Exception
                        52      JUMP_IF_NOT_EXC_MATCH           98
                        54      POP_TOP                         
                        56      STORE_FAST                      3: exc
                        58      POP_TOP                         
                        60      SETUP_FINALLY                   28 (to 90)
                        62      LOAD_CONST                      3: False
                        64      LOAD_GLOBAL                     6: str
                        66      LOAD_FAST                       3: exc
                        68      CALL_FUNCTION                   1
                        70      LOAD_CONST                      4: 'E_CONTEXT_FAILED'
                        72      LOAD_CONST                      5: ('ok', 'error', 'error_code')
                        74      BUILD_CONST_KEY_MAP             3
                        76      POP_BLOCK                       
                        78      ROT_FOUR                        
                        80      POP_EXCEPT                      
                        82      LOAD_CONST                      0: None
                        84      STORE_FAST                      3: exc
                        86      DELETE_FAST                     3: exc
                        88      RETURN_VALUE                    
                        90      LOAD_CONST                      0: None
                        92      STORE_FAST                      3: exc
                        94      DELETE_FAST                     3: exc
                        96      RERAISE                         
                        98      RERAISE                         
                        100     LOAD_CONST                      0: None
                        102     RETURN_VALUE                    
                'MemoryServiceInterface.context'
                [Code]
                    File Name: /Users/s/openclaw-memory-auto/mcp_server/memory_service_interface.py
                    Object Name: status
                    Arg Count: 1
                    Pos Only Arg Count: 0
                    KW Only Arg Count: 0
                    Locals: 3
                    Stack Size: 10
                    Flags: 0x01000043 (CO_OPTIMIZED | CO_NEWLOCALS | CO_NOFREE | CO_FUTURE_ANNOTATIONS)
                    [Names]
                        'available'
                        '_core_unavailable'
                        'hasattr'
                        'core'
                        'get_monitoring_status'
                        'config'
                        'get'
                        'datetime'
                        'utcnow'
                        'isoformat'
                        '_json_safe'
                        'Exception'
                        'str'
                    [Var Names]
                        'self'
                        'health'
                        'exc'
                    [Free Vars]
                    [Cell Vars]
                    [Constants]
                        None
                        'get_monitoring_status'
                        True
                        'server'
                        'name'
                        'openclaw-memory'
                        (
                            'ok'
                            'server'
                            'time'
                            'health'
                        )
                        False
                        'E_STATUS_FAILED'
                        (
                            'ok'
                            'error'
                            'error_code'
                        )
                    [Disassembly]
                        0       LOAD_FAST                       0: self
                        2       LOAD_METHOD                     0: available
                        4       CALL_METHOD                     0
                        6       POP_JUMP_IF_TRUE                16
                        8       LOAD_FAST                       0: self
                        10      LOAD_METHOD                     1: _core_unavailable
                        12      CALL_METHOD                     0
                        14      RETURN_VALUE                    
                        16      SETUP_FINALLY                   74 (to 92)
                        18      LOAD_GLOBAL                     2: hasattr
                        20      LOAD_FAST                       0: self
                        22      LOAD_ATTR                       3: core
                        24      LOAD_CONST                      1: 'get_monitoring_status'
                        26      CALL_FUNCTION                   2
                        28      POP_JUMP_IF_FALSE               40
                        30      LOAD_FAST                       0: self
                        32      LOAD_ATTR                       3: core
                        34      LOAD_METHOD                     4: get_monitoring_status
                        36      CALL_METHOD                     0
                        38      JUMP_FORWARD                    2 (to 42)
                        40      BUILD_MAP                       0
                        42      STORE_FAST                      1: health
                        44      LOAD_CONST                      2: True
                        46      LOAD_FAST                       0: self
                        48      LOAD_ATTR                       5: config
                        50      LOAD_METHOD                     6: get
                        52      LOAD_CONST                      3: 'server'
                        54      BUILD_MAP                       0
                        56      CALL_METHOD                     2
                        58      LOAD_METHOD                     6: get
                        60      LOAD_CONST                      4: 'name'
                        62      LOAD_CONST                      5: 'openclaw-memory'
                        64      CALL_METHOD                     2
                        66      LOAD_GLOBAL                     7: datetime
                        68      LOAD_METHOD                     8: utcnow
                        70      CALL_METHOD                     0
                        72      LOAD_METHOD                     9: isoformat
                        74      CALL_METHOD                     0
                        76      LOAD_FAST                       0: self
                        78      LOAD_METHOD                     10: _json_safe
                        80      LOAD_FAST                       1: health
                        82      CALL_METHOD                     1
                        84      LOAD_CONST                      6: ('ok', 'server', 'time', 'health')
                        86      BUILD_CONST_KEY_MAP             4
                        88      POP_BLOCK                       
                        90      RETURN_VALUE                    
                        92      DUP_TOP                         
                        94      LOAD_GLOBAL                     11: Exception
                        96      JUMP_IF_NOT_EXC_MATCH           142
                        98      POP_TOP                         
                        100     STORE_FAST                      2: exc
                        102     POP_TOP                         
                        104     SETUP_FINALLY                   28 (to 134)
                        106     LOAD_CONST                      7: False
                        108     LOAD_GLOBAL                     12: str
                        110     LOAD_FAST                       2: exc
                        112     CALL_FUNCTION                   1
                        114     LOAD_CONST                      8: 'E_STATUS_FAILED'
                        116     LOAD_CONST                      9: ('ok', 'error', 'error_code')
                        118     BUILD_CONST_KEY_MAP             3
                        120     POP_BLOCK                       
                        122     ROT_FOUR                        
                        124     POP_EXCEPT                      
                        126     LOAD_CONST                      0: None
                        128     STORE_FAST                      2: exc
                        130     DELETE_FAST                     2: exc
                        132     RETURN_VALUE                    
                        134     LOAD_CONST                      0: None
                        136     STORE_FAST                      2: exc
                        138     DELETE_FAST                     2: exc
                        140     RERAISE                         
                        142     RERAISE                         
                        144     LOAD_CONST                      0: None
                        146     RETURN_VALUE                    
                'MemoryServiceInterface.status'
                (
                    'resource_key'
                    'return'
                )
                [Code]
                    File Name: /Users/s/openclaw-memory-auto/mcp_server/memory_service_interface.py
                    Object Name: profile
                    Arg Count: 2
                    Pos Only Arg Count: 0
                    KW Only Arg Count: 0
                    Locals: 12
                    Stack Size: 9
                    Flags: 0x01000043 (CO_OPTIMIZED | CO_NEWLOCALS | CO_NOFREE | CO_FUTURE_ANNOTATIONS)
                    [Names]
                        'workspace'
                        'exists'
                        '_profile_error'
                        'ERR_PROFILE_NOT_FOUND'
                        '_resource_int'
                        'read_text'
                        '_profile_ok'
                        'json'
                        'loads'
                        'Exception'
                        'ERR_PROFILE_PARSE'
                        'dumps'
                        'get'
                        'datetime'
                        'utcnow'
                        'timedelta'
                        'sorted'
                        'glob'
                        'strptime'
                        'stem'
                        'append'
                        'name'
                        'join'
                        'ERR_PROFILE_UNKNOWN'
                    [Var Names]
                        'self'
                        'resource_key'
                        'p'
                        'tail_chars'
                        'content'
                        'obj'
                        'base'
                        'recent_days'
                        'item_chars'
                        'start'
                        'parts'
                        'd'
                    [Free Vars]
                    [Cell Vars]
                    [Constants]
                        None
                        'long-term'
                        'MEMORY.md'
                        'MEMORY.md not found'
                        'long_term_tail_chars'
                        12000
                        'utf-8'
                        'ignore'
                        (
                            'encoding'
                            'errors'
                        )
                        (
                            'path'
                        )
                        'profile'
                        'memory'
                        'memory_blocks.json'
                        'profile not found'
                        (
                            'encoding'
                        )
                        'profile parse failed'
                        'human'
                        ''
                        'persona'
                        (
                            'human'
                            'persona'
                        )
                        False
                        2
                        (
                            'ensure_ascii'
                            'indent'
                        )
                        'recent'
                        'recent_days'
                        3
                        'recent_item_chars'
                        4000
                        (
                            'days'
                        )
                        '*.md'
                        '%Y-%m-%d'
                        '# '
                        '\n'
                        'no recent logs'
                        '\n\n'
                        'unknown_resource'
                    [Disassembly]
                        0       LOAD_FAST                       1: resource_key
                        2       LOAD_CONST                      1: 'long-term'
                        4       COMPARE_OP                      2 (==)
                        6       POP_JUMP_IF_FALSE               92
                        8       LOAD_FAST                       0: self
                        10      LOAD_ATTR                       0: workspace
                        12      LOAD_CONST                      2: 'MEMORY.md'
                        14      BINARY_TRUE_DIVIDE              
                        16      STORE_FAST                      2: p
                        18      LOAD_FAST                       2: p
                        20      LOAD_METHOD                     1: exists
                        22      CALL_METHOD                     0
                        24      POP_JUMP_IF_TRUE                40
                        26      LOAD_FAST                       0: self
                        28      LOAD_METHOD                     2: _profile_error
                        30      LOAD_FAST                       1: resource_key
                        32      LOAD_CONST                      3: 'MEMORY.md not found'
                        34      LOAD_GLOBAL                     3: ERR_PROFILE_NOT_FOUND
                        36      CALL_METHOD                     3
                        38      RETURN_VALUE                    
                        40      LOAD_FAST                       0: self
                        42      LOAD_METHOD                     4: _resource_int
                        44      LOAD_CONST                      4: 'long_term_tail_chars'
                        46      LOAD_CONST                      5: 12000
                        48      CALL_METHOD                     2
                        50      STORE_FAST                      3: tail_chars
                        52      LOAD_FAST                       2: p
                        54      LOAD_ATTR                       5: read_text
                        56      LOAD_CONST                      6: 'utf-8'
                        58      LOAD_CONST                      7: 'ignore'
                        60      LOAD_CONST                      8: ('encoding', 'errors')
                        62      CALL_FUNCTION_KW                2
                        64      LOAD_FAST                       3: tail_chars
                        66      UNARY_NEGATIVE                  
                        68      LOAD_CONST                      0: None
                        70      BUILD_SLICE                     2
                        72      BINARY_SUBSCR                   
                        74      STORE_FAST                      4: content
                        76      LOAD_FAST                       0: self
                        78      LOAD_ATTR                       6: _profile_ok
                        80      LOAD_FAST                       1: resource_key
                        82      LOAD_FAST                       4: content
                        84      LOAD_FAST                       2: p
                        86      LOAD_CONST                      9: ('path',)
                        88      CALL_FUNCTION_KW                3
                        90      RETURN_VALUE                    
                        92      LOAD_FAST                       1: resource_key
                        94      LOAD_CONST                      10: 'profile'
                        96      COMPARE_OP                      2 (==)
                        98      POP_JUMP_IF_FALSE               246
                        100     LOAD_FAST                       0: self
                        102     LOAD_ATTR                       0: workspace
                        104     LOAD_CONST                      11: 'memory'
                        106     BINARY_TRUE_DIVIDE              
                        108     LOAD_CONST                      12: 'memory_blocks.json'
                        110     BINARY_TRUE_DIVIDE              
                        112     STORE_FAST                      2: p
                        114     LOAD_FAST                       2: p
                        116     LOAD_METHOD                     1: exists
                        118     CALL_METHOD                     0
                        120     POP_JUMP_IF_TRUE                136
                        122     LOAD_FAST                       0: self
                        124     LOAD_METHOD                     2: _profile_error
                        126     LOAD_FAST                       1: resource_key
                        128     LOAD_CONST                      13: 'profile not found'
                        130     LOAD_GLOBAL                     3: ERR_PROFILE_NOT_FOUND
                        132     CALL_METHOD                     3
                        134     RETURN_VALUE                    
                        136     SETUP_FINALLY                   22 (to 160)
                        138     LOAD_GLOBAL                     7: json
                        140     LOAD_METHOD                     8: loads
                        142     LOAD_FAST                       2: p
                        144     LOAD_ATTR                       5: read_text
                        146     LOAD_CONST                      6: 'utf-8'
                        148     LOAD_CONST                      14: ('encoding',)
                        150     CALL_FUNCTION_KW                1
                        152     CALL_METHOD                     1
                        154     STORE_FAST                      5: obj
                        156     POP_BLOCK                       
                        158     JUMP_FORWARD                    32 (to 192)
                        160     DUP_TOP                         
                        162     LOAD_GLOBAL                     9: Exception
                        164     JUMP_IF_NOT_EXC_MATCH           190
                        166     POP_TOP                         
                        168     POP_TOP                         
                        170     POP_TOP                         
                        172     LOAD_FAST                       0: self
                        174     LOAD_METHOD                     2: _profile_error
                        176     LOAD_FAST                       1: resource_key
                        178     LOAD_CONST                      15: 'profile parse failed'
                        180     LOAD_GLOBAL                     10: ERR_PROFILE_PARSE
                        182     CALL_METHOD                     3
                        184     ROT_FOUR                        
                        186     POP_EXCEPT                      
                        188     RETURN_VALUE                    
                        190     RERAISE                         
                        192     LOAD_GLOBAL                     7: json
                        194     LOAD_ATTR                       11: dumps
                        196     LOAD_FAST                       5: obj
                        198     LOAD_METHOD                     12: get
                        200     LOAD_CONST                      16: 'human'
                        202     LOAD_CONST                      17: ''
                        204     CALL_METHOD                     2
                        206     LOAD_FAST                       5: obj
                        208     LOAD_METHOD                     12: get
                        210     LOAD_CONST                      18: 'persona'
                        212     LOAD_CONST                      17: ''
                        214     CALL_METHOD                     2
                        216     LOAD_CONST                      19: ('human', 'persona')
                        218     BUILD_CONST_KEY_MAP             2
                        220     LOAD_CONST                      20: False
                        222     LOAD_CONST                      21: 2
                        224     LOAD_CONST                      22: ('ensure_ascii', 'indent')
                        226     CALL_FUNCTION_KW                3
                        228     STORE_FAST                      4: content
                        230     LOAD_FAST                       0: self
                        232     LOAD_ATTR                       6: _profile_ok
                        234     LOAD_FAST                       1: resource_key
                        236     LOAD_FAST                       4: content
                        238     LOAD_FAST                       2: p
                        240     LOAD_CONST                      9: ('path',)
                        242     CALL_FUNCTION_KW                3
                        244     RETURN_VALUE                    
                        246     LOAD_FAST                       1: resource_key
                        248     LOAD_CONST                      23: 'recent'
                        250     COMPARE_OP                      2 (==)
                        252     POP_JUMP_IF_FALSE               480
                        256     LOAD_FAST                       0: self
                        258     LOAD_ATTR                       0: workspace
                        260     LOAD_CONST                      11: 'memory'
                        262     BINARY_TRUE_DIVIDE              
                        264     STORE_FAST                      6: base
                        266     LOAD_FAST                       0: self
                        268     LOAD_METHOD                     4: _resource_int
                        270     LOAD_CONST                      24: 'recent_days'
                        272     LOAD_CONST                      25: 3
                        274     CALL_METHOD                     2
                        276     STORE_FAST                      7: recent_days
                        278     LOAD_FAST                       0: self
                        280     LOAD_METHOD                     4: _resource_int
                        282     LOAD_CONST                      26: 'recent_item_chars'
                        284     LOAD_CONST                      27: 4000
                        286     CALL_METHOD                     2
                        288     STORE_FAST                      8: item_chars
                        290     LOAD_GLOBAL                     13: datetime
                        292     LOAD_METHOD                     14: utcnow
                        294     CALL_METHOD                     0
                        296     LOAD_GLOBAL                     15: timedelta
                        298     LOAD_FAST                       7: recent_days
                        300     LOAD_CONST                      28: ('days',)
                        302     CALL_FUNCTION_KW                1
                        304     BINARY_SUBTRACT                 
                        306     STORE_FAST                      9: start
                        308     BUILD_LIST                      0
                        310     STORE_FAST                      10: parts
                        312     LOAD_GLOBAL                     16: sorted
                        314     LOAD_FAST                       6: base
                        316     LOAD_METHOD                     17: glob
                        318     LOAD_CONST                      29: '*.md'
                        320     CALL_METHOD                     1
                        322     CALL_FUNCTION                   1
                        324     GET_ITER                        
                        326     FOR_ITER                        108 (to 436)
                        328     STORE_FAST                      2: p
                        330     SETUP_FINALLY                   18 (to 350)
                        332     LOAD_GLOBAL                     13: datetime
                        334     LOAD_METHOD                     18: strptime
                        336     LOAD_FAST                       2: p
                        338     LOAD_ATTR                       19: stem
                        340     LOAD_CONST                      30: '%Y-%m-%d'
                        342     CALL_METHOD                     2
                        344     STORE_FAST                      11: d
                        346     POP_BLOCK                       
                        348     JUMP_FORWARD                    26 (to 376)
                        350     DUP_TOP                         
                        352     LOAD_GLOBAL                     9: Exception
                        354     JUMP_IF_NOT_EXC_MATCH           374
                        358     POP_TOP                         
                        360     POP_TOP                         
                        362     POP_TOP                         
                        364     POP_EXCEPT                      
                        366     JUMP_ABSOLUTE                   326
                        370     POP_EXCEPT                      
                        372     JUMP_FORWARD                    2 (to 376)
                        374     RERAISE                         
                        376     LOAD_FAST                       11: d
                        378     LOAD_FAST                       9: start
                        380     COMPARE_OP                      0 (<)
                        382     POP_JUMP_IF_FALSE               390
                        386     JUMP_ABSOLUTE                   326
                        390     LOAD_FAST                       10: parts
                        392     LOAD_METHOD                     20: append
                        394     LOAD_CONST                      31: '# '
                        396     LOAD_FAST                       2: p
                        398     LOAD_ATTR                       21: name
                        400     FORMAT_VALUE                    0 (FVC_NONE)
                        402     LOAD_CONST                      32: '\n'
                        404     BUILD_STRING                    3
                        406     LOAD_FAST                       2: p
                        408     LOAD_ATTR                       5: read_text
                        410     LOAD_CONST                      6: 'utf-8'
                        412     LOAD_CONST                      7: 'ignore'
                        414     LOAD_CONST                      8: ('encoding', 'errors')
                        416     CALL_FUNCTION_KW                2
                        418     LOAD_CONST                      0: None
                        420     LOAD_FAST                       8: item_chars
                        422     BUILD_SLICE                     2
                        424     BINARY_SUBSCR                   
                        426     BINARY_ADD                      
                        428     CALL_METHOD                     1
                        430     POP_TOP                         
                        432     JUMP_ABSOLUTE                   326
                        436     LOAD_FAST                       10: parts
                        438     POP_JUMP_IF_TRUE                458
                        442     LOAD_FAST                       0: self
                        444     LOAD_ATTR                       6: _profile_ok
                        446     LOAD_FAST                       1: resource_key
                        448     LOAD_CONST                      33: 'no recent logs'
                        450     LOAD_FAST                       6: base
                        452     LOAD_CONST                      9: ('path',)
                        454     CALL_FUNCTION_KW                3
                        456     RETURN_VALUE                    
                        458     LOAD_FAST                       0: self
                        460     LOAD_ATTR                       6: _profile_ok
                        462     LOAD_FAST                       1: resource_key
                        464     LOAD_CONST                      34: '\n\n'
                        466     LOAD_METHOD                     22: join
                        468     LOAD_FAST                       10: parts
                        470     CALL_METHOD                     1
                        472     LOAD_FAST                       6: base
                        474     LOAD_CONST                      9: ('path',)
                        476     CALL_FUNCTION_KW                3
                        478     RETURN_VALUE                    
                        480     LOAD_FAST                       0: self
                        482     LOAD_METHOD                     2: _profile_error
                        484     LOAD_FAST                       1: resource_key
                        486     LOAD_CONST                      35: 'unknown_resource'
                        488     LOAD_GLOBAL                     23: ERR_PROFILE_UNKNOWN
                        490     CALL_METHOD                     3
                        492     RETURN_VALUE                    
                'MemoryServiceInterface.profile'
                [Code]
                    File Name: /Users/s/openclaw-memory-auto/mcp_server/memory_service_interface.py
                    Object Name: _core_unavailable
                    Arg Count: 1
                    Pos Only Arg Count: 0
                    KW Only Arg Count: 0
                    Locals: 1
                    Stack Size: 4
                    Flags: 0x01000043 (CO_OPTIMIZED | CO_NEWLOCALS | CO_NOFREE | CO_FUTURE_ANNOTATIONS)
                    [Names]
                        'core_error'
                        'ERR_CORE_UNAVAILABLE'
                    [Var Names]
                        'self'
                    [Free Vars]
                    [Cell Vars]
                    [Constants]
                        None
                        False
                        'MemoryCore unavailable: '
                        (
                            'ok'
                            'error'
                            'error_code'
                        )
                    [Disassembly]
                        0       LOAD_CONST                      1: False
                        2       LOAD_CONST                      2: 'MemoryCore unavailable: '
                        4       LOAD_FAST                       0: self
                        6       LOAD_ATTR                       0: core_error
                        8       FORMAT_VALUE                    0 (FVC_NONE)
                        10      BUILD_STRING                    2
                        12      LOAD_GLOBAL                     1: ERR_CORE_UNAVAILABLE
                        14      LOAD_CONST                      3: ('ok', 'error', 'error_code')
                        16      BUILD_CONST_KEY_MAP             3
                        18      RETURN_VALUE                    
                'MemoryServiceInterface._core_unavailable'
                (
                    'key'
                    'default'
                    'return'
                )
                [Code]
                    File Name: /Users/s/openclaw-memory-auto/mcp_server/memory_service_interface.py
                    Object Name: _resource_int
                    Arg Count: 3
                    Pos Only Arg Count: 0
                    KW Only Arg Count: 0
                    Locals: 5
                    Stack Size: 8
                    Flags: 0x01000043 (CO_OPTIMIZED | CO_NEWLOCALS | CO_NOFREE | CO_FUTURE_ANNOTATIONS)
                    [Names]
                        'profile_cfg'
                        'get'
                        'int'
                        'Exception'
                    [Var Names]
                        'self'
                        'key'
                        'default'
                        'raw'
                        'value'
                    [Free Vars]
                    [Cell Vars]
                    [Constants]
                        None
                        0
                    [Disassembly]
                        0       LOAD_FAST                       0: self
                        2       LOAD_ATTR                       0: profile_cfg
                        4       LOAD_METHOD                     1: get
                        6       LOAD_FAST                       1: key
                        8       LOAD_FAST                       2: default
                        10      CALL_METHOD                     2
                        12      STORE_FAST                      3: raw
                        14      SETUP_FINALLY                   26 (to 42)
                        16      LOAD_GLOBAL                     2: int
                        18      LOAD_FAST                       3: raw
                        20      CALL_FUNCTION                   1
                        22      STORE_FAST                      4: value
                        24      LOAD_FAST                       4: value
                        26      LOAD_CONST                      1: 0
                        28      COMPARE_OP                      4 (>)
                        30      POP_JUMP_IF_FALSE               36
                        32      LOAD_FAST                       4: value
                        34      JUMP_FORWARD                    2 (to 38)
                        36      LOAD_FAST                       2: default
                        38      POP_BLOCK                       
                        40      RETURN_VALUE                    
                        42      DUP_TOP                         
                        44      LOAD_GLOBAL                     3: Exception
                        46      JUMP_IF_NOT_EXC_MATCH           62
                        48      POP_TOP                         
                        50      POP_TOP                         
                        52      POP_TOP                         
                        54      LOAD_FAST                       2: default
                        56      ROT_FOUR                        
                        58      POP_EXCEPT                      
                        60      RETURN_VALUE                    
                        62      RERAISE                         
                        64      LOAD_CONST                      0: None
                        66      RETURN_VALUE                    
                'MemoryServiceInterface._resource_int'
                'Path'
                (
                    'resource_key'
                    'content'
                    'path'
                    'return'
                )
                [Code]
                    File Name: /Users/s/openclaw-memory-auto/mcp_server/memory_service_interface.py
                    Object Name: _profile_ok
                    Arg Count: 4
                    Pos Only Arg Count: 0
                    KW Only Arg Count: 0
                    Locals: 4
                    Stack Size: 5
                    Flags: 0x01000043 (CO_OPTIMIZED | CO_NEWLOCALS | CO_NOFREE | CO_FUTURE_ANNOTATIONS)
                    [Names]
                        'str'
                    [Var Names]
                        'self'
                        'resource_key'
                        'content'
                        'path'
                    [Free Vars]
                    [Cell Vars]
                    [Constants]
                        None
                        True
                        (
                            'ok'
                            'resource'
                            'content'
                            'path'
                        )
                    [Disassembly]
                        0       LOAD_CONST                      1: True
                        2       LOAD_FAST                       1: resource_key
                        4       LOAD_FAST                       2: content
                        6       LOAD_GLOBAL                     0: str
                        8       LOAD_FAST                       3: path
                        10      CALL_FUNCTION                   1
                        12      LOAD_CONST                      2: ('ok', 'resource', 'content', 'path')
                        14      BUILD_CONST_KEY_MAP             4
                        16      RETURN_VALUE                    
                'MemoryServiceInterface._profile_ok'
                (
                    'resource_key'
                    'error'
                    'error_code'
                    'return'
                )
                [Code]
                    File Name: /Users/s/openclaw-memory-auto/mcp_server/memory_service_interface.py
                    Object Name: _profile_error
                    Arg Count: 4
                    Pos Only Arg Count: 0
                    KW Only Arg Count: 0
                    Locals: 4
                    Stack Size: 6
                    Flags: 0x01000043 (CO_OPTIMIZED | CO_NEWLOCALS | CO_NOFREE | CO_FUTURE_ANNOTATIONS)
                    [Names]
                    [Var Names]
                        'self'
                        'resource_key'
                        'error'
                        'error_code'
                    [Free Vars]
                    [Cell Vars]
                    [Constants]
                        None
                        False
                        (
                            'ok'
                            'resource'
                            'error'
                            'error_code'
                            'content'
                        )
                    [Disassembly]
                        0       LOAD_CONST                      1: False
                        2       LOAD_FAST                       1: resource_key
                        4       LOAD_FAST                       2: error
                        6       LOAD_FAST                       3: error_code
                        8       LOAD_FAST                       2: error
                        10      LOAD_CONST                      2: ('ok', 'resource', 'error', 'error_code', 'content')
                        12      BUILD_CONST_KEY_MAP             5
                        14      RETURN_VALUE                    
                'MemoryServiceInterface._profile_error'
                (
                    'raw'
                    'return'
                )
                [Code]
                    File Name: /Users/s/openclaw-memory-auto/mcp_server/memory_service_interface.py
                    Object Name: _normalize_submit_result
                    Arg Count: 2
                    Pos Only Arg Count: 0
                    KW Only Arg Count: 0
                    Locals: 13
                    Stack Size: 7
                    Flags: 0x01000043 (CO_OPTIMIZED | CO_NEWLOCALS | CO_NOFREE | CO_FUTURE_ANNOTATIONS)
                    [Names]
                        'isinstance'
                        'list'
                        'dict'
                        'get'
                        'str'
                        'append'
                        '_json_safe'
                        '_normalize_result_row'
                    [Var Names]
                        'self'
                        'raw'
                        'items'
                        'normalized_items'
                        'accepted_count'
                        'review_count'
                        'rejected_count'
                        'saved_any'
                        'item'
                        'row'
                        'result'
                        'record'
                        'status'
                    [Free Vars]
                    [Cell Vars]
                    [Constants]
                        None
                        0
                        False
                        'result'
                        'record'
                        'status'
                        ''
                        frozenset({
                            'saved'
                            'success'
                            'accepted'
                        })
                        1
                        True
                        frozenset({
                            'pending_review'
                            'saved_review'
                            'queued_review'
                            'redacted_accept'
                        })
                        (
                            'result'
                            'record'
                            'status'
                        )
                        (
                            'items'
                            'accepted_count'
                            'review_count'
                            'rejected_count'
                            'saved_any'
                        )
                    [Disassembly]
                        0       LOAD_GLOBAL                     0: isinstance
                        2       LOAD_FAST                       1: raw
                        4       LOAD_GLOBAL                     1: list
                        6       CALL_FUNCTION                   2
                        8       POP_JUMP_IF_FALSE               14
                        10      LOAD_FAST                       1: raw
                        12      JUMP_FORWARD                    2 (to 16)
                        14      BUILD_LIST                      0
                        16      STORE_FAST                      2: items
                        18      BUILD_LIST                      0
                        20      STORE_FAST                      3: normalized_items
                        22      LOAD_CONST                      1: 0
                        24      STORE_FAST                      4: accepted_count
                        26      LOAD_CONST                      1: 0
                        28      STORE_FAST                      5: review_count
                        30      LOAD_CONST                      1: 0
                        32      STORE_FAST                      6: rejected_count
                        34      LOAD_CONST                      2: False
                        36      STORE_FAST                      7: saved_any
                        38      LOAD_FAST                       2: items
                        40      GET_ITER                        
                        42      FOR_ITER                        196 (to 240)
                        44      STORE_FAST                      8: item
                        46      LOAD_GLOBAL                     0: isinstance
                        48      LOAD_FAST                       8: item
                        50      LOAD_GLOBAL                     2: dict
                        52      CALL_FUNCTION                   2
                        54      POP_JUMP_IF_FALSE               60
                        56      LOAD_FAST                       8: item
                        58      JUMP_FORWARD                    2 (to 62)
                        60      BUILD_MAP                       0
                        62      STORE_FAST                      9: row
                        64      LOAD_GLOBAL                     0: isinstance
                        66      LOAD_FAST                       9: row
                        68      LOAD_METHOD                     3: get
                        70      LOAD_CONST                      3: 'result'
                        72      CALL_METHOD                     1
                        74      LOAD_GLOBAL                     2: dict
                        76      CALL_FUNCTION                   2
                        78      POP_JUMP_IF_FALSE               90
                        80      LOAD_FAST                       9: row
                        82      LOAD_METHOD                     3: get
                        84      LOAD_CONST                      3: 'result'
                        86      CALL_METHOD                     1
                        88      JUMP_FORWARD                    2 (to 92)
                        90      BUILD_MAP                       0
                        92      STORE_FAST                      10: result
                        94      LOAD_GLOBAL                     0: isinstance
                        96      LOAD_FAST                       9: row
                        98      LOAD_METHOD                     3: get
                        100     LOAD_CONST                      4: 'record'
                        102     CALL_METHOD                     1
                        104     LOAD_GLOBAL                     2: dict
                        106     CALL_FUNCTION                   2
                        108     POP_JUMP_IF_FALSE               120
                        110     LOAD_FAST                       9: row
                        112     LOAD_METHOD                     3: get
                        114     LOAD_CONST                      4: 'record'
                        116     CALL_METHOD                     1
                        118     JUMP_FORWARD                    2 (to 122)
                        120     BUILD_MAP                       0
                        122     STORE_FAST                      11: record
                        124     LOAD_GLOBAL                     4: str
                        126     LOAD_FAST                       10: result
                        128     LOAD_METHOD                     3: get
                        130     LOAD_CONST                      5: 'status'
                        132     CALL_METHOD                     1
                        134     JUMP_IF_TRUE_OR_POP             148
                        136     LOAD_FAST                       11: record
                        138     LOAD_METHOD                     3: get
                        140     LOAD_CONST                      5: 'status'
                        142     CALL_METHOD                     1
                        144     JUMP_IF_TRUE_OR_POP             148
                        146     LOAD_CONST                      6: ''
                        148     CALL_FUNCTION                   1
                        150     STORE_FAST                      12: status
                        152     LOAD_FAST                       12: status
                        154     LOAD_CONST                      7: frozenset({'saved', 'success', 'accepted'})
                        156     CONTAINS_OP                     0 (in)
                        158     POP_JUMP_IF_FALSE               174
                        160     LOAD_FAST                       4: accepted_count
                        162     LOAD_CONST                      8: 1
                        164     INPLACE_ADD                     
                        166     STORE_FAST                      4: accepted_count
                        168     LOAD_CONST                      9: True
                        170     STORE_FAST                      7: saved_any
                        172     JUMP_FORWARD                    34 (to 208)
                        174     LOAD_FAST                       12: status
                        176     LOAD_CONST                      10: frozenset({'pending_review', 'saved_review', 'queued_review', 'redacted_accept'})
                        178     CONTAINS_OP                     0 (in)
                        180     POP_JUMP_IF_FALSE               196
                        182     LOAD_FAST                       5: review_count
                        184     LOAD_CONST                      8: 1
                        186     INPLACE_ADD                     
                        188     STORE_FAST                      5: review_count
                        190     LOAD_CONST                      9: True
                        192     STORE_FAST                      7: saved_any
                        194     JUMP_FORWARD                    12 (to 208)
                        196     LOAD_FAST                       12: status
                        198     POP_JUMP_IF_FALSE               208
                        200     LOAD_FAST                       6: rejected_count
                        202     LOAD_CONST                      8: 1
                        204     INPLACE_ADD                     
                        206     STORE_FAST                      6: rejected_count
                        208     LOAD_FAST                       3: normalized_items
                        210     LOAD_METHOD                     5: append
                        212     LOAD_FAST                       0: self
                        214     LOAD_METHOD                     6: _json_safe
                        216     LOAD_FAST                       10: result
                        218     CALL_METHOD                     1
                        220     LOAD_FAST                       0: self
                        222     LOAD_METHOD                     7: _normalize_result_row
                        224     LOAD_FAST                       11: record
                        226     CALL_METHOD                     1
                        228     LOAD_FAST                       12: status
                        230     LOAD_CONST                      11: ('result', 'record', 'status')
                        232     BUILD_CONST_KEY_MAP             3
                        234     CALL_METHOD                     1
                        236     POP_TOP                         
                        238     JUMP_ABSOLUTE                   42
                        240     LOAD_FAST                       3: normalized_items
                        242     LOAD_FAST                       4: accepted_count
                        244     LOAD_FAST                       5: review_count
                        246     LOAD_FAST                       6: rejected_count
                        248     LOAD_FAST                       7: saved_any
                        250     LOAD_CONST                      12: ('items', 'accepted_count', 'review_count', 'rejected_count', 'saved_any')
                        252     BUILD_CONST_KEY_MAP             5
                        254     RETURN_VALUE                    
                'MemoryServiceInterface._normalize_submit_result'
                (
                    'row'
                    'return'
                )
                [Code]
                    File Name: /Users/s/openclaw-memory-auto/mcp_server/memory_service_interface.py
                    Object Name: _normalize_result_row
                    Arg Count: 2
                    Pos Only Arg Count: 0
                    KW Only Arg Count: 0
                    Locals: 5
                    Stack Size: 14
                    Flags: 0x01000043 (CO_OPTIMIZED | CO_NEWLOCALS | CO_NOFREE | CO_FUTURE_ANNOTATIONS)
                    [Names]
                        'isinstance'
                        'dict'
                        'get'
                        'str'
                        '_json_safe'
                    [Var Names]
                        'self'
                        'row'
                        'obj'
                        'content'
                        'text'
                    [Free Vars]
                    [Cell Vars]
                    [Constants]
                        None
                        'content'
                        'text'
                        ''
                        'id'
                        'source'
                        'category'
                        'confidence'
                        'date'
                        'status'
                        'knowledge_tier'
                        'trust_level'
                        (
                            'id'
                            'source'
                            'content'
                            'text'
                            'category'
                            'confidence'
                            'date'
                            'status'
                            'knowledge_tier'
                            'trust_level'
                            'raw'
                        )
                    [Disassembly]
                        0       LOAD_GLOBAL                     0: isinstance
                        2       LOAD_FAST                       1: row
                        4       LOAD_GLOBAL                     1: dict
                        6       CALL_FUNCTION                   2
                        8       POP_JUMP_IF_FALSE               14
                        10      LOAD_FAST                       1: row
                        12      JUMP_FORWARD                    2 (to 16)
                        14      BUILD_MAP                       0
                        16      STORE_FAST                      2: obj
                        18      LOAD_FAST                       2: obj
                        20      LOAD_METHOD                     2: get
                        22      LOAD_CONST                      1: 'content'
                        24      CALL_METHOD                     1
                        26      STORE_FAST                      3: content
                        28      LOAD_FAST                       3: content
                        30      LOAD_CONST                      0: None
                        32      IS_OP                           0 (is)
                        34      POP_JUMP_IF_FALSE               46
                        36      LOAD_FAST                       2: obj
                        38      LOAD_METHOD                     2: get
                        40      LOAD_CONST                      2: 'text'
                        42      CALL_METHOD                     1
                        44      STORE_FAST                      3: content
                        46      LOAD_FAST                       3: content
                        48      LOAD_CONST                      0: None
                        50      IS_OP                           0 (is)
                        52      POP_JUMP_IF_FALSE               58
                        54      LOAD_CONST                      3: ''
                        56      JUMP_FORWARD                    6 (to 64)
                        58      LOAD_GLOBAL                     3: str
                        60      LOAD_FAST                       3: content
                        62      CALL_FUNCTION                   1
                        64      STORE_FAST                      4: text
                        66      LOAD_FAST                       2: obj
                        68      LOAD_METHOD                     2: get
                        70      LOAD_CONST                      4: 'id'
                        72      CALL_METHOD                     1
                        74      LOAD_CONST                      0: None
                        76      IS_OP                           1 (is not)
                        78      POP_JUMP_IF_FALSE               96
                        80      LOAD_GLOBAL                     3: str
                        82      LOAD_FAST                       2: obj
                        84      LOAD_METHOD                     2: get
                        86      LOAD_CONST                      4: 'id'
                        88      LOAD_CONST                      3: ''
                        90      CALL_METHOD                     2
                        92      CALL_FUNCTION                   1
                        94      JUMP_FORWARD                    2 (to 98)
                        96      LOAD_CONST                      3: ''
                        98      LOAD_FAST                       2: obj
                        100     LOAD_METHOD                     2: get
                        102     LOAD_CONST                      5: 'source'
                        104     CALL_METHOD                     1
                        106     LOAD_CONST                      0: None
                        108     IS_OP                           1 (is not)
                        110     POP_JUMP_IF_FALSE               128
                        112     LOAD_GLOBAL                     3: str
                        114     LOAD_FAST                       2: obj
                        116     LOAD_METHOD                     2: get
                        118     LOAD_CONST                      5: 'source'
                        120     LOAD_CONST                      3: ''
                        122     CALL_METHOD                     2
                        124     CALL_FUNCTION                   1
                        126     JUMP_FORWARD                    2 (to 130)
                        128     LOAD_CONST                      3: ''
                        130     LOAD_FAST                       4: text
                        132     LOAD_FAST                       4: text
                        134     LOAD_FAST                       2: obj
                        136     LOAD_METHOD                     2: get
                        138     LOAD_CONST                      6: 'category'
                        140     CALL_METHOD                     1
                        142     LOAD_CONST                      0: None
                        144     IS_OP                           1 (is not)
                        146     POP_JUMP_IF_FALSE               164
                        148     LOAD_GLOBAL                     3: str
                        150     LOAD_FAST                       2: obj
                        152     LOAD_METHOD                     2: get
                        154     LOAD_CONST                      6: 'category'
                        156     LOAD_CONST                      3: ''
                        158     CALL_METHOD                     2
                        160     CALL_FUNCTION                   1
                        162     JUMP_FORWARD                    2 (to 166)
                        164     LOAD_CONST                      3: ''
                        166     LOAD_FAST                       2: obj
                        168     LOAD_METHOD                     2: get
                        170     LOAD_CONST                      7: 'confidence'
                        172     LOAD_CONST                      0: None
                        174     CALL_METHOD                     2
                        176     LOAD_FAST                       0: self
                        178     LOAD_METHOD                     4: _json_safe
                        180     LOAD_FAST                       2: obj
                        182     LOAD_METHOD                     2: get
                        184     LOAD_CONST                      8: 'date'
                        186     LOAD_CONST                      3: ''
                        188     CALL_METHOD                     2
                        190     CALL_METHOD                     1
                        192     LOAD_FAST                       2: obj
                        194     LOAD_METHOD                     2: get
                        196     LOAD_CONST                      9: 'status'
                        198     CALL_METHOD                     1
                        200     LOAD_CONST                      0: None
                        202     IS_OP                           1 (is not)
                        204     POP_JUMP_IF_FALSE               222
                        206     LOAD_GLOBAL                     3: str
                        208     LOAD_FAST                       2: obj
                        210     LOAD_METHOD                     2: get
                        212     LOAD_CONST                      9: 'status'
                        214     LOAD_CONST                      3: ''
                        216     CALL_METHOD                     2
                        218     CALL_FUNCTION                   1
                        220     JUMP_FORWARD                    2 (to 224)
                        222     LOAD_CONST                      3: ''
                        224     LOAD_FAST                       2: obj
                        226     LOAD_METHOD                     2: get
                        228     LOAD_CONST                      10: 'knowledge_tier'
                        230     CALL_METHOD                     1
                        232     LOAD_CONST                      0: None
                        234     IS_OP                           1 (is not)
                        236     POP_JUMP_IF_FALSE               254
                        238     LOAD_GLOBAL                     3: str
                        240     LOAD_FAST                       2: obj
                        242     LOAD_METHOD                     2: get
                        244     LOAD_CONST                      10: 'knowledge_tier'
                        246     LOAD_CONST                      3: ''
                        248     CALL_METHOD                     2
                        250     CALL_FUNCTION                   1
                        252     JUMP_FORWARD                    2 (to 256)
                        254     LOAD_CONST                      3: ''
                        256     LOAD_FAST                       2: obj
                        258     LOAD_METHOD                     2: get
                        260     LOAD_CONST                      11: 'trust_level'
                        262     CALL_METHOD                     1
                        264     LOAD_CONST                      0: None
                        266     IS_OP                           1 (is not)
                        268     POP_JUMP_IF_FALSE               288
                        272     LOAD_GLOBAL                     3: str
                        274     LOAD_FAST                       2: obj
                        276     LOAD_METHOD                     2: get
                        278     LOAD_CONST                      11: 'trust_level'
                        280     LOAD_CONST                      3: ''
                        282     CALL_METHOD                     2
                        284     CALL_FUNCTION                   1
                        286     JUMP_FORWARD                    2 (to 290)
                        288     LOAD_CONST                      3: ''
                        290     LOAD_FAST                       0: self
                        292     LOAD_METHOD                     4: _json_safe
                        294     LOAD_FAST                       2: obj
                        296     CALL_METHOD                     1
                        298     LOAD_CONST                      12: ('id', 'source', 'content', 'text', 'category', 'confidence', 'date', 'status', 'knowledge_tier', 'trust_level', 'raw')
                        300     BUILD_CONST_KEY_MAP             11
                        302     RETURN_VALUE                    
                'MemoryServiceInterface._normalize_result_row'
                (
                    'value'
                    'return'
                )
                [Code]
                    File Name: /Users/s/openclaw-memory-auto/mcp_server/memory_service_interface.py
                    Object Name: _json_safe
                    Arg Count: 1
                    Pos Only Arg Count: 0
                    KW Only Arg Count: 0
                    Locals: 1
                    Stack Size: 4
                    Flags: 0x01000043 (CO_OPTIMIZED | CO_NEWLOCALS | CO_NOFREE | CO_FUTURE_ANNOTATIONS)
                    [Names]
                        'isinstance'
                        'dict'
                        'items'
                        'list'
                        'datetime'
                        'date'
                        'isoformat'
                    [Var Names]
                        'value'
                    [Free Vars]
                    [Cell Vars]
                    [Constants]
                        None
                        [Code]
                            File Name: /Users/s/openclaw-memory-auto/mcp_server/memory_service_interface.py
                            Object Name: <dictcomp>
                            Arg Count: 1
                            Pos Only Arg Count: 0
                            KW Only Arg Count: 0
                            Locals: 3
                            Stack Size: 6
                            Flags: 0x01000053 (CO_OPTIMIZED | CO_NEWLOCALS | CO_NESTED | CO_NOFREE | CO_FUTURE_ANNOTATIONS)
                            [Names]
                                'str'
                                'MemoryServiceInterface'
                                '_json_safe'
                            [Var Names]
                                '.0'
                                'k'
                                'v'
                            [Free Vars]
                            [Cell Vars]
                            [Constants]
                            [Disassembly]
                                0       BUILD_MAP                       0
                                2       LOAD_FAST                       0: .0
                                4       FOR_ITER                        24 (to 30)
                                6       UNPACK_SEQUENCE                 2
                                8       STORE_FAST                      1: k
                                10      STORE_FAST                      2: v
                                12      LOAD_GLOBAL                     0: str
                                14      LOAD_FAST                       1: k
                                16      CALL_FUNCTION                   1
                                18      LOAD_GLOBAL                     1: MemoryServiceInterface
                                20      LOAD_METHOD                     2: _json_safe
                                22      LOAD_FAST                       2: v
                                24      CALL_METHOD                     1
                                26      MAP_ADD                         2
                                28      JUMP_ABSOLUTE                   4
                                30      RETURN_VALUE                    
                        'MemoryServiceInterface._json_safe.<locals>.<dictcomp>'
                        [Code]
                            File Name: /Users/s/openclaw-memory-auto/mcp_server/memory_service_interface.py
                            Object Name: <listcomp>
                            Arg Count: 1
                            Pos Only Arg Count: 0
                            KW Only Arg Count: 0
                            Locals: 2
                            Stack Size: 5
                            Flags: 0x01000053 (CO_OPTIMIZED | CO_NEWLOCALS | CO_NESTED | CO_NOFREE | CO_FUTURE_ANNOTATIONS)
                            [Names]
                                'MemoryServiceInterface'
                                '_json_safe'
                            [Var Names]
                                '.0'
                                'v'
                            [Free Vars]
                            [Cell Vars]
                            [Constants]
                            [Disassembly]
                                0       BUILD_LIST                      0
                                2       LOAD_FAST                       0: .0
                                4       FOR_ITER                        14 (to 20)
                                6       STORE_FAST                      1: v
                                8       LOAD_GLOBAL                     0: MemoryServiceInterface
                                10      LOAD_METHOD                     1: _json_safe
                                12      LOAD_FAST                       1: v
                                14      CALL_METHOD                     1
                                16      LIST_APPEND                     2
                                18      JUMP_ABSOLUTE                   4
                                20      RETURN_VALUE                    
                        'MemoryServiceInterface._json_safe.<locals>.<listcomp>'
                    [Disassembly]
                        0       LOAD_GLOBAL                     0: isinstance
                        2       LOAD_FAST                       0: value
                        4       LOAD_GLOBAL                     1: dict
                        6       CALL_FUNCTION                   2
                        8       POP_JUMP_IF_FALSE               28
                        10      LOAD_CONST                      1: <CODE> <dictcomp>
                        12      LOAD_CONST                      2: 'MemoryServiceInterface._json_safe.<locals>.<dictcomp>'
                        14      MAKE_FUNCTION                   0
                        16      LOAD_FAST                       0: value
                        18      LOAD_METHOD                     2: items
                        20      CALL_METHOD                     0
                        22      GET_ITER                        
                        24      CALL_FUNCTION                   1
                        26      RETURN_VALUE                    
                        28      LOAD_GLOBAL                     0: isinstance
                        30      LOAD_FAST                       0: value
                        32      LOAD_GLOBAL                     3: list
                        34      CALL_FUNCTION                   2
                        36      POP_JUMP_IF_FALSE               52
                        38      LOAD_CONST                      3: <CODE> <listcomp>
                        40      LOAD_CONST                      4: 'MemoryServiceInterface._json_safe.<locals>.<listcomp>'
                        42      MAKE_FUNCTION                   0
                        44      LOAD_FAST                       0: value
                        46      GET_ITER                        
                        48      CALL_FUNCTION                   1
                        50      RETURN_VALUE                    
                        52      LOAD_GLOBAL                     0: isinstance
                        54      LOAD_FAST                       0: value
                        56      LOAD_GLOBAL                     4: datetime
                        58      LOAD_GLOBAL                     5: date
                        60      BUILD_TUPLE                     2
                        62      CALL_FUNCTION                   2
                        64      POP_JUMP_IF_FALSE               74
                        66      LOAD_FAST                       0: value
                        68      LOAD_METHOD                     6: isoformat
                        70      CALL_METHOD                     0
                        72      RETURN_VALUE                    
                        74      LOAD_FAST                       0: value
                        76      RETURN_VALUE                    
                'MemoryServiceInterface._json_safe'
                (
                    'p'
                    'return'
                )
                [Code]
                    File Name: /Users/s/openclaw-memory-auto/mcp_server/memory_service_interface.py
                    Object Name: _expand
                    Arg Count: 1
                    Pos Only Arg Count: 0
                    KW Only Arg Count: 0
                    Locals: 1
                    Stack Size: 2
                    Flags: 0x01000043 (CO_OPTIMIZED | CO_NEWLOCALS | CO_NOFREE | CO_FUTURE_ANNOTATIONS)
                    [Names]
                        'Path'
                        'expanduser'
                        'resolve'
                    [Var Names]
                        'p'
                    [Free Vars]
                    [Cell Vars]
                    [Constants]
                        None
                    [Disassembly]
                        0       LOAD_GLOBAL                     0: Path
                        2       LOAD_FAST                       0: p
                        4       CALL_FUNCTION                   1
                        6       LOAD_METHOD                     1: expanduser
                        8       CALL_METHOD                     0
                        10      LOAD_METHOD                     2: resolve
                        12      CALL_METHOD                     0
                        14      RETURN_VALUE                    
                'MemoryServiceInterface._expand'
                (
                    None
                )
                (
                    5
                )
            [Disassembly]
                0       LOAD_NAME                       0: __name__
                2       STORE_NAME                      1: __module__
                4       LOAD_CONST                      0: 'MemoryServiceInterface'
                6       STORE_NAME                      2: __qualname__
                8       LOAD_CONST                      1: 'Thin service boundary between server/adapter and memory engine.'
                10      STORE_NAME                      3: __doc__
                12      LOAD_CONST                      60: (None,)
                14      LOAD_CONST                      3: 'Any'
                16      LOAD_CONST                      4: 'Dict[str, Any]'
                18      LOAD_CONST                      5: 'Optional[str]'
                20      LOAD_CONST                      6: 'None'
                22      LOAD_CONST                      7: ('core', 'config', 'core_error', 'return')
                24      BUILD_CONST_KEY_MAP             4
                26      LOAD_CONST                      8: <CODE> __init__
                28      LOAD_CONST                      9: 'MemoryServiceInterface.__init__'
                30      MAKE_FUNCTION                   5
                32      STORE_NAME                      4: __init__
                34      LOAD_NAME                       5: classmethod
                36      LOAD_CONST                      4: 'Dict[str, Any]'
                38      LOAD_CONST                      10: "'MemoryServiceInterface'"
                40      LOAD_CONST                      11: ('config', 'return')
                42      BUILD_CONST_KEY_MAP             2
                44      LOAD_CONST                      12: <CODE> from_config
                46      LOAD_CONST                      13: 'MemoryServiceInterface.from_config'
                48      MAKE_FUNCTION                   4
                50      CALL_FUNCTION                   1
                52      STORE_NAME                      6: from_config
                54      LOAD_CONST                      14: 'bool'
                56      LOAD_CONST                      15: ('return',)
                58      BUILD_CONST_KEY_MAP             1
                60      LOAD_CONST                      16: <CODE> available
                62      LOAD_CONST                      17: 'MemoryServiceInterface.available'
                64      MAKE_FUNCTION                   4
                66      STORE_NAME                      7: available
                68      LOAD_CONST                      18: 'MemoryCandidate'
                70      LOAD_CONST                      4: 'Dict[str, Any]'
                72      LOAD_CONST                      19: ('candidate', 'return')
                74      BUILD_CONST_KEY_MAP             2
                76      LOAD_CONST                      20: <CODE> submit
                78      LOAD_CONST                      21: 'MemoryServiceInterface.submit'
                80      MAKE_FUNCTION                   4
                82      STORE_NAME                      8: submit
                84      LOAD_CONST                      61: (5,)
                86      LOAD_CONST                      23: 'str'
                88      LOAD_CONST                      24: 'int'
                90      LOAD_CONST                      4: 'Dict[str, Any]'
                92      LOAD_CONST                      25: ('query', 'top_k', 'return')
                94      BUILD_CONST_KEY_MAP             3
                96      LOAD_CONST                      26: <CODE> query
                98      LOAD_CONST                      27: 'MemoryServiceInterface.query'
                100     MAKE_FUNCTION                   5
                102     STORE_NAME                      9: query
                104     LOAD_CONST                      23: 'str'
                106     LOAD_CONST                      4: 'Dict[str, Any]'
                108     LOAD_CONST                      28: ('message', 'return')
                110     BUILD_CONST_KEY_MAP             2
                112     LOAD_CONST                      29: <CODE> context
                114     LOAD_CONST                      30: 'MemoryServiceInterface.context'
                116     MAKE_FUNCTION                   4
                118     STORE_NAME                      10: context
                120     LOAD_CONST                      4: 'Dict[str, Any]'
                122     LOAD_CONST                      15: ('return',)
                124     BUILD_CONST_KEY_MAP             1
                126     LOAD_CONST                      31: <CODE> status
                128     LOAD_CONST                      32: 'MemoryServiceInterface.status'
                130     MAKE_FUNCTION                   4
                132     STORE_NAME                      11: status
                134     LOAD_CONST                      23: 'str'
                136     LOAD_CONST                      4: 'Dict[str, Any]'
                138     LOAD_CONST                      33: ('resource_key', 'return')
                140     BUILD_CONST_KEY_MAP             2
                142     LOAD_CONST                      34: <CODE> profile
                144     LOAD_CONST                      35: 'MemoryServiceInterface.profile'
                146     MAKE_FUNCTION                   4
                148     STORE_NAME                      12: profile
                150     LOAD_CONST                      4: 'Dict[str, Any]'
                152     LOAD_CONST                      15: ('return',)
                154     BUILD_CONST_KEY_MAP             1
                156     LOAD_CONST                      36: <CODE> _core_unavailable
                158     LOAD_CONST                      37: 'MemoryServiceInterface._core_unavailable'
                160     MAKE_FUNCTION                   4
                162     STORE_NAME                      13: _core_unavailable
                164     LOAD_CONST                      23: 'str'
                166     LOAD_CONST                      24: 'int'
                168     LOAD_CONST                      24: 'int'
                170     LOAD_CONST                      38: ('key', 'default', 'return')
                172     BUILD_CONST_KEY_MAP             3
                174     LOAD_CONST                      39: <CODE> _resource_int
                176     LOAD_CONST                      40: 'MemoryServiceInterface._resource_int'
                178     MAKE_FUNCTION                   4
                180     STORE_NAME                      14: _resource_int
                182     LOAD_CONST                      23: 'str'
                184     LOAD_CONST                      23: 'str'
                186     LOAD_CONST                      41: 'Path'
                188     LOAD_CONST                      4: 'Dict[str, Any]'
                190     LOAD_CONST                      42: ('resource_key', 'content', 'path', 'return')
                192     BUILD_CONST_KEY_MAP             4
                194     LOAD_CONST                      43: <CODE> _profile_ok
                196     LOAD_CONST                      44: 'MemoryServiceInterface._profile_ok'
                198     MAKE_FUNCTION                   4
                200     STORE_NAME                      15: _profile_ok
                202     LOAD_CONST                      23: 'str'
                204     LOAD_CONST                      23: 'str'
                206     LOAD_CONST                      23: 'str'
                208     LOAD_CONST                      4: 'Dict[str, Any]'
                210     LOAD_CONST                      45: ('resource_key', 'error', 'error_code', 'return')
                212     BUILD_CONST_KEY_MAP             4
                214     LOAD_CONST                      46: <CODE> _profile_error
                216     LOAD_CONST                      47: 'MemoryServiceInterface._profile_error'
                218     MAKE_FUNCTION                   4
                220     STORE_NAME                      16: _profile_error
                222     LOAD_CONST                      3: 'Any'
                224     LOAD_CONST                      4: 'Dict[str, Any]'
                226     LOAD_CONST                      48: ('raw', 'return')
                228     BUILD_CONST_KEY_MAP             2
                230     LOAD_CONST                      49: <CODE> _normalize_submit_result
                232     LOAD_CONST                      50: 'MemoryServiceInterface._normalize_submit_result'
                234     MAKE_FUNCTION                   4
                236     STORE_NAME                      17: _normalize_submit_result
                238     LOAD_CONST                      3: 'Any'
                240     LOAD_CONST                      4: 'Dict[str, Any]'
                242     LOAD_CONST                      51: ('row', 'return')
                244     BUILD_CONST_KEY_MAP             2
                246     LOAD_CONST                      52: <CODE> _normalize_result_row
                248     LOAD_CONST                      53: 'MemoryServiceInterface._normalize_result_row'
                250     MAKE_FUNCTION                   4
                252     STORE_NAME                      18: _normalize_result_row
                254     LOAD_NAME                       19: staticmethod
                256     LOAD_CONST                      3: 'Any'
                258     LOAD_CONST                      3: 'Any'
                260     LOAD_CONST                      54: ('value', 'return')
                262     BUILD_CONST_KEY_MAP             2
                264     LOAD_CONST                      55: <CODE> _json_safe
                266     LOAD_CONST                      56: 'MemoryServiceInterface._json_safe'
                268     MAKE_FUNCTION                   4
                270     CALL_FUNCTION                   1
                272     STORE_NAME                      20: _json_safe
                274     LOAD_NAME                       19: staticmethod
                276     LOAD_CONST                      23: 'str'
                278     LOAD_CONST                      41: 'Path'
                280     LOAD_CONST                      57: ('p', 'return')
                282     BUILD_CONST_KEY_MAP             2
                284     LOAD_CONST                      58: <CODE> _expand
                286     LOAD_CONST                      59: 'MemoryServiceInterface._expand'
                288     MAKE_FUNCTION                   4
                290     CALL_FUNCTION                   1
                292     STORE_NAME                      21: _expand
                294     LOAD_CONST                      2: None
                296     RETURN_VALUE                    
        'MemoryServiceInterface'
    [Disassembly]
        0       LOAD_CONST                      0: 0
        2       LOAD_CONST                      1: ('annotations',)
        4       IMPORT_NAME                     0: __future__
        6       IMPORT_FROM                     1: annotations
        8       STORE_NAME                      1: annotations
        10      POP_TOP                         
        12      LOAD_CONST                      0: 0
        14      LOAD_CONST                      2: None
        16      IMPORT_NAME                     2: json
        18      STORE_NAME                      2: json
        20      LOAD_CONST                      0: 0
        22      LOAD_CONST                      2: None
        24      IMPORT_NAME                     3: os
        26      STORE_NAME                      3: os
        28      LOAD_CONST                      0: 0
        30      LOAD_CONST                      2: None
        32      IMPORT_NAME                     4: sys
        34      STORE_NAME                      4: sys
        36      LOAD_CONST                      0: 0
        38      LOAD_CONST                      3: ('date', 'datetime', 'timedelta')
        40      IMPORT_NAME                     5: datetime
        42      IMPORT_FROM                     6: date
        44      STORE_NAME                      6: date
        46      IMPORT_FROM                     5: datetime
        48      STORE_NAME                      5: datetime
        50      IMPORT_FROM                     7: timedelta
        52      STORE_NAME                      7: timedelta
        54      POP_TOP                         
        56      LOAD_CONST                      0: 0
        58      LOAD_CONST                      4: ('Path',)
        60      IMPORT_NAME                     8: pathlib
        62      IMPORT_FROM                     9: Path
        64      STORE_NAME                      9: Path
        66      POP_TOP                         
        68      LOAD_CONST                      0: 0
        70      LOAD_CONST                      5: ('Any', 'Dict', 'List', 'Optional')
        72      IMPORT_NAME                     10: typing
        74      IMPORT_FROM                     11: Any
        76      STORE_NAME                      11: Any
        78      IMPORT_FROM                     12: Dict
        80      STORE_NAME                      12: Dict
        82      IMPORT_FROM                     13: List
        84      STORE_NAME                      13: List
        86      IMPORT_FROM                     14: Optional
        88      STORE_NAME                      14: Optional
        90      POP_TOP                         
        92      LOAD_CONST                      0: 0
        94      LOAD_CONST                      6: ('MemoryCandidate',)
        96      IMPORT_NAME                     15: integration_hooks.service_models
        98      IMPORT_FROM                     16: MemoryCandidate
        100     STORE_NAME                      16: MemoryCandidate
        102     POP_TOP                         
        104     LOAD_CONST                      7: 'E_CORE_UNAVAILABLE'
        106     STORE_NAME                      17: ERR_CORE_UNAVAILABLE
        108     LOAD_CONST                      8: 'E_PROFILE_NOT_FOUND'
        110     STORE_NAME                      18: ERR_PROFILE_NOT_FOUND
        112     LOAD_CONST                      9: 'E_PROFILE_PARSE'
        114     STORE_NAME                      19: ERR_PROFILE_PARSE
        116     LOAD_CONST                      10: 'E_PROFILE_UNKNOWN'
        118     STORE_NAME                      20: ERR_PROFILE_UNKNOWN
        120     LOAD_BUILD_CLASS                
        122     LOAD_CONST                      11: <CODE> MemoryServiceInterface
        124     LOAD_CONST                      12: 'MemoryServiceInterface'
        126     MAKE_FUNCTION                   0
        128     LOAD_CONST                      12: 'MemoryServiceInterface'
        130     CALL_FUNCTION                   2
        132     STORE_NAME                      21: MemoryServiceInterface
        134     LOAD_CONST                      2: None
        136     RETURN_VALUE                    
